Workbook

Sheet A
A3: Etiquetas de fila | B3: Suma de mar-25 | C3: Suma de TOTAL COBROS Y RESERVAS | H3: Etiquetas de fila | I3: Suma de mar-25 | J3: Suma de Total de Cobro Ppto | K3: Suma de TOTAL COBROS Y RESERVAS | L3: Suma de Variación ppto versus cobro real | N3: Etiquetas de fila | O3: Suma de mar-25 | P3: Suma de TOTAL COBROS Y RESERVAS
A4: Cliente Atrasado | B4: 25000 | C4: 1741825.6 | H4: Cliente al día | I4: 15961.42 | J4: 199192.64 | K4: 199192.64 | L4: 0 | N4: Cliente Atrasado | O4: 943639.33 | P4: 14614695
A5: Enganche Completado | B5: 20500 | C5: 3579629 | H5: Cliente atrasado | I5: 15293.08 | J5: 435504.98 | K5: 272644.18 | L5: 162860.8 | N5: Enganche Completado | O5: 29962 | P5: 1202813.2
A6: Superávit de Enganche | B6: 3740366 | C6: 10330693 | H6: Cliente disponible | J6: 0 | K6: 0 | L6: 0 | N6: Disponible | O6: 0 | P6: 0
A7: Disponible | B7: 0 | C7: 0 | H7: Pendiente plan de pagos | J7: 0 | K7: 1500 | L7: -1500 | N7: Superávit de Enganche | O7: 50500 | P7: 1330269
A8: Total general | B8: 3785866 | C8: 15652148 | H8: Superavit de enganche | I8: 15857.17 | J8: 146846.17 | K8: 155646.01 | L8: -8799.84 | N8: Total general | O8: 1024101.3 | P8: 17147777
H9: Total general | I9: 47111.67 | J9: 781543.79 | K9: 628982.83 | L9: 152560.96
A16: En cada tabla colocar el mes que corresponda para poder llevar bien la estadistica

Sheet B
A3: Etiquetas de fila | B3: Cuenta de Apto | C3: Suma de TOTAL COBROS Y RESERVAS | I3: Etiquetas de fila | J3: Suma de feb-25 | K3: Cuenta de Apto | L3: Suma de Total de Cobro Ppto | M3: Suma de TOTAL COBROS Y RESERVAS | N3: Suma de Variación ppto versus cobro real | R3: Etiquetas de fila | S3: Cuenta de Apto | T3: Suma de TOTAL COBROS Y RESERVAS
A4: Cliente Atrasado | B4: 11 | C4: 1741825.6 | I4: Cliente al día | J4: 17160.23 | K4: 11 | L4: 199192.64 | M4: 199192.64 | N4: 0 | R4: Cliente Atrasado | S4: 244 | T4: 14614695
A5: Enganche Completado | B5: 17 | C5: 3579629 | I5: Cliente atrasado | J5: 16376.42 | K5: 26 | L5: 435504.98 | M5: 272644.18 | N5: 162860.8 | R5: Enganche Completado | S5: 4 | T5: 1202813.2
A6: Superávit de Enganche | B6: 46 | C6: 10330693 | I6: Cliente disponible | J6: 0 | K6: 30 | L6: 0 | M6: 0 | N6: 0 | R6: Disponible | S6: 46 | T6: 0
A7: Disponible | B7: 1 | C7: 0 | I7: Pendiente plan de pagos | J7: 1500 | K7: 1 | L7: 0 | M7: 1500 | N7: -1500 | R7: Superávit de Enganche | S7: 4 | T7: 1330269
A8: Total general | B8: 75 | C8: 15652148 | I8: Superavit de enganche | J8: 16773.37 | K8: 10 | L8: 146846.17 | M8: 155646.01 | N8: -8799.84 | R8: Total general | S8: 298 | T8: 17147777
I9: Total general | J9: 51810.02 | K9: 78 | L9: 781543.79 | M9: 628982.83 | N9: 152560.96

Sheet C
A4: Etiquetas de fila | B4: Suma de mar-25 | C4: Suma de Acumulado | F4: Etiquetas de fila | G4: Suma de mar-25 | H4: Suma de Acumulado | K4: Etiquetas de fila | L4: Suma de mar-25 | M4: Suma de b
A5: 0 | C5: 2322161.9 | F5: 0 | G5: 2228.57 | H5: 27742.84 | K5: 0 | L5: 1346050.5 | M5: 18963742
A6: -5000 | C6: 676200 | F6: 459835.32 | G6: 1022.73 | H6: 12750.03 | K6: Total general | L6: 1346050.5 | M6: 18963742
A7: 111875 | C7: 900000 | F7: 463755.6 | G7: 1244.44 | H7: 12699.96
A8: 3520.45 | C8: 770000 | F8: 458927.83 | G8: 1045.45 | H8: 14090.85
A9: 725400 | C9: 80600 | F9: 494900 | H9: 23899.94
A10: 652330.22 | C10: 81400 | F10: 346215 | G10: 1784.29 | H10: 29548.64
A11: 1201700 | C11: 63300 | F11: #N/D | G11: 1875 | H11: 5250
A12: 1045100 | C12: 55100 | F12: 448214.94 | G12: 2434.74 | H12: 42185.84
A13: 575700 | C13: 64000 | F13: 477700 | G13: 1125 | H13: 13875
A14: 645000 | B14: 645000 | C14: 650000 | F14: 461012 | G14: 1045.45 | H14: 12499.95
A15: 705400 | C15: 100000 | F15: 452581.8 | G15: 2240.91 | H15: 36354.56
A16: 689591.49 | C16: 84000 | F16: 463588.23 | G16: 1323.53 | H16: 12088.24
A17: 445693.09 | C17: 37100 | F17: 460317.64 | G17: 1323.53 | H17: 12088.24
A18: 435029.72 | C18: 173320 | F18: 349636.4 | G18: 1704.55 | H18: 28272.8
A19: 923800 | C19: 47500 | F19: 450159 | G19: 2374.5 | H19: 40866.5
A20: 468690.28 | C20: 38500 | F20: 507200 | H20: 0
A21: 650000 | C21: 0 | F21: 474706 | H21: 0
A22: 309477.87 | C22: 58000 | F22: 474100 | H22: 14100
A23: 717500 | C23: 166000 | F23: 463438.44 | G23: 1723.08 | H23: 6669.24
A24: 546878.68 | C24: 48066 | F24: 461200 | G24: 1493.33 | H24: 10459.98
A25: 456605.45 | C25: 130000 | F25: 486200 | H25: 0
A26: 915700 | C26: 47500 | F26: 956042 | H26: 0
A27: 590900 | C27: 40500 | F27: 486950 | G27: 1125 | H27: 13875
A28: 615000 | C28: 68000 | F28: 505700 | H28: 0
A29: 483000 | C29: 54780 | F29: 459100 | H29: 0
A30: 422900 | C30: 70390 | F30: 452400.06 | G30: 2333.33 | H30: 35499.95
A31: 942821 | C31: 0 | F31: 473200 | H31: 23900
A32: 589500 | C32: 65500 | F32: 462530 | G32: 1178.95 | H32: 13289.5
A33: 175000 | C33: 414500 | F33: 365237.5 | H33: 0
A34: 899300 | C34: 49500 | F34: 394300 | H34: 0
A35: 488991.83 | C35: 68000 | F35: 476200 | G35: 1229.5 | H35: 29124.5
A36: 492984.65 | C36: 54780 | F36: 460275 | H36: 24000.04
A37: 335086.45 | C37: 54700 | F37: 487200 | H37: 0
A38: 497324.27 | C38: 68800 | F38: 505237.5 | G38: 2323.81 | H38: 35857.15
A39: 930000 | C39: 49500 | F39: 362637.5 | G39: 1062.5 | H39: 15312.5
A40: 403500 | C40: 66500 | F40: 475500 | H40: 0
A41: 764500 | C41: 40500 | F41: 461526.16 | G41: 2436.84 | H41: 39489.44
A42: 869929.1 | C42: 47500 | F42: 474700 | H42: 0
A43: 445000 | C43: 69000 | F43: 460805.27 | H43: 0
A44: 333187.37 | C44: 49800 | F44: 356468.38 | H44: 0
A45: 468282.11 | C45: 69800 | F45: 459973.25 | G45: 1045.45 | H45: 14590.85
A46: 671165.65 | C46: 80682.4 | F46: (en blanco) | G46: 5378.95
A47: 809100 | C47: 40900 | F47: 471726.68 | G47: 1493.33 | H47: 8966.65
A48: 591706.96 | C48: 49400 | F48: 470200 | G48: 1500 | H48: 1500
A49: 333014.03 | C49: 49800 | F49: 460412.5 | G49: 1462.5 | H49: 10737.5
A50: 248000 | C50: 250000 | F50: Total general | G50: 48559.26 | H50: 621585.69
A51: 628200 | C51: 69800
A52: 451104.27 | C52: 66500
A53: 543500 | C53: 66500
A54: 471723.22 | C54: 76720
A55: 333353.52 | C55: 49800
A56: 308362.91 | C56: 49800
A57: 710550 | C57: 78950
A58: 954300 | C58: 50317.1
A59: 446232.63 | C59: 38900
A60: 642400 | C60: 75400
A61: 602175.3 | C61: 51600
A62: 600000 | C62: 250000
... A75: 460000 | C75: 0
A76: Total general | B76: 645000 | C76: 10097247

Sheet RESUMEN
B2: DESARROLLOS INMOBILIARIOS
B3: RESUMEN DE COBROS POR PROYECTOS
B5: Al mes de : | C5: 45900
F6: ( + ) | G6: ( - ) | K6: ( + ) A | L6: ( - ) B | M6: ( = ) C | O6: ( + ) D | P6: ( - ) E | R6: ( C ) - (D-E) | V6: ( + ) | W6: ( - )
B7: Proyecto | C7: PPTO del mes | D7: Cobro del mes | E7: % de cobro del mes | F7: Ppto Acumulado | G7: Cobros Acumulados | H7: % de cobros acumulado | I7: Total cobros pendientes | K7: Efectivo acum. que se debió recibir | L7: Cobros por Efectuar (Casos Especiales / F&F) | M7: Cobros Netos Acumulados | O7: Cobros realizados | P7: Cobros Adicionales | R7: Saldo Conciliado | S7: Cobros por Efectuar (Clientes en Mora) | T7: Diferencia | V7: Cobros (Desistimientos) | W7: Devoluciones (Desistimientos) | Y7: (Faltante) / Sobrante en Flujo de Caja
B8: Casa Elisa | C8: =+'SANTA ELISA PPTO'!AL80 -> 0 | D8: =+'SANTA ELISA'!AV80 -> 0 | E8: =IFERROR((+D8/C8),0) -> 0 | F8: =+'SANTA ELISA PPTO'!AL81 -> 10097247 | G8: =+'SANTA ELISA PPTO'!AM80 -> 10097247 | H8: =IFERROR((+G8/F8),0) -> 1 | I8: =+F8-G8 -> 0
B9: Gran Jaguar | C9: =+'BOULEVARD PPTO'!AE311 -> 2967923.5 | D9: =+'BOULEVARD 5'!AM305-'BOULEVARD 5'!AM254-'BOULEVARD 5'!AM266 -> 3072696.4 | E9: =IFERROR((+D9/C9),0) -> 1.0353018 | F9: =+'BOULEVARD PPTO'!AE313 -> 23321517 | G9: =+'BOULEVARD 5'!AT305-612138 -> 30721735 | H9: =IFERROR((+G9/F9),0) -> 1.3173129 | I9: =+F9-G9 -> -7400218.6 | K9: =+'BOULEVARD 5'!BJ305 -> #VALUE! | L9: =+'BOULEVARD 5'!BO306 -> 2682559 | M9: =+K9-L9 -> #VALUE! | O9: =+'BOULEVARD 5'!BK305+'BOULEVARD 5'!BL305+'BOULEVARD 5'!BM305 -> 31333873 | P9: =+'BOULEVARD 5'!BN305 -> #VALUE! | R9: =((M9)-(O9-P9)) -> #VALUE! | S9: =+'BOULEVARD 5'!BO305-+'BOULEVARD 5'!BO306 -> #VALUE! | T9: =+R9-S9 -> #VALUE! | V9: =+'BOULEVARD 5'!AT306 -> 874279.14 | W9: 177175.45 | Y9: =-R9+V9-W9 -> #VALUE!
B10: Chinautla | C10: =+'BENESTARE PPTO'!AE115 -> 105339.09 | D10: =+'BENESTARE '!AQ174 -> 101165.69 | E10: =IFERROR((+D10/C10),0) -> 0.96038128 | F10: =+'BENESTARE PPTO'!AE116 -> 957782.27 | G10: =+'BENESTARE '!AX174 -> 1478044.7 | H10: =IFERROR((+G10/F10),0) -> 1.5431949 | I10: =+F10-G10 -> -520262.4 | K10: =+BENES!BD87 -> #NUM! | L10: =+BENES!BI88 -> 0 | M10: =+K10-L10 -> #NUM! | O10: =+BENES!BE87+BENES!BF87+BENES!BG87 -> 841408.68 | P10: =+BENES!BH87 -> #NUM! | R10: =((M10)-(O10-P10)) -> #NUM! | S10: =+BENES!BI87 -> #NUM! | T10: =+R10-S10 -> #NUM! | V10: =+BENES!AN88 -> 100416.23 | Y10: =-R10+V10-W10 -> #NUM!
B11: Bosque Las T. | C11: =+'BL PPTO'!AE120 -> 54685.15 | D11: =+'BL-TAPIAS'!O124 -> 53271.38 | E11: =IFERROR((+D11/C11),0) -> 0.97414709 | F11: =+'BL PPTO'!AE123 -> 95544.37 | G11: =+'BL-TAPIAS'!V124 -> 545624.27 | H11: =IFERROR((+G11/F11),0) -> 5.7106899 | I11: =+F11-G11 -> -450079.9 | K11: =+'BL-TAPIAS'!AL124 -> 163461.59 | L11: =+'BL-TAPIAS'!AQ125 -> 0 | M11: =+K11-L11 -> 163461.59 | O11: =+'BL-TAPIAS'!AM124+'BL-TAPIAS'!AN124+'BL-TAPIAS'!AO124 -> 545624.27 | P11: =+'BL-TAPIAS'!AP124 -> 388329.36 | R11: =((M11)-(O11-P11)) -> 6166.68 | S11: =+'BL-TAPIAS'!AQ124 -> 6171.68 | T11: =+R11-S11 -> -5 | V11: =+'BL-TAPIAS'!V125 -> 8000 | Y11: =-R11+V11-W11 -> 1833.32
C12: =SUM(C8:C11) -> 3127947.7 | D12: =SUM(D8:D11) -> 3227133.5 | E12: =IFERROR((+D12/C12),0) -> 1.0317095 | F12: =SUM(F8:F11) -> 34472091 | G12: =SUM(G8:G11) -> 42842652 | H12: =IFERROR((+G12/F12),0) -> 1.2428214 | I12: =SUM(I8:I11) -> -8370560.9 | K12: =SUM(K8:K11) -> #VALUE! | L12: =SUM(L8:L11) -> 2682559 | M12: =SUM(M8:M11) -> #VALUE! | O12: =SUM(O8:O11) -> 32720906 | P12: =SUM(P8:P11) -> #VALUE! | R12: =SUM(R8:R11) -> #VALUE! | S12: =SUM(S8:S11) -> #VALUE! | T12: =SUM(T8:T11) -> #VALUE! | V12: =SUM(V8:V11) -> 982695.37 | W12: =SUM(W8:W11) -> 177175.45 | Y12: =SUM(Y8:Y11) -> #VALUE!
L13: =+I9-L9 -> -10082778
B14: Proyecto | C14: Total Apartamentos | D14: Cliente al día | E14: Cliente atrasado | F14: Disponible | G14: Enganche completado | H14: Superávit de Enganche | I14: F&F
B15: Casa Elisa | C15: =COUNTA('SANTA ELISA'!B5:B79) -> 75 | D15: =COUNTIF('SANTA ELISA'!$BG$5:$BG$79,D$14) -> 0 | E15: =COUNTIF('SANTA ELISA'!$BG$5:$BG$79,E$14) -> 11 | F15: =COUNTIF('SANTA ELISA'!$BG$5:$BG$79,F$14) -> 1 | G15: =COUNTIF('SANTA ELISA'!$BG$5:$BG$79,G$14) -> 17 | H15: =COUNTIF('SANTA ELISA'!$BG$5:$BG$79,H$14) -> 46 | I15: =COUNTIF('SANTA ELISA'!$BG$5:$BG$79,I$14) -> 0
B16: Gran Jaguar | C16: =COUNTA('BOULEVARD 5'!B7:B304) -> 298 | D16: =COUNTIF('BOULEVARD 5'!$BB:$BB,D$14) -> 61 | E16: =COUNTIF('BOULEVARD 5'!BB:BB,E14)-I16 -> 159 | F16: =COUNTIF('BOULEVARD 5'!$BB:$BB,F$14) -> 14 | G16: =COUNTIF('BOULEVARD 5'!$BB:$BB,G$14) -> 7 | H16: =COUNTIF('BOULEVARD 5'!BB:BB,H$14) -> 30 | I16: =COUNTIFS('BOULEVARD 5'!$BB:$BB,E$14,'BOULEVARD 5'!BQ:BQ,$I14) -> 26
B17: Chinautla | C17: =COUNTA(BENES!B7:B86) -> 80 | D17: =COUNTIF(BENES!$AV:$AV,D$14) -> 36 | E17: =COUNTIF(BENES!$AV:$AV,E$14) -> 17 | F17: =COUNTIF(BENES!$AV:$AV,F$14) -> 16 | G17: =COUNTIF(BENES!$AV:$AV,G$14) -> 0 | H17: =COUNTIF(BENES!$AV:$AV,H$14) -> 0 | I17: =COUNTIFS(BENES!$AV:$AV,E$14,BENES!BK:BK,$I14) -> 0
B18: Bosque Las T. | C18: =COUNTA('BL-TAPIAS'!B7:B123) -> 117 | D18: =COUNTIF('BL-TAPIAS'!$AD:$AD,D$14) -> 61 | E18: =COUNTIF('BL-TAPIAS'!$AD:$AD,E$14) -> 5 | F18: =COUNTIF('BL-TAPIAS'!$AD:$AD,F$14) -> 51 | G18: =COUNTIF('BL-TAPIAS'!$AD:$AD,G$14) -> 0 | H18: =COUNTIF('BL-TAPIAS'!$AD:$AD,H$14) -> 0 | I18: =COUNTIFS('BL-TAPIAS'!$AD:$AD,E$14,'BL-TAPIAS'!AS:AS,$I14) -> 0
C19: =SUM(C15:C18) -> 570 | D19: =SUM(D15:D18) -> 158 | E19: =SUM(E15:E18) -> 192 | F19: =SUM(F15:F18) -> 82 | G19: =SUM(G15:G18) -> 24 | H19: =SUM(H15:H18) -> 76 | I19: =SUM(I15:I18) -> 26
B22: % de las cantidades
B23: Proyecto | C23: Total Apartamentos | D23: Cliente al día | E23: Cliente atrasado | F23: Cliente Disponible | G23: Enganche completado | H23: Superávit de Enganche | I23: F&F
B24: Casa Elisa | C24: 1 | D24: =+D15/$C$15 -> 0 | E24: =+E15/$C$15 -> 0.14666667 | F24: =+F15/$C$15 -> 0.013333333 | G24: =+G15/$C$15 -> 0.22666667 | H24: =+H15/$C$15 -> 0.61333333 | I24: =+I15/$C$15 -> 0
B25: Gran Jaguar | C25: 1 | D25: =+D16/$C$16 -> 0.20469799 | E25: =+E16/$C$16 -> 0.53355705 | F25: =+F16/$C$16 -> 0.046979866 | G25: =+G16/$C$16 -> 0.023489933 | H25: =+H16/$C$16 -> 0.10067114 | I25: =+I16/$C$16 -> 0.087248322
B26: Chinautla | C26: 1 | D26: =+D17/$C$17 -> 0.45 | E26: =+E17/$C$17 -> 0.2125 | F26: =+F17/$C$17 -> 0.2 | G26: =+G17/$C$17 -> 0 | H26: =+H17/$C$17 -> 0 | I26: =+I17/$C$17 -> 0
B27: Bosque Las T. | C27: 1 | D27: =+D18/$C$18 -> 0.52136752 | E27: =+E18/$C$18 -> 0.042735043 | F27: =+F18/$C$18 -> 0.43589744 | G27: =+G18/$C$18 -> 0 | H27: =+H18/$C$18 -> 0 | I27: =+I18/$C$18 -> 0
C28: =AVERAGE(C24:C27) -> 1 | D28: =AVERAGE(D24:D27) -> 0.29401638 | E28: =AVERAGE(E24:E27) -> 0.23386469 | F28: =AVERAGE(F24:F27) -> 0.17405266 | G28: =AVERAGE(G24:G27) -> 0.06253915 | H28: =AVERAGE(H24:H27) -> 0.17850112 | I28: =AVERAGE(I24:I27) -> 0.021812081

Sheet Detalle2
A1: Detalles para Cobro no realizado. - Apto: 315, Cuotas: 2, ESTATUS CLIENTE: Cliente Atrasado
A3: Apto | B3: Tipo | C3: NOTAS | D3: Vendedor | E3: Cliente | F3: Reservado | G3: Estatus | H3: Precio de Venta | I3: Enganche | J3: mar-23 | K3: abr-23 | L3: may-23 | M3: jun-23 | N3: jul-23 | O3: ago-23 | P3: sep-23 | Q3: oct-23 | R3: nov-23 | S3: dic-23 | T3: ene-24 | U3: feb-24 | V3: mar-24 | W3: abr-24 | X3: may-24 | Y3: jun-24 | Z3: jul-24 | AA3: ago-24 | AB3: sep-24 | AC3: oct-24 | AD3: nov-24 | AE3: dic-24 | AF3: ene-25 | AG3: feb-25 | AH3: mar-25 | AI3: abr-25 | AJ3: may-25 | AK3: jun-25 | AL3: jul-25 | AM3: ago-25 | AN3: TOTAL COBROS Y RESERVAS | AO3: % Cobro | AP3: SALDO PENDIENTE ENGANCHE | AQ3: % Pendiente | AR3: Monto a Financiar por Banco | AS3: % a Financiar | AT3: Proyección de Cobros (S/ Modelo Financiero) | AU3: Status inmueble | AV3: ESTATUS CLIENTE | AW3: Cuotas Pactadas | AX3: Cuota de Enganche | AY3: Total cuotas pactadas | AZ3: Monto de Reserva Pactado | BA3: Monto de Cuota Pactada | BB3: Cuotas Pagadas | BC3: Cantidad de cuotas que deben estar pagadas por el cliente | BD3: Monto que debe estar cancelado a la fecha | BE3: Monto pagado de cuotas a la fecha | BF3: Enganche + Cuotas Extraordinarias Pagadas | BG3: Diferencia | BH3: Cobro adicional a lo pactado | BI3: Cobro no realizado según lo pactado | BJ3: Cuotas | BK3: Caso Especial / F&F | BL3: Observaciones
A4: 315 | B4: E1 | D4: Sofia Paredes | E4: Lilian America Roldan Ochoa | F4: 45752 | G4: 4.Plan de pagos | H4: 1543627 | I4: 154426.97 | J4: 0 | K4: 0 | L4: 0 | M4: 0 | N4: 0 | O4: 0 | P4: 0 | Q4: 0 | R4: 0 | S4: 0 | T4: 0 | U4: 0 | V4: 0 | W4: 0 | X4: 0 | Y4: 0 | Z4: 0 | AA4: 0 | AB4: 0 | AC4: 0 | AD4: 0 | AE4: 0 | AF4: 0 | AG4: 0 | AH4: 0 | AI4: 10000 | AJ4: 10000 | AL4: 10024 | AN4: 30024 | AO4: 0.194422 | AP4: -124402.97 | AQ4: -0.805578 | AR4: 1513603 | AS4: 0.9805497 | AT4: 154426.97 | AU4: Vendido | AV4: Cliente Atrasado | AW4: 13 | AX4: 1 | AY4: 14 | AZ4: 10000 | BA4: 11110 | BB4: 0 | BC4: 3 | BD4: 43330 | BE4: 30024 | BF4: 0 | BG4: 0 | BH4: 0 | BI4: 13306 | BJ4: 2

Sheet Detalle3
A1: Detalles para Cobro no realizado. - Apto.: 602, Cuotas: 2, ESTATUS CLIENTE: Cliente Atrasado
A3: Apto. | B3: Tipo. | C3: NOTAS | D3: Vendedor | E3: Cliente | F3: Fecha Reserva | G3: Estatus | H3: Precio de Venta | I3: Enganche | J3: mar-23 | K3: abr-23 | L3: may-23 | M3: jun-23 | N3: jul-23 | O3: ago-23 | P3: sep-23 | Q3: oct-23 | R3: nov-23 | S3: dic-23 | T3: ene-24 | U3: feb-24 | V3: mar-24 | W3: abr-24 | X3: may-24 | Y3: jun-24 | Z3: jul-24 | AA3: ago-24 | AB3: sep-24 | AC3: oct-24 | AD3: nov-24 | AE3: dic-24 | AF3: ene-25 | AG3: feb-25 | AH3: mar-25 | AI3: abr-25 | AJ3: may-25 | AK3: jun-25 | AL3: jul-25 | AM3: ago-25 | AN3: TOTAL COBROS Y RESERVAS | AO3: % Cobro | AP3: SALDO PENDIENTE ENGANCHE | AQ3: % Pendiente | AR3: Monto a Financiar por Banco | AS3: % a Financiar | AT3: Proyección de Cobros (S/ Modelo Financiero) | AU3: Status inmueble | AV3: ESTATUS CLIENTE | AW3: Cuotas Pactadas | AX3: Cuota de Enganche | AY3: Total cuotas pactadas | AZ3: Monto de Reserva Pactado | BA3: Monto de Cuota Pactada | BB3: Cuotas Pagadas | BC3: Cantidad de cuotas que deben estar pagadas por el cliente | BD3: Monto que debe estar cancelado a la fecha | BE3: Monto pagado de cuotas a la fecha | BF3: Enganche + Cuotas Extraordinarias Pagadas | BG3: Diferencia | BH3: Cobro adicional a lo pactado | BI3: Cobro no realizado según lo pactado | BJ3: Cuotas | BK3: Caso Especial / F&F | BL3: Observaciones
A4: 602 | B4: E10 | D4: Anahí Cisneros | E4: Judith Fabiola Arevalo Valdez de Franco | F4: 45815 | G4: 2. Reserva | H4: 1529194.3 | I4: 152894.33 | J4: 0 | K4: 0 | L4: 0 | M4: 0 | N4: 0 | O4: 0 | P4: 0 | Q4: 0 | R4: 0 | S4: 0 | T4: 0 | U4: 0 | V4: 0 | W4: 0 | X4: 0 | Y4: 0 | Z4: 0 | AA4: 0 | AB4: 0 | AC4: 0 | AD4: 0 | AE4: 0 | AF4: 0 | AG4: 0 | AH4: 0 | AI4: 0 | AK4: 10000 | AN4: 10000 | AO4: 0.065404649 | AP4: -142894.33 | AQ4: -0.93459535 | AR4: 1519194.3 | AS4: 0.99346061 | AT4: 152894.33 | AU4: Vendido | AV4: Cliente Atrasado | AW4: 12 | AX4: 1 | AY4: 13 | AZ4: 10000 | BA4: 11908 | BB4: 0 | BC4: 2 | BD4: 33816 | BE4: 10000 | BF4: 0 | BG4: 0 | BH4: 0 | BI4: 23816 | BJ4: 2

Sheet ALERTA (B5)
F2: RESUMEN
C3: PROYECTO: | D3: GRAN JAGUAR
C4: ESTATUS CLIENTE | D4: Cliente Atrasado
C6: Cuotas | D6: Apto. | E6: Cobro no realizado.
C7: 1 | D7: 104 | E7: 1824
D8: 109 | E8: 7704
D9: 110 | E9: 2388
D10: 111 | E10: 820
D11: 312 | E11: 7851
D12: 404 | E12: 2791
D13: 410 | E13: 5.46
D14: 505 | E14: 7645
D15: 506 | E15: 450
D16: 508 | E16: 6404
D17: 510 | E17: 1868
D18: 512 | E18: 2477
D19: 513 | E19: 2415
... D51: 1609 | E51: 2290
C52: Total 1 | E52: 157496.42
C53: Total general | E53: 157496.42

Sheet Detalle1
A1: Detalles para Cobro no realizado. - Apto: 104, Cuotas: 19, ESTATUS CLIENTE: Cliente Atrasado
A3: Apto | B3: Torre | C3: Tipo | D3: Vendedor | E3: Cliente | F3: Reservado | G3: Estatus | H3: Precio de Venta | I3: Enganche | J3: mar-23 | K3: abr-23 | L3: may-23 | M3: jun-23 | N3: jul-23 | O3: ago-23 | P3: sep-23 | Q3: oct-23 | R3: nov-23 | S3: dic-23 | T3: ene-24 | U3: feb-24 | V3: mar-24 | W3: abr-24 | X3: may-24 | Y3: jun-24 | Z3: jul-24 | AA3: ago-24 | AB3: sep-24 | AC3: oct-24 | AD3: nov-24 | AE3: dic-24 | AF3: ene-25 | AG3: feb-25 | AH3: mar-25 | AI3: abr-25 | AJ3: may-25 | AK3: jun-25 | AL3: jul-25 | AM3: ago-25 | AN3: TOTAL COBROS Y RESERVAS | AO3: % Cobro | AP3: SALDO PENDIENTE ENGANCHE | AQ3: % Pendiente | AR3: Monto a Financiar por Banco | AS3: % a Financiar | AT3: Proyección de Cobros (S/ Modelo Financiero) | AU3: Status inmueble | AV3: ESTATUS CLIENTE | AW3: Cuotas Pactadas | AX3: Cuota de Enganche | AY3: Total cuotas pactadas | AZ3: Monto de Reserva Pactado | BA3: Monto de Cuota Pactada | BB3: Cuotas Pagadas | BC3: Cantidad de cuotas que deben estar pagadas por el cliente | BD3: Monto que debe estar cancelado a la fecha | BE3: Monto pagado de cuotas a la fecha | BF3: Enganche + Cuotas Extraordinarias Pagadas | BG3: Diferencia | BH3: Cobro adicional a lo pactado | BI3: Cobro no realizado según lo pactado | BJ3: Cuotas | BK3: Caso Especial / F&F | BL3: Observaciones
A4: 104 | B4: A | C4: B | D4: Abigail Garcia | E4: Astrid Marleny Pineda Gonzalez | F4: 45258 | G4: 4.Plan de pagos | H4: 494900 | I4: 23900 | J4: 0 | K4: 0 | L4: 0 | M4: 0 | N4: 0 | O4: 0 | P4: 0 | Q4: 0 | R4: 0 | S4: 0 | T4: 0 | U4: 0 | V4: 0 | W4: 0 | X4: 0 | Y4: 0 | Z4: 0 | AA4: 0 | AB4: 0 | AC4: 0 | AD4: 300 | AE4: 500 | AF4: 0 | AG4: 0 | AH4: 1000 | AJ4: 500 | AL4: 500 | AN4: 2800 | AO4: 0.11715481 | AP4: -21100 | AQ4: -0.88284519 | AR4: 492100 | AS4: 0.99434229 | AT4: 23900 | AU4: Vendido | AV4: Cliente Atrasado | AW4: 13 | AX4: 1 | AY4: 14 | AZ4: 300 | BA4: 1815.38 | BB4: 0 | BC4: 20 | BD4: 36607.6 | BE4: 2300 | BF4: 0 | BG4: 500 | BH4: 0 | BI4: 33807.6 | BJ4: 19

Sheet ALERTA BEN
F2: RESUMEN
C3: PROYECTO: | D3: BENESTARE
C4: ESTATUS CLIENTE | D4: Cliente Atrasado
C6: Cuotas | D6: Apto | E6: Cobro no realizado.
C7: 0 | D7: 108 | E7: 0
D8: 305 | E8: 0
D9: 403 | E9: 0
D10: 502 | E10: 0
D11: 211 | E11: 0
D12: 412 | E12: 500
D13: 609 | E13: 0
C14: Total 0 | E14: 500
C15: 1 | D15: 105 | E15: 1769.38
D16: 106 | E16: 2228.57
D17: 109 | E17: 1874.5
D18: 205 | E18: 28.77
D19: 213 | E19: 750
D20: 304 | E20: 1426.63
D21: 306 | E21: 34842
D22: 308 | E22: 750
D23: 311 | E23: 84.25
D24: 312 | E24: 1272.22
D25: 401 | E25: 2333.33
D26: 405 | E26: 1800
D27: 407 | E27: 451.01
... D34: 111 | E34: 750
C35: Total 1 | E35: 57373.07
C36: 2 | D36: 301 | E36: 2986.14
D37: 302 | E37: 2800
D38: 305 | E38: 2125
D39: 306 | E39: 44800
D40: 309 | E40: 2800
D41: 504 | E41: 2800
D42: 606 | E42: 1184.21
D43: 610 | E43: 1045.9
D44: (en blanco) | E44: 1500
C45: Total 2 | E45: 62041.25
C46: 3 | D46: 102 | E46: 3733.32
D47: 203 | E47: 3970.59
D48: 207 | E48: 5623.5
D49: 410 | E49: 2194.08
D50: 601 | E50: 3418
C51: Total 3 | E51: 18939.49
C52: 4 | D52: 403 | E52: 4714.25
C53: Total 4 | E53: 4714.25
C54: 5 | D54: 108 | E54: 10109.22
C55: Total 5 | E55: 10109.22
C56: 7 | D56: 602 | E56: 15299.8
C57: Total 7 | E57: 15299.8
C58: 8 | D58: 210 | E58: 10459.98
C59: Total 8 | E59: 10459.98
C60: 12 | D60: 212 | E60: 17919.96
C61: Total 12 | E61: 17919.96
C62: 14 | D62: 213 | E62: 19419.96
C63: Total 14 | E63: 19419.96
C64: 20 | D64: 104 | E64: 35622.98
C65: Total 20 | E65: 35622.98
C66: Total general | E66: 252399.96

Sheet ALERTA BLT
F2: RESUMEN
C3: PROYECTO: | D3: Bosque Las Tapias
C4: Status Cliente | D4: Cliente Atrasado
C6: Cuotas | D6: Apto | E6: Cobro no realizado.
C7: 0
D8: 802 | E8: 0
D9: 806 | E9: 0
D10: 908 | E10: 0
D11: 1001 | E11: 0
C12: 2
D13: 904 | E13: 3111.12
D14: 905 | E14: 3055.56
C15: Total general | E15: 6166.68

Sheet SANTA ELISA
B1: 1 | C1: =+B1+1 -> 2 | D1: =+C1+1 -> 3 | E1: =+D1+1 -> 4 | F1: =+E1+1 -> 5 | G1: =+F1+1 -> 6 | H1: =+G1+1 -> 7 | I1: =+H1+1 -> 8 | J1: =+I1+1 -> 9 | ... AS1: =+AR1+1 -> 44
B2: INVERSIONES INMOBILIARIAS SANTA ELISA, S.A.
B3: REPORTE DE RESERVAS | H3: PROMESA FIRMADO POR CLIENTE ( A )
B4: Apto | C4: Vendedor | D4: Cliente | E4: Reservado | F4: Tipo | G4: Cotizador | H4: Precio de Venta | I4: Diferencia Cotizador vs PV | J4: Enganche | K4: Estatus | L4: 44742 | M4: 44773 | N4: 44804 | O4: 44834 | P4: 44865 | Q4: 44895 | R4: 44926 | S4: 44957 | T4: 44985 | U4: 45016 | V4: 45046 | W4: 45077 | X4: 45107 | Y4: 45138 | Z4: 45169 | AA4: 45199 | AB4: 45230 | AC4: 45260 | AD4: 45291 | AE4: 45322 | AF4: 45351 | AG4: 45382 | AH4: 45412 | AI4: 45443 | AJ4: 45473 | AK4: 45504 | AL4: 45535 | AM4: 45565 | AN4: 45596 | AO4: 45626 | AP4: 45657 | AQ4: 45688 | AR4: 45716 | AS4: 45747 | AT4: 45777 | AU4: 45808 | AV4: 45838 | AW4: 45869 | AX4: TOTAL COBROS Y RESERVAS | AY4: % Cobro | AZ4: SALDO PENDIENTE ENGANCHE | BA4: % Pendiente | BB4: Monto a Financiar por Banco | BC4: % a Financiar | BD4: Proyección de Cobros (S/ Modelo Financiero) | BE4: Variación modelo Finan. vs cobro real | BF4: Status inmueble | BG4: ESTATUS CLIENTE | BH4: Cuotas Pactadas | BI4: Cuotas Pagadas | BJ4: Cuotas Atrasadas
B5: 101 | C5: Noemi M. | D5: Thelma Suyapa Aguilera Sanchez de Roca | E5: 44797 | F5: B1 | G5: 806000 | H5: 806000 | I5: =+G5-H5 -> 0 | J5: 80600 | K5: 4.PLAN DE PAGOS | L5: 0 | M5: 0 | N5: 5000 | O5: 3285 | P5: 3285 | Q5: 3285 | R5: 3285 | S5: 3285 | T5: 3285 | U5: 3285 | V5: 3285 | W5: 3285 | X5: 3285 | Y5: 3285 | Z5: 3285 | AA5: 3285 | AB5: 3285 | AC5: 3285 | AD5: 3285 | AE5: 3285 | AF5: 3285 | AG5: 3285 | AH5: 3285 | AI5: 3285 | AJ5: 3285 | AK5: 3330 | AL5: 0 | AM5: 0 | AN5: 0 | AO5: 0 | AP5: 0 | AQ5: 0 | AR5: 0 | AS5: 0 | AT5: 0 | AX5: =SUM(L5:AV5) -> 80600 | AY5: =IFERROR((+AX5/BD5),0) -> 1 | AZ5: =+AX5-BD5 -> 0 | BA5: =IFERROR((+AZ5/BD5),0) -> 0 | BB5: =+H5-AX5 -> 725400 | BC5: =+BB5/H5 -> 0.9 | BD5: =IF(BF5="Vendido",J5*1,IF(BF5="Disponible",J5*0,IF(BF5="Enganche Completado",J5*1,IF(BF5="Superávit de Enganche",J5*1,0)))) -> 80600 | BE5: =IF(D5=0,J5*0,BD5-AX5) -> 0 | BF5: =IF(D5=0,"Apartamento Disponible",IF(D5>1,"Vendido",0)) -> Vendido | BG5: =IF(AND(BF5="Vendido",E5>=0,AZ5=0),"Enganche Completado",IF(AND(BF5="Vendido",E5>=0,AZ5>0),"Superávit de Enganche",IF(AND(BF5="Apartamento Disponible",E5=0,AZ5=0),"Disponible","Cliente Atrasado"))) -> Enganche Completado | BI5: =COUNTIF(L5:AT5,">0.01") -> 24 | BJ5: =IF(AND(BG5="Cliente Atrasado",COUNTIF(L5:AT5,"<0.01")),DATEDIF(E5,AT$4+1,"m"),0) -> 0
B6: 102 | C6: Noemi M. | D6: Cristina Estefanía Villagrán Marroquin | E6: 44934 | F6: B3 | G6: 814000 | H6: 814000 | I6: =+G6-H6 -> 0 | J6: 81400 | K6: 4.PLAN DE PAGOS | L6: 0 | M6: 0 | N6: 0 | O6: 0 | P6: 0 | Q6: 0 | R6: 0 | S6: 5000 | T6: 8480 | U6: 0 | V6: 8480 | W6: 0 | X6: 4240 | Y6: 8480 | Z6: 0 | AA6: 4240 | AB6: 8480 | AC6: 0 | AD6: 8480 | AE6: 4240 | AF6: 0 | AG6: 4240 | AH6: 8480 | AI6: 4240 | AJ6: 0 | AK6: 4320 | AL6: 500 | AM6: 0 | AN6: 0 | AO6: 0 | AP6: 0 | AQ6: 0 | AR6: 0 | AS6: 0 | AT6: 79769.78 | AX6: =SUM(L6:AV6) -> 161669.78 | AY6: =IFERROR((+AX6/BD6),0) -> 1.9861152 | AZ6: =+AX6-BD6 -> 80269.78 | BA6: =IFERROR((+AZ6/BD6),0) -> 0.98611523 | BB6: =+H6-AX6 -> 652330.22 | BC6: =+BB6/H6 -> 0.80138848 | BD6: =IF(BF6="Vendido",J6*1,IF(BF6="Disponible",J6*0,IF(BF6="Enganche Completado",J6*1,IF(BF6="Superávit de Enganche",J6*1,0)))) -> 81400 | BE6: =IF(D6=0,J6*0,BD6-AX6) -> -80269.78 | BF6: =IF(D6=0,"Apartamento Disponible",IF(D6>1,"Vendido",0)) -> Vendido | BG6: =IF(AND(BF6="Vendido",E6>=0,AZ6=0),"Enganche Completado",IF(AND(BF6="Vendido",E6>=0,AZ6>0),"Superávit de Enganche",IF(AND(BF6="Apartamento Disponible",E6=0,AZ6=0),"Disponible","Cliente Atrasado"))) -> Superávit de Enganche | BI6: =COUNTIF(L6:AT6,">0.01") -> 15 | BJ6: =IF(AND(BG6="Cliente Atrasado",COUNTIF(L6:AT6,"<0.01")),DATEDIF(E6,AT$4+1,"m"),0) -> 0
B7: 103 | C7: Paula H. | D7: Chelsy Amarilis Orellana De León | E7: 44895 | F7: A4 | G7: 1265000 | H7: 1265000 | I7: =+G7-H7 -> 0 | J7: 63300 | K7: 4.PLAN DE PAGOS | L7: 0 | M7: 0 | N7: 0 | O7: 0 | P7: 0 | Q7: 0 | R7: 0 | S7: 0 | T7: 0 | U7: 0 | V7: 0 | W7: 0 | X7: 0 | Y7: 0 | Z7: 0 | AA7: 0 | AB7: 0 | AC7: 0 | AD7: 0 | AE7: 0 | AF7: 0 | AG7: 0 | AH7: 0 | AI7: 0 | AJ7: 0 | AK7: 0 | AL7: 0 | AM7: 5000 | AN7: =5000 -> 5000 | AO7: 5000 | AP7: 5000 | AQ7: =1650+20000 -> 21650 | AR7: =20000+1650 -> 21650 | AS7: 0 | AX7: =SUM(L7:AV7) -> 63300 | AY7: =IFERROR((+AX7/BD7),0) -> 1 | AZ7: =+AX7-BD7 -> 0 | BA7: =IFERROR((+AZ7/BD7),0) -> 0 | BB7: =+H7-AX7 -> 1201700 | BC7: =+BB7/H7 -> 0.94996047 | BD7: =IF(BF7="Vendido",J7*1,IF(BF7="Disponible",J7*0,IF(BF7="Enganche Completado",J7*1,IF(BF7="Superávit de Enganche",J7*1,0)))) -> 63300 | BE7: =IF(D7=0,J7*0,BD7-AX7) -> 0 | BF7: =IF(D7=0,"Apartamento Disponible",IF(D7>1,"Vendido",0)) -> Vendido | BG7: =IF(AND(BF7="Vendido",E7>=0,AZ7=0),"Enganche Completado",IF(AND(BF7="Vendido",E7>=0,AZ7>0),"Superávit de Enganche",IF(AND(BF7="Apartamento Disponible",E7=0,AZ7=0),"Disponible","Cliente Atrasado"))) -> Enganche Completado | BI7: =COUNTIF(L7:AT7,">0.01") -> 6 | BJ7: =IF(AND(BG7="Cliente Atrasado",COUNTIF(L7:AT7,"<0.01")),DATEDIF(E7,AT$4+1,"m"),0) -> 0
B8: 104 | C8: Eder Daniel V. | D8: Ada Marcela Moscoso Lopez / Mostello | E8: 45614 | F8: A2 | G8: 1100200 | H8: 1100200 | I8: =+G8-H8 -> 0 | J8: 55100 | K8: 4.PLAN DE PAGOS | L8: 0 | M8: 0 | N8: 0 | O8: 0 | P8: 0 | Q8: 0 | R8: 0 | S8: 0 | T8: 0 | U8: 0 | V8: 0 | W8: 0 | X8: 0 | Y8: 0 | AA8: 0 | AB8: 0 | AC8: 0 | AD8: 0 | AE8: 0 | AF8: 0 | AG8: 0 | AH8: 0 | AI8: 0 | AJ8: 0 | AK8: 0 | AL8: 0 | AM8: 0 | AN8: 0 | AO8: 5000 | AP8: =90+50010 -> 50100 | AQ8: 0 | AR8: 0 | AS8: 0 | AX8: =SUM(L8:AV8) -> 55100 | AY8: =IFERROR((+AX8/BD8),0) -> 1 | AZ8: =+AX8-BD8 -> 0 | BA8: =IFERROR((+AZ8/BD8),0) -> 0 | BB8: =+H8-AX8 -> 1045100 | BC8: =+BB8/H8 -> 0.9499182 | BD8: =IF(BF8="Vendido",J8*1,IF(BF8="Disponible",J8*0,IF(BF8="Enganche Completado",J8*1,IF(BF8="Superávit de Enganche",J8*1,0)))) -> 55100 | BE8: =IF(D8=0,J8*0,BD8-AX8) -> 0 | BF8: =IF(D8=0,"Apartamento Disponible",IF(D8>1,"Vendido",0)) -> Vendido | BG8: =IF(AND(BF8="Vendido",E8>=0,AZ8=0),"Enganche Completado",IF(AND(BF8="Vendido",E8>=0,AZ8>0),"Superávit de Enganche",IF(AND(BF8="Apartamento Disponible",E8=0,AZ8=0),"Disponible","Cliente Atrasado"))) -> Enganche Completado | BI8: =COUNTIF(L8:AT8,">0.01") -> 2 | BJ8: =IF(AND(BG8="Cliente Atrasado",COUNTIF(L8:AT8,"<0.01")),DATEDIF(E8,AT$4+1,"m"),0) -> 0
B9: 105 | C9: Ricardo O. | D9: Juan Pablo Matheu Morales | E9: 44972 | F9: C1 | G9: 639700 | H9: 639700 | I9: =+G9-H9 -> 0 | J9: 64000 | K9: 4.PLAN DE PAGOS | L9: 0 | M9: 0 | N9: 0 | O9: 0 | P9: 0 | Q9: 0 | R9: 0 | S9: 0 | T9: 5000 | U9: 0 | V9: 5000 | W9: 0 | X9: 0 | Y9: 5000 | Z9: 0 | AA9: 0 | AB9: 0 | AC9: 0 | AD9: 0 | AE9: 0 | AF9: 8000 | AG9: 0 | AH9: 2000 | AI9: 0 | AJ9: 2000 | AK9: 14500 | AL9: 0 | AM9: 2000 | AN9: 0 | AO9: 0 | AP9: 0 | AQ9: 0 | AR9: 0 | AS9: 20500 | AX9: =SUM(L9:AV9) -> 64000 | AY9: =IFERROR((+AX9/BD9),0) -> 1 | AZ9: =+AX9-BD9 -> 0 | BA9: =IFERROR((+AZ9/BD9),0) -> 0 | BB9: =+H9-AX9 -> 575700 | BC9: =+BB9/H9 -> 0.8999531 | BD9: =IF(BF9="Vendido",J9*1,IF(BF9="Disponible",J9*0,IF(BF9="Enganche Completado",J9*1,IF(BF9="Superávit de Enganche",J9*1,0)))) -> 64000 | BE9: =IF(D9=0,J9*0,BD9-AX9) -> 0 | BF9: =IF(D9=0,"Apartamento Disponible",IF(D9>1,"Vendido",0)) -> Vendido | BG9: =IF(AND(BF9="Vendido",E9>=0,AZ9=0),"Enganche Completado",IF(AND(BF9="Vendido",E9>=0,AZ9>0),"Superávit de Enganche",IF(AND(BF9="Apartamento Disponible",E9=0,AZ9=0),"Disponible","Cliente Atrasado"))) -> Enganche Completado | BI9: =COUNTIF(L9:AT9,">0.01") -> 9 | BJ9: =IF(AND(BG9="Cliente Atrasado",COUNTIF(L9:AT9,"<0.01")),DATEDIF(E9,AT$4+1,"m"),0) -> 0
B10: 201 | C10: Paula H. | D10: Hernan Benito Guerra Bardales | E10: 45701 | F10: C2 | G10: 650000 | H10: 650000 | I10: =+G10-H10 -> 0 | J10: 650000 | K10: 2.RESERVADO | L10: 0 | M10: 0 | N10: 0 | O10: 0 | P10: 0 | Q10: 0 | R10: 0 | S10: 0 | T10: 0 | U10: 0 | V10: 0 | W10: 0 | X10: 0 | Y10: 0 | AA10: 0 | AB10: 0 | AC10: 0 | AD10: 0 | AE10: 0 | AF10: 0 | AG10: 0 | AH10: 0 | AI10: 0 | AJ10: 0 | AK10: 0 | AL10: 0 | AM10: 0 | AN10: 0 | AO10: 0 | AP10: 0 | AQ10: 0 | AR10: 5000 | AS10: 0 | AX10: =SUM(L10:AV10) -> 5000 | AY10: =IFERROR((+AX10/BD10),0) -> 0.0076923077 | AZ10: =+AX10-BD10 -> -645000 | BA10: =IFERROR((+AZ10/BD10),0) -> -0.99230769 | BB10: =+H10-AX10 -> 645000 | BC10: =+BB10/H10 -> 0.99230769 | BD10: =IF(BF10="Vendido",J10*1,IF(BF10="Disponible",J10*0,IF(BF10="Enganche Completado",J10*1,IF(BF10="Superávit de Enganche",J10*1,0)))) -> 650000 | BE10: =IF(D10=0,J10*0,BD10-AX10) -> 645000 | BF10: =IF(D10=0,"Apartamento Disponible",IF(D10>1,"Vendido",0)) -> Vendido | BG10: =IF(AND(BF10="Vendido",E10>=0,AZ10=0),"Enganche Completado",IF(AND(BF10="Vendido",E10>=0,AZ10>0),"Superávit de Enganche",IF(AND(BF10="Apartamento Disponible",E10=0,AZ10=0),"Disponible","Cliente Atrasado"))) -> Cliente Atrasado | BI10: =COUNTIF(L10:AT10,">0.01") -> 1 | BJ10: =IF(AND(BG10="Cliente Atrasado",COUNTIF(L10:AT10,"<0.01")),DATEDIF(E10,AT$4+1,"m"),0) -> 2
B11: 202 | C11: Paula H. | D11: Ángel Roberto Sic García/ANGEL EDUARDO SIC MORALES | E11: 45398 | F11: A5 | G11: 805400 | H11: 805400 | I11: =+G11-H11 -> 0 | J11: 100000 | K11: 4.PLAN DE PAGOS | L11: 0 | M11: 0 | N11: 0 | O11: 0 | P11: 0 | Q11: 0 | R11: 0 | S11: 0 | T11: 0 | U11: 0 | V11: 0 | W11: 0 | X11: 0 | Y11: 0 | Z11: 0 | AA11: 0 | AB11: 0 | AC11: 0 | AD11: 0 | AE11: 0 | AF11: 0 | AG11: 0 | AH11: 5000 | AI11: 3500 | AJ11: 3500 | AK11: 3500 | AL11: 3500 | AM11: 3500 | AN11: 3500 | AO11: 74000 | AP11: 0 | AQ11: 0 | AR11: 0 | AS11: 0 | AX11: =SUM(L11:AV11) -> 100000 | AY11: =IFERROR((+AX11/BD11),0) -> 1 | AZ11: =+AX11-BD11 -> 0 | BA11: =IFERROR((+AZ11/BD11),0) -> 0 | BB11: =+H11-AX11 -> 705400 | BC11: =+BB11/H11 -> 0.87583809 | BD11: =IF(BF11="Vendido",J11*1,IF(BF11="Disponible",J11*0,IF(BF11="Enganche Completado",J11*1,IF(BF11="Superávit de Enganche",J11*1,0)))) -> 100000 | BE11: =IF(D11=0,J11*0,BD11-AX11) -> 0 | BF11: =IF(D11=0,"Apartamento Disponible",IF(D11>1,"Vendido",0)) -> Vendido | BG11: =IF(AND(BF11="Vendido",E11>=0,AZ11=0),"Enganche Completado",IF(AND(BF11="Vendido",E11>=0,AZ11>0),"Superávit de Enganche",IF(AND(BF11="Apartamento Disponible",E11=0,AZ11=0),"Disponible","Cliente Atrasado"))) -> Enganche Completado | BI11: =COUNTIF(L11:AT11,">0.01") -> 8 | BJ11: =IF(AND(BG11="Cliente Atrasado",COUNTIF(L11:AT11,"<0.01")),DATEDIF(E11,AT$4+1,"m"),0) -> 0
B12: 203 | C12: Francisco S. | D12: Ana Cristina Velásquez de Gómez | E12: 44740 | F12: A6 | G12: 840000 | H12: 840000 | I12: =+G12-H12 -> 0 | J12: 84000 | K12: 4.PLAN DE PAGOS | L12: 5000 | M12: 3434.78 | N12: 3434.78 | O12: 3434.78 | P12: 3434.78 | Q12: 3434.78 | R12: 3434.78 | S12: 3434.78 | T12: 3434.78 | U12: 3434.78 | V12: 3434.78 | W12: 3434.78 | X12: 3434.78 | Y12: 3434.78 | Z12: 3434.78 | AA12: 3434.78 | AB12: 3434.78 | AC12: 3434.78 | AD12: 3434.78 | AE12: 3434.78 | AF12: 3434.78 | AG12: 3434.78 | AH12: 3434.78 | AI12: 3434.78 | AJ12: 0 | AK12: 0.06 | AL12: 0 | AM12: 0 | AN12: 0 | AO12: 0 | AP12: 0 | AQ12: 0 | AR12: 0 | AS12: 66408.51 | AX12: =SUM(L12:AV12) -> 150408.51 | AY12: =IFERROR((+AX12/BD12),0) -> 1.7905775 | AZ12: =+AX12-BD12 -> 66408.51 | BA12: =IFERROR((+AZ12/BD12),0) -> 0.7905775 | BB12: =+H12-AX12 -> 689591.49 | BC12: =+BB12/H12 -> 0.82094225 | BD12: =IF(BF12="Vendido",J12*1,IF(BF12="Disponible",J12*0,IF(BF12="Enganche Completado",J12*1,IF(BF12="Superávit de Enganche",J12*1,0)))) -> 84000 | BE12: =IF(D12=0,J12*0,BD12-AX12) -> -66408.51 | BF12: =IF(D12=0,"Apartamento Disponible",IF(D12>1,"Vendido",0)) -> Vendido | BG12: =IF(AND(BF12="Vendido",E12>=0,AZ12=0),"Enganche Completado",IF(AND(BF12="Vendido",E12>=0,AZ12>0),"Superávit de Enganche",IF(AND(BF12="Apartamento Disponible",E12=0,AZ12=0),"Disponible","Cliente Atrasado"))) -> Superávit de Enganche | BI12: =COUNTIF(L12:AT12,">0.01") -> 26 | BJ12: =IF(AND(BG12="Cliente Atrasado",COUNTIF(L12:AT12,"<0.01")),DATEDIF(E12,AT$4+1,"m"),0) -> 0
B13: 204 | C13: Paula H. | D13: Alfonso Javier Miranda Ramon | E13: 45376 | F13: B2 | G13: 742700 | H13: 742700 | I13: =+G13-H13 -> 0 | J13: 37100 | K13: 4.PLAN DE PAGOS | L13: 0 | M13: 0 | N13: 0 | O13: 0 | P13: 0 | Q13: 0 | R13: 0 | S13: 0 | T13: 0 | U13: 0 | V13: 0 | W13: 0 | X13: 0 | Y13: 0 | Z13: 0 | AA13: 0 | AB13: 0 | AC13: 0 | AD13: 0 | AE13: 0 | AF13: 0 | AG13: 3000 | AH13: 3000 | AI13: 3000 | AJ13: 3000 | AK13: 0 | AL13: 3000 | AM13: 3000 | AN13: 0 | AO13: 0 | AP13: 3000 | AQ13: 16200 | AR13: 0 | AS13: 259806.91 | AX13: =SUM(L13:AV13) -> 297006.91 | AY13: =IFERROR((+AX13/BD13),0) -> 8.0055771 | AZ13: =+AX13-BD13 -> 259906.91 | BA13: =IFERROR((+AZ13/BD13),0) -> 7.0055771 | BB13: =+H13-AX13 -> 445693.09 | BC13: =+BB13/H13 -> 0.60009841 | BD13: =IF(BF13="Vendido",J13*1,IF(BF13="Disponible",J13*0,IF(BF13="Enganche Completado",J13*1,IF(BF13="Superávit de Enganche",J13*1,0)))) -> 37100 | BE13: =IF(D13=0,J13*0,BD13-AX13) -> -259906.91 | BF13: =IF(D13=0,"Apartamento Disponible",IF(D13>1,"Vendido",0)) -> Vendido | BG13: =IF(AND(BF13="Vendido",E13>=0,AZ13=0),"Enganche Completado",IF(AND(BF13="Vendido",E13>=0,AZ13>0),"Superávit de Enganche",IF(AND(BF13="Apartamento Disponible",E13=0,AZ13=0),"Disponible","Cliente Atrasado"))) -> Superávit de Enganche | BI13: =COUNTIF(L13:AT13,">0.01") -> 9 | BJ13: =IF(AND(BG13="Cliente Atrasado",COUNTIF(L13:AT13,"<0.01")),DATEDIF(E13,AT$4+1,"m"),0) -> 0
B14: 205 | C14: Paula H. | D14: Elfego Adonias Apen Son y Dany Alexis Gómez Ajuchán | E14: 45152 | F14: B2 | G14: 718200 | H14: 733200 | I14: =+G14-H14 -> -15000 | J14: 73320 | K14: 4.PLAN DE PAGOS | L14: 0 | M14: 0 | N14: 0 | O14: 0 | P14: 0 | Q14: 0 | R14: 0 | S14: 0 | T14: 0 | U14: 0 | V14: 0 | W14: 0 | X14: 0 | Y14: 0 | Z14: 6000 | AA14: 6000 | AB14: 6000 | AC14: 6000 | AD14: 6000 | AE14: 8000 | AF14: 8000 | AG14: 7000 | AH14: 6000 | AI14: 5700 | AJ14: 6000 | AK14: 8000 | AL14: 10000 | AM14: 12000 | AN14: 12000 | AO14: 10250 | AP14: 10250 | AQ14: 0 | AR14: 0 | AS14: 164970.28 | AX14: =SUM(L14:AV14) -> 298170.28 | AY14: =IFERROR((+AX14/BD14),0) -> 4.0666978 | AZ14: =+AX14-BD14 -> 224850.28 | BA14: =IFERROR((+AZ14/BD14),0) -> 3.0666978 | BB14: =+H14-AX14 -> 435029.72 | BC14: =+BB14/H14 -> 0.59333022 | BD14: =IF(BF14="Vendido",J14*1,IF(BF14="Disponible",J14*0,IF(BF14="Enganche Completado",J14*1,IF(BF14="Superávit de Enganche",J14*1,0)))) -> 73320 | BE14: =IF(D14=0,J14*0,BD14-AX14) -> -224850.28 | BF14: =IF(D14=0,"Apartamento Disponible",IF(D14>1,"Vendido",0)) -> Vendido | BG14: =IF(AND(BF14="Vendido",E14>=0,AZ14=0),"Enganche Completado",IF(AND(BF14="Vendido",E14>=0,AZ14>0),"Superávit de Enganche",IF(AND(BF14="Apartamento Disponible",E14=0,AZ14=0),"Disponible","Cliente Atrasado"))) -> Superávit de Enganche | BI14: =COUNTIF(L14:AT14,">0.01") -> 18 | BJ14: =IF(AND(BG14="Cliente Atrasado",COUNTIF(L14:AT14,"<0.01")),DATEDIF(E14,AT$4+1,"m"),0) -> 0
B15: 206 | C15: Efren Sanchez | D15: José Pablo Arana López | E15: 45636 | F15: A3 | G15: 948800 | H15: =680566.51+268233.49 -> 948800 | I15: =+G15-H15 -> 0 | J15: 47500 | K15: 2.RESERVADO | L15: 0 | M15: 0 | N15: 0 | O15: 0 | P15: 0 | Q15: 0 | R15: 0 | S15: 0 | T15: 0 | U15: 0 | V15: 0 | W15: 0 | X15: 0 | Y15: 0 | AA15: 0 | AB15: 0 | AC15: 0 | AD15: 0 | AE15: 0 | AF15: 0 | AG15: 0 | AH15: 0 | AI15: 0 | AJ15: 0 | AK15: 0 | AL15: 0 | AM15: 0 | AN15: 0 | AO15: 0 | AP15: =2500+2500 -> 5000 | AQ15: 0 | AR15: 0 | AS15: 20000 | AX15: =SUM(L15:AV15) -> 25000 | AY15: =IFERROR((+AX15/BD15),0) -> 0.52631579 | AZ15: =+AX15-BD15 -> -22500 | BA15: =IFERROR((+AZ15/BD15),0) -> -0.47368421 | BB15: =+H15-AX15 -> 923800 | BC15: =+BB15/H15 -> 0.97365093 | BD15: =IF(BF15="Vendido",J15*1,IF(BF15="Disponible",J15*0,IF(BF15="Enganche Completado",J15*1,IF(BF15="Superávit de Enganche",J15*1,0)))) -> 47500 | BE15: =IF(D15=0,J15*0,BD15-AX15) -> 22500 | BF15: =IF(D15=0,"Apartamento Disponible",IF(D15>1,"Vendido",0)) -> Vendido | BG15: =IF(AND(BF15="Vendido",E15>=0,AZ15=0),"Enganche Completado",IF(AND(BF15="Vendido",E15>=0,AZ15>0),"Superávit de Enganche",IF(AND(BF15="Apartamento Disponible",E15=0,AZ15=0),"Disponible","Cliente Atrasado"))) -> Cliente Atrasado | BI15: =COUNTIF(L15:AT15,">0.01") -> 2 | BJ15: 3
B16: 207 | C16: Paula H. | D16: Edwin Oswaldo Saenz Marroquin y Leslie Gabriela Senz | E16: 45347 | F16: A1 | G16: 769700 | H16: 769700 | I16: =+G16-H16 -> 0 | J16: 38500 | K16: 4.PLAN DE PAGOS | L16: 0 | M16: 0 | N16: 0 | O16: 0 | P16: 0 | Q16: 0 | R16: 0 | S16: 0 | T16: 0 | U16: 0 | V16: 0 | W16: 0 | X16: 0 | Y16: 0 | Z16: 0 | AA16: 0 | AB16: 0 | AC16: 0 | AD16: 0 | AE16: 0 | AF16: 5000 | AG16: 3700 | AH16: 7420.56 | AI16: 3700 | AJ16: 3700 | AK16: 3700 | AL16: 3700 | AM16: 3700 | AN16: 3700 | AO16: 3700 | AP16: =10000+10000+8500 -> 28500 | AQ16: 10000 | AR16: 220489.16 | AS16: 0 | AX16: =SUM(L16:AV16) -> 301009.72 | AY16: =IFERROR((+AX16/BD16),0) -> 7.8184343 | AZ16: =+AX16-BD16 -> 262509.72 | BA16: =IFERROR((+AZ16/BD16),0) -> 6.8184343 | BB16: =+H16-AX16 -> 468690.28 | BC16: =+BB16/H16 -> 0.60892592 | BD16: =IF(BF16="Vendido",J16*1,IF(BF16="Disponible",J16*0,IF(BF16="Enganche Completado",J16*1,IF(BF16="Superávit de Enganche",J16*1,0)))) -> 38500 | BE16: =IF(D16=0,J16*0,BD16-AX16) -> -262509.72 | BF16: =IF(D16=0,"Apartamento Disponible",IF(D16>1,"Vendido",0)) -> Vendido | BG16: =IF(AND(BF16="Vendido",E16>=0,AZ16=0),"Enganche Completado",IF(AND(BF16="Vendido",E16>=0,AZ16>0),"Superávit de Enganche",IF(AND(BF16="Apartamento Disponible",E16=0,AZ16=0),"Disponible","Cliente Atrasado"))) -> Superávit de Enganche | BI16: =COUNTIF(L16:AT16,">0.01") -> 13 | BJ16: =IF(AND(BG16="Cliente Atrasado",COUNTIF(L16:AT16,"<0.01")),DATEDIF(E16,AT$4+1,"m"),0) -> 0
B17: 208 | F17: C2 | G17: 650000 | H17: 650000 | I17: =+G17-H17 -> 0 | J17: 65000 | K17: 1.DISPONIBLE | L17: 0 | M17: 0 | N17: 0 | O17: 0 | P17: 0 | Q17: 0 | R17: 0 | S17: 0 | T17: 0 | U17: 0 | V17: 0 | W17: 0 | X17: 0 | Y17: 0 | Z17: 0 | AA17: 0 | AB17: 0 | AC17: 0 | AD17: 0 | AE17: 0 | AF17: 0 | AG17: 0 | AH17: 0 | AI17: 0 | AJ17: 0 | AK17: 0 | AL17: 0 | AM17: 0 | AN17: 0 | AO17: 0 | AP17: 0 | AQ17: 0 | AR17: 0 | AS17: 0 | AX17: =SUM(L17:AV17) -> 0 | AY17: =IFERROR((+AX17/BD17),0) -> 0 | AZ17: =+AX17-BD17 -> 0 | BA17: =IFERROR((+AZ17/BD17),0) -> 0 | BB17: =+H17-AX17 -> 650000 | BC17: =+BB17/H17 -> 1 | BD17: =IF(BF17="Vendido",J17*1,IF(BF17="Disponible",J17*0,IF(BF17="Enganche Completado",J17*1,IF(BF17="Superávit de Enganche",J17*1,0)))) -> 0 | BE17: =IF(D17=0,J17*0,BD17-AX17) -> 0 | BF17: =IF(D17=0,"Apartamento Disponible",IF(D17>1,"Vendido",0)) -> Apartamento Disponible | BG17: =IF(AND(BF17="Vendido",E17>=0,AZ17=0),"Enganche Completado",IF(AND(BF17="Vendido",E17>=0,AZ17>0),"Superávit de Enganche",IF(AND(BF17="Apartamento Disponible",E17=0,AZ17=0),"Disponible","Cliente Atrasado"))) -> Disponible | BI17: =COUNTIF(L17:AT17,">0.01") -> 0 | BJ17: =IF(AND(BG17="Cliente Atrasado",COUNTIF(L17:AT17,"<0.01")),DATEDIF(E17,AT$4+1,"m"),0) -> 0
B18: 301 | C18: Noemi M. | D18: Héctor Enrique Zacarias Illescas | E18: 44996 | F18: C2 | G18: 572700 | H18: 572700 | I18: =+G18-H18 -> 0 | J18: 58000 | K18: 4.PLAN DE PAGOS | L18: 0 | M18: 0 | N18: 0 | O18: 0 | P18: 0 | Q18: 0 | R18: 0 | S18: 0 | T18: 0 | U18: 7500 | V18: 10000 | W18: 20000 | X18: 0 | Y18: 10000 | Z18: 20000 | AA18: 12500 | AB18: 0 | AC18: 0 | AD18: 0 | AE18: 0 | AF18: 10000 | AG18: 0 | AH18: 30000 | AI18: 5000 | AJ18: 15000 | AK18: 0 | AL18: 0 | AM18: 20000 | AN18: 40000 | AO18: 0 | AP18: 0 | AQ18: 0 | AR18: 5000 | AS18: 0 | AT18: 58222.13 | AX18: =SUM(L18:AV18) -> 263222.13 | AY18: =IFERROR((+AX18/BD18),0) -> 4.5383126 | AZ18: =+AX18-BD18 -> 205222.13 | BA18: =IFERROR((+AZ18/BD18),0) -> 3.5383126 | BB18: =+H18-AX18 -> 309477.87 | BC18: =+BB18/H18 -> 0.54038392 | BD18: =IF(BF18="Vendido",J18*1,IF(BF18="Disponible",J18*0,IF(BF18="Enganche Completado",J18*1,IF(BF18="Superávit de Enganche",J18*1,0)))) -> 58000 | BE18: =IF(D18=0,J18*0,BD18-AX18) -> -205222.13 | BF18: =IF(D18=0,"Apartamento Disponible",IF(D18>1,"Vendido",0)) -> Vendido | BG18: =IF(AND(BF18="Vendido",E18>=0,AZ18=0),"Enganche Completado",IF(AND(BF18="Vendido",E18>=0,AZ18>0),"Superávit de Enganche",IF(AND(BF18="Apartamento Disponible",E18=0,AZ18=0),"Disponible","Cliente Atrasado"))) -> Superávit de Enganche | BI18: =COUNTIF(L18:AT18,">0.01") -> 14 | BJ18: =IF(AND(BG18="Cliente Atrasado",COUNTIF(L18:AT18,"<0.01")),DATEDIF(E18,AT$4+1,"m"),0) -> 0
B19: 302 | C19: Eder Veliz | D19: Guilmar Renato Najarro Díaz | E19: 45763 | F19: A1 | G19: 698000 | H19: 815000 | I19: =+G19-H19 -> -117000 | J19: 200000 | K19: 2. RESERVADO | L19: 0 | M19: 0 | N19: 0 | O19: 0 | P19: 0 | Q19: 0 | R19: 0 | S19: 0 | T19: 0 | U19: 0 | V19: 0 | W19: 0 | X19: 0 | Y19: 0 | Z19: 0 | AA19: 0 | AB19: 0 | AC19: 0 | AD19: 0 | AE19: 0 | AF19: 0 | AG19: 0 | AH19: 0 | AI19: 0 | AJ19: 0 | AK19: 0 | AL19: 0 | AM19: 0 | AN19: 0 | AO19: 0 | AP19: 0 | AQ19: 0 | AR19: 0 | AS19: 0 | AT19: 0 | AU19: 97500 | AX19: =SUM(L19:AV19) -> 97500 | AY19: =IFERROR((+AX19/BD19),0) -> 0.4875 | AZ19: =+AX19-BD19 -> -102500 | BA19: =IFERROR((+AZ19/BD19),0) -> -0.5125 | BB19: =+H19-AX19 -> 717500 | BC19: =+BB19/H19 -> 0.8803681 | BD19: =IF(BF19="Vendido",J19*1,IF(BF19="Disponible",J19*0,IF(BF19="Enganche Completado",J19*1,IF(BF19="Superávit de Enganche",J19*1,0)))) -> 200000 | BE19: =IF(D19=0,J19*0,BD19-AX19) -> 102500 | BF19: =IF(D19=0,"Apartamento Disponible",IF(D19>1,"Vendido",0)) -> Vendido | BG19: =IF(AND(BF19="Vendido",E19>=0,AZ19=0),"Enganche Completado",IF(AND(BF19="Vendido",E19>=0,AZ19>0),"Superávit de Enganche",IF(AND(BF19="Apartamento Disponible",E19=0,AZ19=0),"Disponible","Cliente Atrasado"))) -> Cliente Atrasado | BI19: =COUNTIF(L19:AT19,">0.01") -> 0 | BJ19: 20 | BK19: Dep. Reserva | BM19: Sin promesa firmada
B20: 303 | C20: Paula H. | D20: Sofia Maricela Ozaeta Góngora de Vásquez y Samuel Alejandro Vásquez Maldonado | E20: 45572 | F20: A3 | G20: 960966 | H20: 960966 | I20: =+G20-H20 -> 0 | J20: 48066 | K20: 4.PLAN DE PAGOS | L20: 0 | M20: 0 | N20: 0 | O20: 0 | P20: 0 | Q20: 0 | R20: 0 | S20: 0 | T20: 0 | U20: 0 | V20: 0 | W20: 0 | X20: 0 | Y20: 0 | AA20: 0 | AB20: 0 | AC20: 0 | AD20: 0 | AE20: 0 | AF20: 0 | AG20: 0 | AH20: 0 | AI20: 0 | AJ20: 0 | AK20: 0 | AL20: 0 | AM20: 0 | AN20: 48066 | AO20: 0 | AP20: 0 | AQ20: 0 | AR20: 0 | AS20: 366021.32 | AX20: =SUM(L20:AV20) -> 414087.32 | AY20: =IFERROR((+AX20/BD20),0) -> 8.6149736 | AZ20: =+AX20-BD20 -> 366021.32 | BA20: =IFERROR((+AZ20/BD20),0) -> 7.6149736 | BB20: =+H20-AX20 -> 546878.68 | BC20: =+BB20/H20 -> 0.56909264 | BD20: =IF(BF20="Vendido",J20*1,IF(BF20="Disponible",J20*0,IF(BF20="Enganche Completado",J20*1,IF(BF20="Superávit de Enganche",J20*1,0)))) -> 48066 | BE20: =IF(D20=0,J20*0,BD20-AX20) -> -366021.32 | BF20: =IF(D20=0,"Apartamento Disponible",IF(D20>1,"Vendido",0)) -> Vendido | BG20: =IF(AND(BF20="Vendido",E20>=0,AZ20=0),"Enganche Completado",IF(AND(BF20="Vendido",E20>=0,AZ20>0),"Superávit de Enganche",IF(AND(BF20="Apartamento Disponible",E20=0,AZ20=0),"Disponible","Cliente Atrasado"))) -> Superávit de Enganche | BI20: =COUNTIF(L20:AT20,">0.01") -> 2 | BJ20: =IF(AND(BG20="Cliente Atrasado",COUNTIF(L20:AT20,"<0.01")),DATEDIF(E20,AT$4+1,"m"),0) -> 0
B21: 304 | C21: Ricardo O. | D21: Luis Alfonso Ramirez Rivas | E21: 44963 | F21: B2 | G21: 655000 | H21: 655000 | I21: =+G21-H21 -> 0 | J21: 130000 | K21: 4.PLAN DE PAGOS | L21: 0 | M21: 0 | N21: 0 | O21: 0 | P21: 0 | Q21: 0 | R21: 0 | S21: 0 | T21: 70500 | U21: 3500 | V21: 3500 | W21: 3500 | X21: 3500 | Y21: 3500 | Z21: 3500 | AA21: 3500 | AB21: 3500 | AC21: 3500 | AD21: 3500 | AE21: 3500 | AF21: 3500 | AG21: 3500 | AH21: 3500 | AI21: 3500 | AJ21: 3500 | AK21: 3500 | AL21: 3500 | AM21: 0 | AN21: 0 | AO21: 0 | AP21: 0 | AQ21: 0 | AR21: 0 | AS21: 64894.55 | AX21: =SUM(L21:AV21) -> 198394.55 | AY21: =IFERROR((+AX21/BD21),0) -> 1.5261119 | AZ21: =+AX21-BD21 -> 68394.55 | BA21: =IFERROR((+AZ21/BD21),0) -> 0.52611192 | BB21: =+H21-AX21 -> 456605.45 | BC21: =+BB21/H21 -> 0.69710756 | BD21: =IF(BF21="Vendido",J21*1,IF(BF21="Disponible",J21*0,IF(BF21="Enganche Completado",J21*1,IF(BF21="Superávit de Enganche",J21*1,0)))) -> 130000 | BE21: =IF(D21=0,J21*0,BD21-AX21) -> -68394.55 | BF21: =IF(D21=0,"Apartamento Disponible",IF(D21>1,"Vendido",0)) -> Vendido | BG21: =IF(AND(BF21="Vendido",E21>=0,AZ21=0),"Enganche Completado",IF(AND(BF21="Vendido",E21>=0,AZ21>0),"Superávit de Enganche",IF(AND(BF21="Apartamento Disponible",E21=0,AZ21=0),"Disponible","Cliente Atrasado"))) -> Superávit de Enganche | BI21: =COUNTIF(L21:AT21,">0.01") -> 20 | BJ21: =IF(AND(BG21="Cliente Atrasado",COUNTIF(L21:AT21,"<0.01")),DATEDIF(E21,AT$4+1,"m"),0) -> 0
B22: 305 | C22: Ricardo O. | D22: Carol Analí Ovalle Valladares | E22: 44957 | F22: B2 | G22: 655000 | H22: 655000 | I22: =+G22-H22 -> 0 | J22: 100000 | K22: 4.PLAN DE PAGOS | L22: 0 | M22: 0 | N22: 0 | O22: 0 | P22: 0 | Q22: 0 | R22: 0 | S22: 5000 | T22: 5275 | U22: 5275 | V22: 5275 | W22: 5275 | X22: 5275 | Y22: 5275 | Z22: 5275 | AA22: 5275 | AB22: 5275 | AC22: 5275 | AD22: 5275 | AE22: 5275 | AF22: 5275 | AG22: 5275 | AH22: 5275 | AI22: 5275 | AJ22: 5275 | AK22: 5275 | AL22: 5275 | AM22: 105275 | AN22: 0 | AO22: 0 | AP22: 0 | AQ22: 0 | AR22: 0 | AS22: 9470.28 | AX22: =SUM(L22:AV22) -> 219970.28 | AY22: =IFERROR((+AX22/BD22),0) -> 2.1997028 | AZ22: =+AX22-BD22 -> 119970.28 | BA22: =IFERROR((+AZ22/BD22),0) -> 1.1997028 | BB22: =+H22-AX22 -> 435029.72 | BC22: =+BB22/H22 -> 0.66416751 | BD22: =IF(BF22="Vendido",J22*1,IF(BF22="Disponible",J22*0,IF(BF22="Enganche Completado",J22*1,IF(BF22="Superávit de Enganche",J22*1,0)))) -> 100000 | BE22: =IF(D22=0,J22*0,BD22-AX22) -> -119970.28 | BF22: =IF(D22=0,"Apartamento Disponible",IF(D22>1,"Vendido",0)) -> Vendido | BG22: =IF(AND(BF22="Vendido",E22>=0,AZ22=0),"Enganche Completado",IF(AND(BF22="Vendido",E22>=0,AZ22>0),"Superávit de Enganche",IF(AND(BF22="Apartamento Disponible",E22=0,AZ22=0),"Disponible","Cliente Atrasado"))) -> Superávit de Enganche | BI22: =COUNTIF(L22:AT22,">0.01") -> 22 | BJ22: =IF(AND(BG22="Cliente Atrasado",COUNTIF(L22:AT22,"<0.01")),DATEDIF(E22,AT$4+1,"m"),0) -> 0
B23: 306 | C23: Antonio R | D23: Lucy Rivas y Jefferson Daniel Mejía Jocol | E23: 45632 | F23: A3 | G23: 948800 | H23: 948800 | I23: =+G23-H23 -> 0 | J23: 47500 | K23: 4.PLAN DE PAGOS | L23: 0 | M23: 0 | N23: 0 | O23: 0 | P23: 0 | Q23: 0 | R23: 0 | S23: 0 | T23: 0 | U23: 0 | V23: 0 | W23: 0 | X23: 0 | Y23: 0 | Z23: 0 | AA23: 0 | AB23: 0 | AC23: 0 | AD23: 0 | AE23: 0 | AF23: 0 | AG23: 0 | AH23: 0 | AI23: 0 | AJ23: 0 | AK23: 0 | AL23: 0 | AM23: 0 | AN23: 0 | AO23: 0 | AP23: 5000 | AQ23: 28100 | AR23: 0 | AS23: 0 | AT23: 0 | AX23: =SUM(L23:AV23) -> 33100 | AY23: =IFERROR((+AX23/BD23),0) -> 0.69684211 | AZ23: =+AX23-BD23 -> -14400 | BA23: =IFERROR((+AZ23/BD23),0) -> -0.30315789 | BB23: =+H23-AX23 -> 915700 | BC23: =+BB23/H23 -> 0.96511383 | BD23: =IF(BF23="Vendido",J23*1,IF(BF23="Disponible",J23*0,IF(BF23="Enganche Completado",J23*1,IF(BF23="Superávit de Enganche",J23*1,0)))) -> 47500 | BE23: =IF(D23=0,J23*0,BD23-AX23) -> 14400 | BF23: =IF(D23=0,"Apartamento Disponible",IF(D23>1,"Vendido",0)) -> Vendido | BG23: =IF(AND(BF23="Vendido",E23>=0,AZ23=0),"Enganche Completado",IF(AND(BF23="Vendido",E23>=0,AZ23>0),"Superávit de Enganche",IF(AND(BF23="Apartamento Disponible",E23=0,AZ23=0),"Disponible","Cliente Atrasado"))) -> Cliente Atrasado | BI23: =COUNTIF(L23:AT23,">0.01") -> 2 | BJ23: 3
B24: 307 | C24: Eder V. | D24: Narda Guisela Guerrero Reyna | E24: 45635 | F24: A1 | G24: 810000 | H24: =581006.4+228993.6 -> 810000 | I24: =+G24-H24 -> 0 | J24: 40500 | K24: 4.PLAN DE PAGOS | L24: 0 | M24: 0 | N24: 0 | O24: 0 | P24: 0 | Q24: 0 | R24: 0 | S24: 0 | T24: 0 | U24: 0 | V24: 0 | W24: 0 | X24: 0 | Y24: 0 | Z24: 0 | AA24: 0 | AB24: 0 | AC24: 0 | AD24: 0 | AE24: 0 | AF24: 0 | AG24: 0 | AH24: 0 | AI24: 0 | AJ24: 0 | AK24: 0 | AL24: 0 | AM24: 0 | AN24: 0 | AO24: 0 | AP24: 5000 | AQ24: 0 | AR24: 0 | AS24: 35500 | AU24: =40500+138100 -> 178600 | AX24: =SUM(L24:AV24) -> 219100 | AY24: =IFERROR((+AX24/BD24),0) -> 5.4098765 | AZ24: =+AX24-BD24 -> 178600 | BA24: =IFERROR((+AZ24/BD24),0) -> 4.4098765 | BB24: =+H24-AX24 -> 590900 | BC24: =+BB24/H24 -> 0.72950617 | BD24: =IF(BF24="Vendido",J24*1,IF(BF24="Disponible",J24*0,IF(BF24="Enganche Completado",J24*1,IF(BF24="Superávit de Enganche",J24*1,0)))) -> 40500 | BE24: =IF(D24=0,J24*0,BD24-AX24) -> -178600 | BF24: =IF(D24=0,"Apartamento Disponible",IF(D24>1,"Vendido",0)) -> Vendido | BG24: =IF(AND(BF24="Vendido",E24>=0,AZ24=0),"Enganche Completado",IF(AND(BF24="Vendido",E24>=0,AZ24>0),"Superávit de Enganche",IF(AND(BF24="Apartamento Disponible",E24=0,AZ24=0),"Disponible","Cliente Atrasado"))) -> Superávit de Enganche | BI24: =COUNTIF(L24:AT24,">0.01") -> 2 | BJ24: =IF(AND(BG24="Cliente Atrasado",COUNTIF(L24:AT24,"<0.01")),DATEDIF(E24,AT$4+1,"m"),0) -> 0
B25: 308 | C25: Paula H. | D25: Rudy Antonio Hernández Ramos | E25: 45653 | F25: C2 | G25: 650000 | H25: 680000 | I25: =+G25-H25 -> -30000 | J25: 34000 | K25: 4.PLAN DE PAGOS | L25: 0 | M25: 0 | N25: 0 | O25: 0 | P25: 0 | Q25: 0 | R25: 0 | S25: 0 | T25: 0 | AG25: 0 | AH25: 0 | AI25: 0 | AJ25: 0 | AK25: 0 | AL25: 0 | AO25: 0 | AP25: 5000 | AQ25: 0 | AR25: 0 | AS25: 60000 | AX25: =SUM(L25:AV25) -> 65000 | AY25: =IFERROR((+AX25/BD25),0) -> 1.9117647 | AZ25: =+AX25-BD25 -> 31000 | BA25: =IFERROR((+AZ25/BD25),0) -> 0.91176471 | BB25: =+H25-AX25 -> 615000 | BC25: =+BB25/H25 -> 0.90441176 | BD25: =IF(BF25="Vendido",J25*1,IF(BF25="Disponible",J25*0,IF(BF25="Enganche Completado",J25*1,IF(BF25="Superávit de Enganche",J25*1,0)))) -> 34000 | BE25: =IF(D25=0,J25*0,BD25-AX25) -> -31000 | BF25: =IF(D25=0,"Apartamento Disponible",IF(D25>1,"Vendido",0)) -> Vendido | BG25: =IF(AND(BF25="Vendido",E25>=0,AZ25=0),"Enganche Completado",IF(AND(BF25="Vendido",E25>=0,AZ25>0),"Superávit de Enganche",IF(AND(BF25="Apartamento Disponible",E25=0,AZ25=0),"Disponible","Cliente Atrasado"))) -> Superávit de Enganche | BI25: =COUNTIF(L25:AT25,">0.01") -> 2 | BJ25: =IF(AND(BG25="Cliente Atrasado",COUNTIF(L25:AT25,"<0.01")),DATEDIF(E25,AT$4+1,"m"),0) -> 0
B26: 401 | C26: Noemi M. | D26: Héctor René Guzmán Morán | E26: 44880 | F26: C2 | G26: 547800 | H26: 547800 | I26: =+G26-H26 -> 0 | J26: 54780 | K26: 4.PLAN DE PAGOS | L26: 0 | M26: 0 | N26: 0 | O26: 0 | P26: 0 | Q26: 5000 | R26: 2480 | S26: 2480 | T26: 2480 | U26: 2480 | V26: 2480 | W26: 2480 | X26: 2480 | Y26: 2480 | Z26: 2480 | AA26: 2480 | AB26: 2480 | AC26: 2480 | AD26: 2480 | AE26: 2480 | AF26: 2480 | AG26: 2480 | AH26: 2480 | AI26: 2480 | AJ26: 2480 | AK26: 2660 | AL26: 0 | AM26: 0 | AN26: 2505 | AO26: 2505 | AP26: 2505 | AQ26: 2505 | AR26: 0 | AS26: 0 | AX26: =SUM(L26:AV26) -> 64800 | AY26: =IFERROR((+AX26/BD26),0) -> 1.1829135 | AZ26: =+AX26-BD26 -> 10020 | BA26: =IFERROR((+AZ26/BD26),0) -> 0.18291347 | BB26: =+H26-AX26 -> 483000 | BC26: =+BB26/H26 -> 0.88170865 | BD26: =IF(BF26="Vendido",J26*1,IF(BF26="Disponible",J26*0,IF(BF26="Enganche Completado",J26*1,IF(BF26="Superávit de Enganche",J26*1,0)))) -> 54780 | BE26: =IF(D26=0,J26*0,BD26-AX26) -> -10020 | BF26: =IF(D26=0,"Apartamento Disponible",IF(D26>1,"Vendido",0)) -> Vendido | BG26: =IF(AND(BF26="Vendido",E26>=0,AZ26=0),"Enganche Completado",IF(AND(BF26="Vendido",E26>=0,AZ26>0),"Superávit de Enganche",IF(AND(BF26="Apartamento Disponible",E26=0,AZ26=0),"Disponible","Cliente Atrasado"))) -> Superávit de Enganche | BI26: =COUNTIF(L26:AT26,">0.01") -> 25 | BJ26: =IF(AND(BG26="Cliente Atrasado",COUNTIF(L26:AT26,"<0.01")),DATEDIF(E26,AT$4+1,"m"),0) -> 0
B27: 402 | C27: Paula H. | D27: Luis Fernando Cifuentes Echeverria | E27: 45125 | F27: A1 | G27: 703900 | H27: 703900 | I27: =+G27-H27 -> 0 | J27: 70390 | K27: 4.PLAN DE PAGOS | L27: 0 | M27: 0 | N27: 0 | O27: 0 | P27: 0 | Q27: 0 | R27: 0 | S27: 0 | T27: 0 | U27: 0 | V27: 0 | W27: 0 | X27: 0 | Y27: 5000 | Z27: 9500 | AA27: 5500 | AB27: 5500 | AC27: 5500 | AD27: 5500 | AE27: 1500 | AF27: 5500 | AG27: 5500 | AH27: 5500 | AI27: 5500 | AJ27: 35500 | AK27: 35500 | AL27: 30000 | AM27: 30000 | AN27: 0 | AO27: 60000 | AP27: 30000 | AR27: 0 | AS27: 0 | AX27: =SUM(L27:AV27) -> 281000 | AY27: =IFERROR((+AX27/BD27),0) -> 3.9920443 | AZ27: =+AX27-BD27 -> 210610 | BA27: =IFERROR((+AZ27/BD27),0) -> 2.9920443 | BB27: =+H27-AX27 -> 422900 | BC27: =+BB27/H27 -> 0.60079557 | BD27: =IF(BF27="Vendido",J27*1,IF(BF27="Disponible",J27*0,IF(BF27="Enganche Completado",J27*1,IF(BF27="Superávit de Enganche",J27*1,0)))) -> 70390 | BE27: =IF(D27=0,J27*0,BD27-AX27) -> -210610 | BF27: =IF(D27=0,"Apartamento Disponible",IF(D27>1,"Vendido",0)) -> Vendido | BG27: =IF(AND(BF27="Vendido",E27>=0,AZ27=0),"Enganche Completado",IF(AND(BF27="Vendido",E27>=0,AZ27>0),"Superávit de Enganche",IF(AND(BF27="Apartamento Disponible",E27=0,AZ27=0),"Disponible","Cliente Atrasado"))) -> Superávit de Enganche | BI27: =COUNTIF(L27:AT27,">0.01") -> 17 | BJ27: =IF(AND(BG27="Cliente Atrasado",COUNTIF(L27:AT27,"<0.01")),DATEDIF(E27,AT$4+1,"m"),0) -> 0
B28: 403 | C28: Paula H. | D28: José Carlos Sanchez Jimenez | E28: 45761 | F28: A3 | G28: 948800 | H28: =691786.39+272655.61 -> 964442 | I28: =+G28-H28 -> -15642 | J28: 48242 | K28: 2. RESERVADO | L28: 0 | M28: 0 | N28: 0 | O28: 0 | P28: 0 | Q28: 0 | R28: 0 | S28: 0 | T28: 0 | U28: 0 | V28: 0 | W28: 0 | X28: 0 | Y28: 0 | Z28: 0 | AA28: 0 | AB28: 0 | AC28: 0 | AD28: 0 | AE28: 0 | AF28: 0 | AG28: 0 | AH28: 0 | AI28: 0 | AJ28: 0 | AK28: 0 | AL28: 0 | AM28: 0 | AN28: 0 | AO28: 0 | AP28: 0 | AQ28: 0 | AR28: 0 | AS28: 0 | AU28: 21621 | AX28: =SUM(L28:AV28) -> 21621 | AY28: =IFERROR((+AX28/BD28),0) -> 0.44817794 | AZ28: =+AX28-BD28 -> -26621 | BA28: =IFERROR((+AZ28/BD28),0) -> -0.55182206 | BB28: =+H28-AX28 -> 942821 | BC28: =+BB28/H28 -> 0.97758186 | BD28: =IF(BF28="Vendido",J28*1,IF(BF28="Disponible",J28*0,IF(BF28="Enganche Completado",J28*1,IF(BF28="Superávit de Enganche",J28*1,0)))) -> 48242 | BE28: =IF(D28=0,J28*0,BD28-AX28) -> 26621 | BF28: =IF(D28=0,"Apartamento Disponible",IF(D28>1,"Vendido",0)) -> Vendido | BG28: =IF(AND(BF28="Vendido",E28>=0,AZ28=0),"Enganche Completado",IF(AND(BF28="Vendido",E28>=0,AZ28>0),"Superávit de Enganche",IF(AND(BF28="Apartamento Disponible",E28=0,AZ28=0),"Disponible","Cliente Atrasado"))) -> Cliente Atrasado | BI28: =COUNTIF(L28:AT28,">0.01") -> 0 | BJ28: =IF(AND(BG28="Cliente Atrasado",COUNTIF(L28:AT28,"<0.01")),DATEDIF(E28,AT$4+1,"m"),0) -> 0 | BK28: Dep. Reserva | BM28: Sin promesa firmada
B29: 404 | C29: Ricardo O. | D29: Nancy Andrea Ovalle Valladares | E29: 44963 | F29: B2 | G29: 655000 | H29: 655000 | I29: =+G29-H29 -> 0 | J29: 65500 | K29: 4.PLAN DE PAGOS | L29: 0 | M29: 0 | N29: 0 | O29: 0 | P29: 0 | Q29: 0 | R29: 0 | S29: 0 | T29: 5000 | U29: 3500 | V29: 3617.76 | W29: 3500 | X29: 3500 | Y29: 3500 | Z29: 3500 | AA29: 7000 | AB29: 0 | AC29: 7000 | AD29: 3500 | AE29: 3500 | AF29: 0 | AG29: 3500 | AH29: 3500 | AI29: 3500 | AJ29: 3500 | AK29: 3500 | AL29: 882.24 | AM29: 0 | AN29: 0 | AO29: 0 | AP29: 0 | AQ29: 0 | AR29: 0 | AS29: 0 | AX29: =SUM(L29:AV29) -> 65500 | AY29: =IFERROR((+AX29/BD29),0) -> 1 | AZ29: =+AX29-BD29 -> 0 | BA29: =IFERROR((+AZ29/BD29),0) -> 0 | BB29: =+H29-AX29 -> 589500 | BC29: =+BB29/H29 -> 0.9 | BD29: =IF(BF29="Vendido",J29*1,IF(BF29="Disponible",J29*0,IF(BF29="Enganche Completado",J29*1,IF(BF29="Superávit de Enganche",J29*1,0)))) -> 65500 | BE29: =IF(D29=0,J29*0,BD29-AX29) -> 0 | BF29: =IF(D29=0,"Apartamento Disponible",IF(D29>1,"Vendido",0)) -> Vendido | BG29: =IF(AND(BF29="Vendido",E29>=0,AZ29=0),"Enganche Completado",IF(AND(BF29="Vendido",E29>=0,AZ29>0),"Superávit de Enganche",IF(AND(BF29="Apartamento Disponible",E29=0,AZ29=0),"Disponible","Cliente Atrasado"))) -> Enganche Completado | BI29: =COUNTIF(L29:AT29,">0.01") -> 17 | BJ29: =IF(AND(BG29="Cliente Atrasado",COUNTIF(L29:AT29,"<0.01")),DATEDIF(E29,AT$4+1,"m"),0) -> 0
B30: 405 | C30: Noemi M. | D30: Lester Eduardo Velasquez Dubon. | E30: 44956 | F30: B2 | G30: 655000 | H30: 655000 | I30: =+G30-H30 -> 0 | J30: 414500 | K30: 4.PLAN DE PAGOS | L30: 0 | M30: 0 | N30: 0 | O30: 0 | P30: 0 | Q30: 0 | R30: 0 | S30: 5000 | T30: 3500 | U30: 3500 | V30: 3500 | W30: 3500 | X30: 3500 | Y30: 3500 | Z30: 3500 | AA30: 3500 | AB30: 3500 | AC30: 3500 | AD30: 3500 | AE30: 3500 | AF30: 3500 | AG30: 3500 | AH30: 3500 | AI30: 3500 | AJ30: 3500 | AK30: 0 | AL30: 0 | AM30: 0 | AN30: 0 | AO30: 0 | AP30: 0 | AQ30: =252200+88000+74800+500 -> 415500 | AR30: 0 | AS30: 0 | AX30: =SUM(L30:AV30) -> 480000 | AY30: =IFERROR((+AX30/BD30),0) -> 1.1580217 | AZ30: =+AX30-BD30 -> 65500 | BA30: =IFERROR((+AZ30/BD30),0) -> 0.15802171 | BB30: =+H30-AX30 -> 175000 | BC30: =+BB30/H30 -> 0.26717557 | BD30: =IF(BF30="Vendido",J30*1,IF(BF30="Disponible",J30*0,IF(BF30="Enganche Completado",J30*1,IF(BF30="Superávit de Enganche",J30*1,0)))) -> 414500 | BE30: =IF(D30=0,J30*0,BD30-AX30) -> -65500 | BF30: =IF(D30=0,"Apartamento Disponible",IF(D30>1,"Vendido",0)) -> Vendido | BG30: =IF(AND(BF30="Vendido",E30>=0,AZ30=0),"Enganche Completado",IF(AND(BF30="Vendido",E30>=0,AZ30>0),"Superávit de Enganche",IF(AND(BF30="Apartamento Disponible",E30=0,AZ30=0),"Disponible","Cliente Atrasado"))) -> Superávit de Enganche | BI30: =COUNTIF(L30:AT30,">0.01") -> 19 | BJ30: =IF(AND(BG30="Cliente Atrasado",COUNTIF(L30:AT30,"<0.01")),DATEDIF(E30,AT$4+1,"m"),0) -> 0
B31: 406 | C31: Paula H. | D31: Gerson Merari Tubac Tepaz | E31: 45625 | F31: A3 | G31: 964442 | H31: 948800 | I31: =+G31-H31 -> 15642 | J31: 49500 | K31: 4.PLAN DE PAGOS | L31: 0 | M31: 0 | N31: 0 | O31: 0 | P31: 0 | Q31: 0 | R31: 0 | S31: 0 | T31: 0 | U31: 0 | V31: 0 | W31: 0 | X31: 0 | Y31: 0 | AA31: 0 | AB31: 0 | AC31: 0 | AD31: 0 | AE31: 0 | AF31: 0 | AG31: 0 | AH31: 0 | AI31: 0 | AJ31: 0 | AK31: 0 | AL31: 0 | AN31: 0 | AO31: =5000+22250 -> 27250 | AP31: 22250 | AQ31: 0 | AR31: 0 | AS31: 0 | AX31: =SUM(L31:AV31) -> 49500 | AY31: =IFERROR((+AX31/BD31),0) -> 1 | AZ31: =+AX31-BD31 -> 0 | BA31: =IFERROR((+AZ31/BD31),0) -> 0 | BB31: =+H31-AX31 -> 899300 | BC31: =+BB31/H31 -> 0.94782884 | BD31: =IF(BF31="Vendido",J31*1,IF(BF31="Disponible",J31*0,IF(BF31="Enganche Completado",J31*1,IF(BF31="Superávit de Enganche",J31*1,0)))) -> 49500 | BE31: =IF(D31=0,J31*0,BD31-AX31) -> 0 | BF31: =IF(D31=0,"Apartamento Disponible",IF(D31>1,"Vendido",0)) -> Vendido | BG31: =IF(AND(BF31="Vendido",E31>=0,AZ31=0),"Enganche Completado",IF(AND(BF31="Vendido",E31>=0,AZ31>0),"Superávit de Enganche",IF(AND(BF31="Apartamento Disponible",E31=0,AZ31=0),"Disponible","Cliente Atrasado"))) -> Enganche Completado | BI31: =COUNTIF(L31:AT31,">0.01") -> 2 | BJ31: =IF(AND(BG31="Cliente Atrasado",COUNTIF(L31:AT31,"<0.01")),DATEDIF(E31,AT$4+1,"m"),0) -> 0
B32: 407 | C32: Noemi M. | D32: Desireé Castro Rodríguez | E32: 44945 | F32: A1 | G32: 680000 | H32: 680000 | I32: =+G32-H32 -> 0 | J32: 68000 | K32: 4.PLAN DE PAGOS | L32: 0 | M32: 0 | N32: 0 | O32: 0 | P32: 0 | Q32: 0 | R32: 0 | S32: 5000 | T32: 3500 | U32: 3500 | V32: 3500 | W32: 3500 | X32: 3500 | Y32: 3500 | Z32: 3500 | AA32: 3500 | AB32: 3500 | AC32: 0 | AD32: 7000 | AE32: 3500 | AF32: 3500 | AG32: 3500 | AH32: 3500 | AI32: 3500 | AJ32: 3500 | AK32: 3500 | AL32: 0 | AM32: 0 | AN32: 0 | AO32: 0 | AP32: 0 | AQ32: 0 | AR32: 0 | AS32: 123008.17 | AX32: =SUM(L32:AV32) -> 191008.17 | AY32: =IFERROR((+AX32/BD32),0) -> 2.8089437 | AZ32: =+AX32-BD32 -> 123008.17 | BA32: =IFERROR((+AZ32/BD32),0) -> 1.8089437 | BB32: =+H32-AX32 -> 488991.83 | BC32: =+BB32/H32 -> 0.71910563 | BD32: =IF(BF32="Vendido",J32*1,IF(BF32="Disponible",J32*0,IF(BF32="Enganche Completado",J32*1,IF(BF32="Superávit de Enganche",J32*1,0)))) -> 68000 | BE32: =IF(D32=0,J32*0,BD32-AX32) -> -123008.17 | BF32: =IF(D32=0,"Apartamento Disponible",IF(D32>1,"Vendido",0)) -> Vendido | BG32: =IF(AND(BF32="Vendido",E32>=0,AZ32=0),"Enganche Completado",IF(AND(BF32="Vendido",E32>=0,AZ32>0),"Superávit de Enganche",IF(AND(BF32="Apartamento Disponible",E32=0,AZ32=0),"Disponible","Cliente Atrasado"))) -> Superávit de Enganche | BI32: =COUNTIF(L32:AT32,">0.01") -> 19 | BJ32: =IF(AND(BG32="Cliente Atrasado",COUNTIF(L32:AT32,"<0.01")),DATEDIF(E32,AT$4+1,"m"),0) -> 0
B33: 408 | C33: Lilian G. | D33: Luis Mariano Calderón Ponce/JOSE VICENTE CALDERON | E33: 44887 | F33: C2 | G33: 547800 | H33: 547800 | I33: =+G33-H33 -> 0 | J33: 54780 | K33: 4.PLAN DE PAGOS | L33: 0 | M33: 0 | N33: 0 | O33: 0 | P33: 0 | Q33: 5000 | R33: 2480.35 | S33: 2480 | T33: 2480 | U33: 2480 | V33: 2480 | W33: 2480 | X33: 2480 | Y33: 2480 | Z33: 2480 | AA33: 2480 | AB33: 2480 | AC33: 0 | AD33: 0 | AE33: 2480 | AF33: 0 | AG33: 2480 | AH33: 2480 | AI33: 2480 | AJ33: 4960 | AK33: 2480 | AL33: 2480 | AM33: 0 | AN33: 2695 | AO33: 0 | AP33: 0 | AQ33: 0 | AR33: 0 | AS33: 0 | AX33: =SUM(L33:AV33) -> 54815.35 | AY33: =IFERROR((+AX33/BD33),0) -> 1.0006453 | AZ33: =+AX33-BD33 -> 35.35 | BA33: =IFERROR((+AZ33/BD33),0) -> 0.00064530851 | BB33: =+H33-AX33 -> 492984.65 | BC33: =+BB33/H33 -> 0.89993547 | BD33: =IF(BF33="Vendido",J33*1,IF(BF33="Disponible",J33*0,IF(BF33="Enganche Completado",J33*1,IF(BF33="Superávit de Enganche",J33*1,0)))) -> 54780 | BE33: =IF(D33=0,J33*0,BD33-AX33) -> -35.35 | BF33: =IF(D33=0,"Apartamento Disponible",IF(D33>1,"Vendido",0)) -> Vendido | BG33: =IF(AND(BF33="Vendido",E33>=0,AZ33=0),"Enganche Completado",IF(AND(BF33="Vendido",E33>=0,AZ33>0),"Superávit de Enganche",IF(AND(BF33="Apartamento Disponible",E33=0,AZ33=0),"Disponible","Cliente Atrasado"))) -> Superávit de Enganche | BI33: =COUNTIF(L33:AT33,">0.01") -> 20 | BJ33: =IF(AND(BG33="Cliente Atrasado",COUNTIF(L33:AT33,"<0.01")),DATEDIF(E33,AT$4+1,"m"),0) -> 0
B34: 501 | C34: Noemi M. | D34: Nery Gamaliel Santos Moscoso | E34: 44820 | F34: C2 | G34: 547000 | H34: 547000 | I34: =+G34-H34 -> 0 | J34: 54700 | K34: 4.PLAN DE PAGOS | L34: 0 | M34: 0 | N34: 0 | O34: 5000 | P34: 2260 | Q34: 2260 | R34: 4520 | S34: 0 | T34: 2260 | U34: 3000 | V34: 3000 | W34: 3000 | X34: 3000 | Y34: 3000 | Z34: 3000 | AA34: 3000 | AB34: 0 | AC34: 2500 | AD34: 2500 | AE34: 0 | AF34: 0 | AG34: 0 | AH34: 7000 | AI34: 5000 | AJ34: 0 | AK34: 3500 | AL34: 0 | AM34: 0 | AN34: 0 | AO34: 0 | AP34: 0 | AQ34: 0 | AR34: 154113.55 | AS34: 0 | AX34: =SUM(L34:AV34) -> 211913.55 | AY34: =IFERROR((+AX34/BD34),0) -> 3.8741051 | AZ34: =+AX34-BD34 -> 157213.55 | BA34: =IFERROR((+AZ34/BD34),0) -> 2.8741051 | BB34: =+H34-AX34 -> 335086.45 | BC34: =+BB34/H34 -> 0.61258949 | BD34: =IF(BF34="Vendido",J34*1,IF(BF34="Disponible",J34*0,IF(BF34="Enganche Completado",J34*1,IF(BF34="Superávit de Enganche",J34*1,0)))) -> 54700 | BE34: =IF(D34=0,J34*0,BD34-AX34) -> -157213.55 | BF34: =IF(D34=0,"Apartamento Disponible",IF(D34>1,"Vendido",0)) -> Vendido | BG34: =IF(AND(BF34="Vendido",E34>=0,AZ34=0),"Enganche Completado",IF(AND(BF34="Vendido",E34>=0,AZ34>0),"Superávit de Enganche",IF(AND(BF34="Apartamento Disponible",E34=0,AZ34=0),"Disponible","Cliente Atrasado"))) -> Superávit de Enganche | BI34: =COUNTIF(L34:AT34,">0.01") -> 18 | BJ34: =IF(AND(BG34="Cliente Atrasado",COUNTIF(L34:AT34,"<0.01")),DATEDIF(E34,AT$4+1,"m"),0) -> 0
B35: 502 | C35: Noemi M. | D35: Carlos Jeffry López Esquivel | E35: 44949 | F35: A1 | G35: 688000 | H35: 688000 | I35: =+G35-H35 -> 0 | J35: 68800 | K35: 4.PLAN DE PAGOS | L35: 0 | M35: 0 | N35: 0 | O35: 0 | P35: 0 | Q35: 0 | R35: 0 | S35: 5000 | T35: 5000 | U35: 5000 | V35: 5000 | W35: 5000 | X35: 5000 | Y35: 5000 | Z35: 5000 | AA35: 5000 | AB35: 5000 | AC35: 5000 | AD35: 5000 | AE35: 5000 | AF35: 5000 | AG35: 5000 | AH35: 5000 | AI35: 0 | AJ35: 0 | AK35: 0 | AL35: 0 | AM35: 0 | AN35: 0 | AO35: 0 | AP35: 0 | AQ35: 0 | AR35: 0 | AS35: 110675.73 | AX35: =SUM(L35:AV35) -> 190675.73 | AY35: =IFERROR((+AX35/BD35),0) -> 2.7714496 | AZ35: =+AX35-BD35 -> 121875.73 | BA35: =IFERROR((+AZ35/BD35),0) -> 1.7714496 | BB35: =+H35-AX35 -> 497324.27 | BC35: =+BB35/H35 -> 0.72285504 | BD35: =IF(BF35="Vendido",J35*1,IF(BF35="Disponible",J35*0,IF(BF35="Enganche Completado",J35*1,IF(BF35="Superávit de Enganche",J35*1,0)))) -> 68800 | BE35: =IF(D35=0,J35*0,BD35-AX35) -> -121875.73 | BF35: =IF(D35=0,"Apartamento Disponible",IF(D35>1,"Vendido",0)) -> Vendido | BG35: =IF(AND(BF35="Vendido",E35>=0,AZ35=0),"Enganche Completado",IF(AND(BF35="Vendido",E35>=0,AZ35>0),"Superávit de Enganche",IF(AND(BF35="Apartamento Disponible",E35=0,AZ35=0),"Disponible","Cliente Atrasado"))) -> Superávit de Enganche | BI35: =COUNTIF(L35:AT35,">0.01") -> 17 | BJ35: =IF(AND(BG35="Cliente Atrasado",COUNTIF(L35:AT35,"<0.01")),DATEDIF(E35,AT$4+1,"m"),0) -> 0
B36: 503 | C36: Paula H. | D36: Enrique Virgilio Reyes | E36: 45341 | F36: A3 | G36: 989600 | H36: 989600 | I36: =+G36-H36 -> 0 | J36: 49500 | K36: 4.PLAN DE PAGOS | L36: 0 | M36: 0 | N36: 0 | O36: 0 | P36: 0 | Q36: 0 | R36: 0 | S36: 0 | T36: 0 | U36: 0 | V36: 0 | W36: 0 | X36: 0 | Y36: 0 | Z36: 0 | AA36: 0 | AB36: 0 | AC36: 0 | AD36: 0 | AE36: 0 | AF36: 5000 | AG36: 0 | AH36: 4900 | AI36: 0 | AJ36: 4900 | AK36: 9800 | AL36: 0 | AM36: 4900 | AN36: 0 | AO36: 0 | AP36: =4900+4900+4900 -> 14700 | AQ36: 0 | AR36: 0 | AS36: 15400 | AX36: =SUM(L36:AV36) -> 59600 | AY36: =IFERROR((+AX36/BD36),0) -> 1.2040404 | AZ36: =+AX36-BD36 -> 10100 | BA36: =IFERROR((+AZ36/BD36),0) -> 0.2040404 | BB36: =+H36-AX36 -> 930000 | BC36: =+BB36/H36 -> 0.93977365 | BD36: =IF(BF36="Vendido",J36*1,IF(BF36="Disponible",J36*0,IF(BF36="Enganche Completado",J36*1,IF(BF36="Superávit de Enganche",J36*1,0)))) -> 49500 | BE36: =IF(D36=0,J36*0,BD36-AX36) -> -10100 | BF36: =IF(D36=0,"Apartamento Disponible",IF(D36>1,"Vendido",0)) -> Vendido | BG36: =IF(AND(BF36="Vendido",E36>=0,AZ36=0),"Enganche Completado",IF(AND(BF36="Vendido",E36>=0,AZ36>0),"Superávit de Enganche",IF(AND(BF36="Apartamento Disponible",E36=0,AZ36=0),"Disponible","Cliente Atrasado"))) -> Superávit de Enganche | BI36: =COUNTIF(L36:AT36,">0.01") -> 7 | BJ36: =IF(AND(BG36="Cliente Atrasado",COUNTIF(L36:AT36,"<0.01")),DATEDIF(E36,AT$4+1,"m"),0) -> 0
B37: 504 | C37: Lilian G. | D37: Sindy Julissa Girón López | E37: 44840 | F37: B2 | G37: 665000 | H37: 665000 | I37: =+G37-H37 -> 0 | J37: 66500 | K37: 4.PLAN DE PAGOS | L37: 0 | M37: 0 | N37: 0 | O37: 0 | P37: 5000 | Q37: 2673 | R37: 2673 | S37: 2673 | T37: 5350 | U37: 2675 | V37: 0 | W37: 2675 | X37: 2675 | Y37: 2675 | Z37: 5350 | AA37: 0 | AB37: 2675 | AC37: 2675 | AD37: 2675 | AE37: 2675 | AF37: 2675 | AG37: 2675 | AH37: 0 | AI37: 5350 | AJ37: 2675 | AK37: 2675 | AL37: 0 | AM37: 2675 | AN37: 2656 | AO37: 0 | AQ37: 0 | AR37: 0 | AS37: 0 | AU37: 195000 | AX37: =SUM(L37:AV37) -> 261500 | AY37: =IFERROR((+AX37/BD37),0) -> 3.9323308 | AZ37: =+AX37-BD37 -> 195000 | BA37: =IFERROR((+AZ37/BD37),0) -> 2.9323308 | BB37: =+H37-AX37 -> 403500 | BC37: =+BB37/H37 -> 0.60676692 | BD37: =IF(BF37="Vendido",J37*1,IF(BF37="Disponible",J37*0,IF(BF37="Enganche Completado",J37*1,IF(BF37="Superávit de Enganche",J37*1,0)))) -> 66500 | BE37: =IF(D37=0,J37*0,BD37-AX37) -> -195000 | BF37: =IF(D37=0,"Apartamento Disponible",IF(D37>1,"Vendido",0)) -> Vendido | BG37: =IF(AND(BF37="Vendido",E37>=0,AZ37=0),"Enganche Completado",IF(AND(BF37="Vendido",E37>=0,AZ37>0),"Superávit de Enganche",IF(AND(BF37="Apartamento Disponible",E37=0,AZ37=0),"Disponible","Cliente Atrasado"))) -> Superávit de Enganche | BI37: =COUNTIF(L37:AT37,">0.01") -> 21 | BJ37: =IF(AND(BG37="Cliente Atrasado",COUNTIF(L37:AT37,"<0.01")),DATEDIF(E37,AT$4+1,"m"),0) -> 0
B38: 505 | C38: Eder V. | D38: Narda Guisela Guerrero Reyna | E38: 45614 | F38: B2 | G38: 815000 | H38: =581006.4+228993.6 -> 810000 | I38: =+G38-H38 -> 5000 | J38: 40500 | K38: 4.PLAN DE PAGOS | L38: 0 | M38: 0 | N38: 0 | O38: 0 | P38: 0 | Q38: 0 | R38: 0 | S38: 0 | T38: 0 | U38: 0 | V38: 0 | W38: 0 | X38: 0 | Y38: 0 | Z38: 0 | AA38: 0 | AB38: 0 | AC38: 0 | AD38: 0 | AE38: 0 | AF38: 0 | AG38: 0 | AH38: 0 | AI38: 0 | AJ38: 0 | AK38: 0 | AL38: 0 | AM38: 0 | AN38: 0 | AO38: 0 | AP38: 5000 | AQ38: 0 | AR38: 0 | AS38: 35500 | AU38: 5000 | AX38: =SUM(L38:AV38) -> 45500 | AY38: =IFERROR((+AX38/BD38),0) -> 1.1234568 | AZ38: =+AX38-BD38 -> 5000 | BA38: =IFERROR((+AZ38/BD38),0) -> 0.12345679 | BB38: =+H38-AX38 -> 764500 | BC38: =+BB38/H38 -> 0.94382716 | BD38: =IF(BF38="Vendido",J38*1,IF(BF38="Disponible",J38*0,IF(BF38="Enganche Completado",J38*1,IF(BF38="Superávit de Enganche",J38*1,0)))) -> 40500 | BE38: =IF(D38=0,J38*0,BD38-AX38) -> -5000 | BF38: =IF(D38=0,"Apartamento Disponible",IF(D38>1,"Vendido",0)) -> Vendido | BG38: =IF(AND(BF38="Vendido",E38>=0,AZ38=0),"Enganche Completado",IF(AND(BF38="Vendido",E38>=0,AZ38>0),"Superávit de Enganche",IF(AND(BF38="Apartamento Disponible",E38=0,AZ38=0),"Disponible","Cliente Atrasado"))) -> Superávit de Enganche | BI38: =COUNTIF(L38:AT38,">0.01") -> 2 | BJ38: =IF(AND(BG38="Cliente Atrasado",COUNTIF(L38:AT38,"<0.01")),DATEDIF(E38,AT$4+1,"m"),0) -> 0
B39: 506 | C39: Paula H. | D39: Ingrid Karina De León López | E39: 45461 | F39: A3 | G39: 980170.9 | H39: 948800 | I39: =+G39-H39 -> 31370.9 | J39: 47500 | K39: 4.PLAN DE PAGOS | L39: 0 | M39: 0 | N39: 0 | O39: 0 | P39: 0 | Q39: 0 | R39: 0 | S39: 0 | T39: 0 | U39: 0 | V39: 0 | W39: 0 | X39: 0 | Y39: 0 | Z39: 0 | AA39: 0 | AB39: 0 | AC39: 0 | AD39: 0 | AE39: 0 | AF39: 0 | AG39: 0 | AH39: 0 | AI39: 0 | AJ39: 5000 | AK39: 8500 | AL39: 8500 | AM39: 8500 | AN39: 8550 | AO39: =8450+31370.9 -> 39820.9 | AQ39: 0 | AR39: 0 | AS39: 0 | AX39: =SUM(L39:AV39) -> 78870.9 | AY39: =IFERROR((+AX39/BD39),0) -> 1.66044 | AZ39: =+AX39-BD39 -> 31370.9 | BA39: =IFERROR((+AZ39/BD39),0) -> 0.66044 | BB39: =+H39-AX39 -> 869929.1 | BC39: =+BB39/H39 -> 0.916873 | BD39: =IF(BF39="Vendido",J39*1,IF(BF39="Disponible",J39*0,IF(BF39="Enganche Completado",J39*1,IF(BF39="Superávit de Enganche",J39*1,0)))) -> 47500 | BE39: =IF(D39=0,J39*0,BD39-AX39) -> -31370.9 | BF39: =IF(D39=0,"Apartamento Disponible",IF(D39>1,"Vendido",0)) -> Vendido | BG39: =IF(AND(BF39="Vendido",E39>=0,AZ39=0),"Enganche Completado",IF(AND(BF39="Vendido",E39>=0,AZ39>0),"Superávit de Enganche",IF(AND(BF39="Apartamento Disponible",E39=0,AZ39=0),"Disponible","Cliente Atrasado"))) -> Superávit de Enganche | BI39: =COUNTIF(L39:AT39,">0.01") -> 6 | BJ39: =IF(AND(BG39="Cliente Atrasado",COUNTIF(L39:AT39,"<0.01")),DATEDIF(E39,AT$4+1,"m"),0) -> 0
B40: 507 | C40: Noemi M. | D40: William Joselito de León Nimatuj | E40: 44939 | F40: A1 | G40: 690000 | H40: 690000 | I40: =+G40-H40 -> 0 | J40: 69000 | K40: 4.PLAN DE PAGOS | L40: 0 | M40: 0 | N40: 0 | O40: 0 | P40: 0 | Q40: 0 | R40: 0 | S40: 5000 | T40: 10000 | U40: 20000 | V40: 0 | W40: 10000 | X40: 10000 | Y40: 0 | Z40: 0 | AA40: 0 | AB40: 40000 | AC40: 0 | AD40: 0 | AE40: 0 | AF40: 0 | AG40: 0 | AH40: 0 | AI40: 50000 | AJ40: 0 | AK40: 0 | AL40: 0 | AM40: 0 | AN40: 50000 | AO40: 50000 | AQ40: 0 | AR40: 0 | AS40: 0 | AX40: =SUM(L40:AV40) -> 245000 | AY40: =IFERROR((+AX40/BD40),0) -> 3.5507246 | AZ40: =+AX40-BD40 -> 176000 | BA40: =IFERROR((+AZ40/BD40),0) -> 2.5507246 | BB40: =+H40-AX40 -> 445000 | BC40: =+BB40/H40 -> 0.64492754 | BD40: =IF(BF40="Vendido",J40*1,IF(BF40="Disponible",J40*0,IF(BF40="Enganche Completado",J40*1,IF(BF40="Superávit de Enganche",J40*1,0)))) -> 69000 | BE40: =IF(D40=0,J40*0,BD40-AX40) -> -176000 | BF40: =IF(D40=0,"Apartamento Disponible",IF(D40>1,"Vendido",0)) -> Vendido | BG40: =IF(AND(BF40="Vendido",E40>=0,AZ40=0),"Enganche Completado",IF(AND(BF40="Vendido",E40>=0,AZ40>0),"Superávit de Enganche",IF(AND(BF40="Apartamento Disponible",E40=0,AZ40=0),"Disponible","Cliente Atrasado"))) -> Superávit de Enganche | BI40: =COUNTIF(L40:AT40,">0.01") -> 9 | BJ40: =IF(AND(BG40="Cliente Atrasado",COUNTIF(L40:AT40,"<0.01")),DATEDIF(E40,AT$4+1,"m"),0) -> 0
B41: 508 | C41: Paula H. | D41: Rudy Antonio Hernandez Ramos | E41: 45653 | F41: C2 | G41: 660000 | H41: 680000 | I41: =+G41-H41 -> -20000 | J41: 34000 | K41: 4.PLAN DE PAGOS | L41: 0 | M41: 0 | N41: 0 | O41: 0 | P41: 0 | Q41: 0 | R41: 0 | S41: 0 | T41: 0 | U41: 0 | V41: 0 | W41: 0 | X41: 0 | Y41: 0 | Z41: 0 | AA41: 0 | AB41: 0 | AC41: 0 | AD41: 0 | AE41: 0 | AF41: 0 | AG41: 0 | AH41: 0 | AI41: 0 | AJ41: 0 | AK41: 0 | AL41: 0 | AM41: 0 | AN41: 0 | AO41: 0 | AP41: 5000 | AQ41: 0 | AR41: 0 | AS41: 60000 | AX41: =SUM(L41:AV41) -> 65000 | AY41: =IFERROR((+AX41/BD41),0) -> 1.9117647 | AZ41: =+AX41-BD41 -> 31000 | BA41: =IFERROR((+AZ41/BD41),0) -> 0.91176471 | BB41: =+H41-AX41 -> 615000 | BC41: =+BB41/H41 -> 0.90441176 | BD41: =IF(BF41="Vendido",J41*1,IF(BF41="Disponible",J41*0,IF(BF41="Enganche Completado",J41*1,IF(BF41="Superávit de Enganche",J41*1,0)))) -> 34000 | BE41: =IF(D41=0,J41*0,BD41-AX41) -> -31000 | BF41: =IF(D41=0,"Apartamento Disponible",IF(D41>1,"Vendido",0)) -> Vendido | BG41: =IF(AND(BF41="Vendido",E41>=0,AZ41=0),"Enganche Completado",IF(AND(BF41="Vendido",E41>=0,AZ41>0),"Superávit de Enganche",IF(AND(BF41="Apartamento Disponible",E41=0,AZ41=0),"Disponible","Cliente Atrasado"))) -> Superávit de Enganche | BI41: =COUNTIF(L41:AT41,">0.01") -> 2 | BJ41: =IF(AND(BG41="Cliente Atrasado",COUNTIF(L41:AT41,"<0.01")),DATEDIF(E41,AT$4+1,"m"),0) -> 0
B42: 601 | C42: Francisco S. | D42: Maria del Carmen Corado Morales | E42: 44827 | F42: C2 | G42: 498000 | H42: 498000 | I42: =+G42-H42 -> 0 | J42: 49800 | K42: 4.PLAN DE PAGOS | L42: 0 | M42: 0 | N42: 0 | O42: 5000 | P42: 1947.83 | Q42: 1947.85 | R42: 1947.85 | S42: 1947.85 | T42: 1947.83 | U42: 1947.83 | V42: 1947.83 | W42: 1947.83 | X42: 1947.83 | Y42: 1947.83 | Z42: 1947.83 | AA42: 1947.83 | AB42: 1947.83 | AC42: 1947.83 | AD42: 1947.83 | AE42: 1947.83 | AF42: 1947.83 | AG42: 1947.83 | AH42: 1947.83 | AI42: 1947.83 | AJ42: 1947.83 | AK42: 1947.83 | AL42: 1947.83 | AM42: 2007.83 | AN42: 0 | AO42: 0 | AP42: 3192.02 | AQ42: 0 | AR42: 109812.63 | AS42: 0 | AX42: =SUM(L42:AV42) -> 164812.63 | AY42: =IFERROR((+AX42/BD42),0) -> 3.3094906 | AZ42: =+AX42-BD42 -> 115012.63 | BA42: =IFERROR((+AZ42/BD42),0) -> 2.3094906 | BB42: =+H42-AX42 -> 333187.37 | BC42: =+BB42/H42 -> 0.66905094 | BD42: =IF(BF42="Vendido",J42*1,IF(BF42="Disponible",J42*0,IF(BF42="Enganche Completado",J42*1,IF(BF42="Superávit de Enganche",J42*1,0)))) -> 49800 | BE42: =IF(D42=0,J42*0,BD42-AX42) -> -115012.63 | BF42: =IF(D42=0,"Apartamento Disponible",IF(D42>1,"Vendido",0)) -> Vendido | BG42: =IF(AND(BF42="Vendido",E42>=0,AZ42=0),"Enganche Completado",IF(AND(BF42="Vendido",E42>=0,AZ42>0),"Superávit de Enganche",IF(AND(BF42="Apartamento Disponible",E42=0,AZ42=0),"Disponible","Cliente Atrasado"))) -> Superávit de Enganche | BI42: =COUNTIF(L42:AT42,">0.01") -> 27 | BJ42: =IF(AND(BG42="Cliente Atrasado",COUNTIF(L42:AT42,"<0.01")),DATEDIF(E42,AT$4+1,"m"),0) -> 0
B43: 602 | C43: Francisco S. | D43: Lucy Abigail Mendoza Fuentes | E43: 44880 | F43: A1 | G43: 698000 | H43: 698000 | I43: =+G43-H43 -> 0 | J43: 69800 | K43: 4.PLAN DE PAGOS | L43: 0 | M43: 0 | N43: 0 | O43: 0 | P43: 0 | Q43: 5000 | R43: 3240 | S43: 3240 | T43: 3240 | U43: 3240 | V43: 3240 | W43: 3240 | X43: 3240 | Y43: 3240 | Z43: 3240 | AA43: 3240 | AB43: 3240 | AC43: 3240 | AD43: 3240 | AE43: 3240 | AF43: 3240 | AG43: 3240 | AH43: 3240 | AI43: 3240 | AJ43: 3240 | AK43: 3240 | AL43: 3240 | AM43: 3240 | AN43: 3240 | AO43: 3240 | AP43: 0 | AQ43: 40 | AR43: 0 | AS43: 146917.89 | AX43: =SUM(L43:AV43) -> 229717.89 | AY43: =IFERROR((+AX43/BD43),0) -> 3.2910872 | AZ43: =+AX43-BD43 -> 159917.89 | BA43: =IFERROR((+AZ43/BD43),0) -> 2.2910872 | BB43: =+H43-AX43 -> 468282.11 | BC43: =+BB43/H43 -> 0.67089128 | BD43: =IF(BF43="Vendido",J43*1,IF(BF43="Disponible",J43*0,IF(BF43="Enganche Completado",J43*1,IF(BF43="Superávit de Enganche",J43*1,0)))) -> 69800 | BE43: =IF(D43=0,J43*0,BD43-AX43) -> -159917.89 | BF43: =IF(D43=0,"Apartamento Disponible",IF(D43>1,"Vendido",0)) -> Vendido | BG43: =IF(AND(BF43="Vendido",E43>=0,AZ43=0),"Enganche Completado",IF(AND(BF43="Vendido",E43>=0,AZ43>0),"Superávit de Enganche",IF(AND(BF43="Apartamento Disponible",E43=0,AZ43=0),"Disponible","Cliente Atrasado"))) -> Superávit de Enganche | BI43: =COUNTIF(L43:AT43,">0.01") -> 27 | BJ43: =IF(AND(BG43="Cliente Atrasado",COUNTIF(L43:AT43,"<0.01")),DATEDIF(E43,AT$4+1,"m"),0) -> 0
B44: 603 | C44: Francisco S. | D44: Werny Jose Ortiz Alegria | E44: 45614 | F44: A3 | G44: 961882.4 | H44: 1002682.4 | I44: =+G44-H44 -> -40800 | J44: 80682.4 | K44: 4.PLAN DE PAGOS | L44: 0 | M44: 0 | N44: 0 | O44: 0 | P44: 0 | Q44: 0 | R44: 0 | S44: 0 | T44: 0 | U44: 0 | V44: 0 | W44: 0 | X44: 0 | Y44: 0 | Z44: 0 | AA44: 0 | AB44: 0 | AC44: 0 | AD44: 0 | AE44: 0 | AF44: 0 | AG44: 0 | AH44: 0 | AI44: 0 | AJ44: 0 | AK44: 0 | AL44: 0 | AM44: 0 | AN44: 0 | AO44: 0 | AP44: 7050 | AQ44: 82.4 | AR44: 324384.35 | AS44: 0 | AX44: =SUM(L44:AV44) -> 331516.75 | AY44: =IFERROR((+AX44/BD44),0) -> 4.1089104 | AZ44: =+AX44-BD44 -> 250834.35 | BA44: =IFERROR((+AZ44/BD44),0) -> 3.1089104 | BB44: =+H44-AX44 -> 671165.65 | BC44: =+BB44/H44 -> 0.66937013 | BD44: =IF(BF44="Vendido",J44*1,IF(BF44="Disponible",J44*0,IF(BF44="Enganche Completado",J44*1,IF(BF44="Superávit de Enganche",J44*1,0)))) -> 80682.4 | BE44: =IF(D44=0,J44*0,BD44-AX44) -> -250834.35 | BF44: =IF(D44=0,"Apartamento Disponible",IF(D44>1,"Vendido",0)) -> Vendido | BG44: =IF(AND(BF44="Vendido",E44>=0,AZ44=0),"Enganche Completado",IF(AND(BF44="Vendido",E44>=0,AZ44>0),"Superávit de Enganche",IF(AND(BF44="Apartamento Disponible",E44=0,AZ44=0),"Disponible","Cliente Atrasado"))) -> Superávit de Enganche | BI44: =COUNTIF(L44:AT44,">0.01") -> 3 | BJ44: =IF(AND(BG44="Cliente Atrasado",COUNTIF(L44:AT44,"<0.01")),DATEDIF(E44,AT$4+1,"m"),0) -> 0
B45: 604 | C45: Paula H. | D45: Carlos Ovaldo Godinez y Godinez | E45: 45322 | F45: B2 | G45: 747264 | H45: 747264 | I45: =+G45-H45 -> 0 | J45: 747264 | K45: 4.PLAN DE PAGOS | L45: 0 | M45: 0 | N45: 0 | O45: 0 | P45: 0 | Q45: 0 | R45: 0 | S45: 0 | T45: 0 | U45: 0 | V45: 0 | W45: 0 | X45: 0 | Y45: 0 | Z45: 0 | AA45: 0 | AB45: 0 | AC45: 0 | AD45: 0 | AE45: 5000 | AF45: 0 | AG45: 3500 | AH45: 3500 | AI45: 3500 | AJ45: 3500 | AK45: 728264 | AL45: 0 | AM45: 0 | AN45: 0 | AO45: 0 | AP45: 0 | AQ45: 0 | AR45: 0 | AS45: 0 | AX45: =SUM(L45:AV45) -> 747264 | AY45: =IFERROR((+AX45/BD45),0) -> 1 | AZ45: =+AX45-BD45 -> 0 | BA45: =IFERROR((+AZ45/BD45),0) -> 0 | BB45: =+H45-AX45 -> 0 | BC45: =+BB45/H45 -> 0 | BD45: =IF(BF45="Vendido",J45*1,IF(BF45="Disponible",J45*0,IF(BF45="Enganche Completado",J45*1,IF(BF45="Superávit de Enganche",J45*1,0)))) -> 747264 | BE45: =IF(D45=0,J45*0,BD45-AX45) -> 0 | BF45: =IF(D45=0,"Apartamento Disponible",IF(D45>1,"Vendido",0)) -> Vendido | BG45: =IF(AND(BF45="Vendido",E45>=0,AZ45=0),"Enganche Completado",IF(AND(BF45="Vendido",E45>=0,AZ45>0),"Superávit de Enganche",IF(AND(BF45="Apartamento Disponible",E45=0,AZ45=0),"Disponible","Cliente Atrasado"))) -> Enganche Completado | BI45: =COUNTIF(L45:AT45,">0.01") -> 6 | BJ45: =IF(AND(BG45="Cliente Atrasado",COUNTIF(L45:AT45,"<0.01")),DATEDIF(E45,AT$4+1,"m"),0) -> 0
B46: 605 | C46: Antonio R | D46: Lauriano Figueroa Del Cid | E46: 45647 | F46: B2 | G46: 665000 | H46: 850000 | I46: =+G46-H46 -> -185000 | J46: 40900 | K46: 4.PLAN DE PAGOS | L46: 0 | M46: 0 | N46: 0 | O46: 0 | P46: 0 | Q46: 0 | R46: 0 | S46: 0 | T46: 0 | U46: 0 | V46: 0 | W46: 0 | X46: 0 | Y46: 0 | Z46: 0 | AA46: 0 | AB46: 0 | AC46: 0 | AD46: 0 | AE46: 0 | AF46: 0 | AG46: 0 | AH46: 0 | AI46: 0 | AJ46: 0 | AK46: 0 | AL46: 0 | AM46: 0 | AN46: 0 | AO46: 0 | AP46: 5000 | AQ46: 0 | AR46: 35900 | AS46: 0 | AX46: =SUM(L46:AV46) -> 40900 | AY46: =IFERROR((+AX46/BD46),0) -> 1 | AZ46: =+AX46-BD46 -> 0 | BA46: =IFERROR((+AZ46/BD46),0) -> 0 | BB46: =+H46-AX46 -> 809100 | BC46: =+BB46/H46 -> 0.95188235 | BD46: =IF(BF46="Vendido",J46*1,IF(BF46="Disponible",J46*0,IF(BF46="Enganche Completado",J46*1,IF(BF46="Superávit de Enganche",J46*1,0)))) -> 40900 | BE46: =IF(D46=0,J46*0,BD46-AX46) -> 0 | BF46: =IF(D46=0,"Apartamento Disponible",IF(D46>1,"Vendido",0)) -> Vendido | BG46: =IF(AND(BF46="Vendido",E46>=0,AZ46=0),"Enganche Completado",IF(AND(BF46="Vendido",E46>=0,AZ46>0),"Superávit de Enganche",IF(AND(BF46="Apartamento Disponible",E46=0,AZ46=0),"Disponible","Cliente Atrasado"))) -> Enganche Completado | BI46: =COUNTIF(L46:AT46,">0.01") -> 2 | BJ46: =IF(AND(BG46="Cliente Atrasado",COUNTIF(L46:AT46,"<0.01")),DATEDIF(E46,AT$4+1,"m"),0) -> 0
B47: 606 | C47: Paula H. | D47: Irasema Dilian Magaña Muñoz | E47: 45521 | F47: A3 | G47: 989600 | H47: =49400+940200 -> 989600 | I47: =+G47-H47 -> 0 | J47: 49400 | K47: 4.PLAN DE PAGOS | L47: 0 | M47: 0 | N47: 0 | O47: 0 | P47: 0 | Q47: 0 | R47: 0 | S47: 0 | T47: 0 | U47: 0 | V47: 0 | W47: 0 | X47: 0 | Y47: 0 | Z47: 0 | AA47: 0 | AB47: 0 | AC47: 0 | AD47: 0 | AE47: 0 | AF47: 0 | AG47: 0 | AH47: 0 | AI47: 0 | AJ47: 0 | AK47: 0 | AL47: 5000 | AM47: 0 | AN47: 0 | AO47: =38000+32000+19900 -> 89900 | AP47: 0 | AQ47: 0 | AR47: 0 | AS47: 302993.04 | AX47: =SUM(L47:AV47) -> 397893.04 | AY47: =IFERROR((+AX47/BD47),0) -> 8.054515 | AZ47: =+AX47-BD47 -> 348493.04 | BA47: =IFERROR((+AZ47/BD47),0) -> 7.054515 | BB47: =+H47-AX47 -> 591706.96 | BC47: =+BB47/H47 -> 0.59792538 | BD47: =IF(BF47="Vendido",J47*1,IF(BF47="Disponible",J47*0,IF(BF47="Enganche Completado",J47*1,IF(BF47="Superávit de Enganche",J47*1,0)))) -> 49400 | BE47: =IF(D47=0,J47*0,BD47-AX47) -> -348493.04 | BF47: =IF(D47=0,"Apartamento Disponible",IF(D47>1,"Vendido",0)) -> Vendido | BG47: =IF(AND(BF47="Vendido",E47>=0,AZ47=0),"Enganche Completado",IF(AND(BF47="Vendido",E47>=0,AZ47>0),"Superávit de Enganche",IF(AND(BF47="Apartamento Disponible",E47=0,AZ47=0),"Disponible","Cliente Atrasado"))) -> Superávit de Enganche | BI47: =COUNTIF(L47:AT47,">0.01") -> 3 | BJ47: =IF(AND(BG47="Cliente Atrasado",COUNTIF(L47:AT47,"<0.01")),DATEDIF(E47,AT$4+1,"m"),0) -> 0
B48: 607 | C48: Noemi M. | D48: Alex André Cruz Caal | E48: 44859 | F48: A1 | G48: 690000 | H48: 676200 | I48: =+G48-H48 -> 13800 | J48: 676200 | K48: 4.PLAN DE PAGOS | L48: 0 | M48: 0 | N48: 0 | O48: 0 | P48: 338100 | Q48: 0 | R48: 0 | S48: 0 | T48: 0 | U48: 0 | V48: 0 | W48: 0 | X48: 0 | Y48: 0 | Z48: 0 | AA48: 0 | AB48: 0 | AC48: 0 | AD48: 0 | AE48: 0 | AF48: 0 | AG48: 0 | AH48: 0 | AI48: 0 | AJ48: 0 | AK48: 0 | AL48: 0 | AM48: 0 | AN48: 0 | AO48: 0 | AP48: 0 | AQ48: =89050+89050+100000+65000 -> 343100 | AR48: 0 | AX48: =SUM(L48:AV48) -> 681200 | AY48: =IFERROR((+AX48/BD48),0) -> 1.0073943 | AZ48: =+AX48-BD48 -> 5000 | BA48: =IFERROR((+AZ48/BD48),0) -> 0.0073942621 | BB48: =+H48-AX48 -> -5000 | BC48: =+BB48/H48 -> -0.0073942621 | BD48: =IF(BF48="Vendido",J48*1,IF(BF48="Disponible",J48*0,IF(BF48="Enganche Completado",J48*1,IF(BF48="Superávit de Enganche",J48*1,0)))) -> 676200 | BE48: =IF(D48=0,J48*0,BD48-AX48) -> -5000 | BF48: =IF(D48=0,"Apartamento Disponible",IF(D48>1,"Vendido",0)) -> Vendido | BG48: =IF(AND(BF48="Vendido",E48>=0,AZ48=0),"Enganche Completado",IF(AND(BF48="Vendido",E48>=0,AZ48>0),"Superávit de Enganche",IF(AND(BF48="Apartamento Disponible",E48=0,AZ48=0),"Disponible","Cliente Atrasado"))) -> Superávit de Enganche | BI48: =COUNTIF(L48:AT48,">0.01") -> 2 | BJ48: =IF(AND(BG48="Cliente Atrasado",COUNTIF(L48:AT48,"<0.01")),DATEDIF(E48,AT$4+1,"m"),0) -> 0
B49: 608 | C49: Noemi M. | D49: Kateryn Gabriela Quinon Reyes de Marroquin | E49: 44801 | F49: C2 | G49: 498000 | H49: 498000 | I49: =+G49-H49 -> 0 | J49: 49800 | K49: 4.PLAN DE PAGOS | L49: 0 | M49: 0 | N49: 5000 | O49: 2000 | P49: 2000 | Q49: 2000 | R49: 2000 | S49: 2000 | T49: 2000 | U49: 2000 | V49: 2000 | W49: 2000 | X49: 2000 | Y49: 2000 | Z49: 2000 | AA49: 2000 | AB49: 2000 | AC49: 2000 | AD49: 2000 | AE49: 2000 | AF49: 2000 | AG49: 2000 | AH49: 2000 | AI49: 2000 | AJ49: 2800 | AK49: 2000 | AL49: 2000 | AM49: 2000 | AN49: 2000 | AO49: 2000 | AP49: 2000 | AQ49: 0 | AR49: 0 | AS49: 103185.97 | AX49: =SUM(L49:AV49) -> 164985.97 | AY49: =IFERROR((+AX49/BD49),0) -> 3.3129713 | AZ49: =+AX49-BD49 -> 115185.97 | BA49: =IFERROR((+AZ49/BD49),0) -> 2.3129713 | BB49: =+H49-AX49 -> 333014.03 | BC49: =+BB49/H49 -> 0.66870287 | BD49: =IF(BF49="Vendido",J49*1,IF(BF49="Disponible",J49*0,IF(BF49="Enganche Completado",J49*1,IF(BF49="Superávit de Enganche",J49*1,0)))) -> 49800 | BE49: =IF(D49=0,J49*0,BD49-AX49) -> -115185.97 | BF49: =IF(D49=0,"Apartamento Disponible",IF(D49>1,"Vendido",0)) -> Vendido | BG49: =IF(AND(BF49="Vendido",E49>=0,AZ49=0),"Enganche Completado",IF(AND(BF49="Vendido",E49>=0,AZ49>0),"Superávit de Enganche",IF(AND(BF49="Apartamento Disponible",E49=0,AZ49=0),"Disponible","Cliente Atrasado"))) -> Superávit de Enganche | BI49: =COUNTIF(L49:AT49,">0.01") -> 30 | BJ49: =IF(AND(BG49="Cliente Atrasado",COUNTIF(L49:AT49,"<0.01")),DATEDIF(E49,AT$4+1,"m"),0) -> 0
B50: 701 | C50: Noemi M. | D50: Rony Hanley Chalí Ramos | E50: 44802 | F50: C2 | G50: 498000 | H50: 498000 | I50: =+G50-H50 -> 0 | J50: 250000 | K50: 4.PLAN DE PAGOS | L50: 0 | M50: 0 | N50: 5000 | O50: 187725 | P50: 8175 | Q50: 0 | R50: 2725 | S50: 5450 | T50: 2725 | U50: 2725 | V50: 2725 | W50: 2725 | X50: 2725 | Y50: 2725 | Z50: 2725 | AA50: 2725 | AB50: 2725 | AC50: 0 | AD50: 5450 | AE50: 0 | AF50: 2725 | AG50: 2725 | AH50: 2725 | AI50: 2775 | AJ50: 0 | AK50: 0 | AL50: 0 | AM50: 0 | AN50: 0 | AO50: 0 | AP50: 0 | AQ50: 0 | AR50: 0 | AS50: 0 | AX50: =SUM(L50:AV50) -> 250000 | AY50: =IFERROR((+AX50/BD50),0) -> 1 | AZ50: =+AX50-BD50 -> 0 | BA50: =IFERROR((+AZ50/BD50),0) -> 0 | BB50: =+H50-AX50 -> 248000 | BC50: =+BB50/H50 -> 0.49799197 | BD50: =IF(BF50="Vendido",J50*1,IF(BF50="Disponible",J50*0,IF(BF50="Enganche Completado",J50*1,IF(BF50="Superávit de Enganche",J50*1,0)))) -> 250000 | BE50: =IF(D50=0,J50*0,BD50-AX50) -> 0 | BF50: =IF(D50=0,"Apartamento Disponible",IF(D50>1,"Vendido",0)) -> Vendido | BG50: =IF(AND(BF50="Vendido",E50>=0,AZ50=0),"Enganche Completado",IF(AND(BF50="Vendido",E50>=0,AZ50>0),"Superávit de Enganche",IF(AND(BF50="Apartamento Disponible",E50=0,AZ50=0),"Disponible","Cliente Atrasado"))) -> Enganche Completado | BI50: =COUNTIF(L50:AT50,">0.01") -> 19 | BJ50: =IF(AND(BG50="Cliente Atrasado",COUNTIF(L50:AT50,"<0.01")),DATEDIF(E50,AT$4+1,"m"),0) -> 0
B51: 702 | C51: Noemi M. | D51: Julio César Chávez Mancio | E51: 44861 | F51: A1 | G51: 698000 | H51: 698000 | I51: =+G51-H51 -> 0 | J51: 69800 | K51: 4.PLAN DE PAGOS | L51: 0 | M51: 0 | N51: 0 | O51: 0 | P51: 5000 | Q51: 3085.71 | R51: 3085.71 | S51: 3085.71 | T51: 0 | U51: 6171.42 | V51: 3085.71 | W51: 3085.71 | X51: 0 | Y51: 3085.71 | Z51: 3085.71 | AA51: 0 | AB51: 0 | AC51: 6171.42 | AD51: 0 | AE51: 6171.42 | AF51: 3085.71 | AG51: 3085.71 | AH51: 0 | AI51: 6171.42 | AJ51: 3085.71 | AK51: 3085.71 | AL51: 0 | AM51: 0 | AN51: 0 | AO51: 0 | AP51: 0 | AQ51: 0 | AR51: 3085.71 | AS51: 0 | AT51: 0 | AU51: 3085.8 | AX51: =SUM(L51:AV51) -> 69800 | AY51: =IFERROR((+AX51/BD51),0) -> 1 | AZ51: =+AX51-BD51 -> 0 | BA51: =IFERROR((+AZ51/BD51),0) -> 0 | BB51: =+H51-AX51 -> 628200 | BC51: =+BB51/H51 -> 0.9 | BD51: =IF(BF51="Vendido",J51*1,IF(BF51="Disponible",J51*0,IF(BF51="Enganche Completado",J51*1,IF(BF51="Superávit de Enganche",J51*1,0)))) -> 69800 | BE51: =IF(D51=0,J51*0,BD51-AX51) -> 0 | BF51: =IF(D51=0,"Apartamento Disponible",IF(D51>1,"Vendido",0)) -> Vendido | BG51: =IF(AND(BF51="Vendido",E51>=0,AZ51=0),"Enganche Completado",IF(AND(BF51="Vendido",E51>=0,AZ51>0),"Superávit de Enganche",IF(AND(BF51="Apartamento Disponible",E51=0,AZ51=0),"Disponible","Cliente Atrasado"))) -> Enganche Completado | BI51: =COUNTIF(L51:AT51,">0.01") -> 17 | BJ51: 14
B52: 703 | C52: Paula H. | D52: Irving Elías López Salguero | E52: 45418 | F52: A3 | G52: 896715.83 | H52: 896715.83 | I52: =+G52-H52 -> 0 | J52: 896715.83 | K52: 4.PLAN DE PAGOS | L52: 0 | M52: 0 | N52: 0 | O52: 0 | P52: 0 | Q52: 0 | R52: 0 | S52: 0 | T52: 0 | U52: 0 | V52: 0 | W52: 0 | X52: 0 | Y52: 0 | Z52: 0 | AA52: 0 | AB52: 0 | AC52: 0 | AD52: 0 | AE52: 0 | AF52: 0 | AG52: 0 | AH52: 0 | AI52: 896715.83 | AJ52: 0 | AK52: 0 | AL52: 0 | AM52: 0 | AN52: 0 | AO52: 0 | AP52: 0 | AQ52: 0 | AS52: 0 | AX52: =SUM(L52:AV52) -> 896715.83 | AY52: =IFERROR((+AX52/BD52),0) -> 1 | AZ52: =+AX52-BD52 -> 0 | BA52: =IFERROR((+AZ52/BD52),0) -> 0 | BB52: =+H52-AX52 -> 0 | BC52: =+BB52/H52 -> 0 | BD52: =IF(BF52="Vendido",J52*1,IF(BF52="Disponible",J52*0,IF(BF52="Enganche Completado",J52*1,IF(BF52="Superávit de Enganche",J52*1,0)))) -> 896715.83 | BE52: =IF(D52=0,J52*0,BD52-AX52) -> 0 | BF52: =IF(D52=0,"Apartamento Disponible",IF(D52>1,"Vendido",0)) -> Vendido | BG52: =IF(AND(BF52="Vendido",E52>=0,AZ52=0),"Enganche Completado",IF(AND(BF52="Vendido",E52>=0,AZ52>0),"Superávit de Enganche",IF(AND(BF52="Apartamento Disponible",E52=0,AZ52=0),"Disponible","Cliente Atrasado"))) -> Enganche Completado | BI52: =COUNTIF(L52:AT52,">0.01") -> 1 | BJ52: =IF(AND(BG52="Cliente Atrasado",COUNTIF(L52:AT52,"<0.01")),DATEDIF(E52,AT$4+1,"m"),0) -> 0
B53: 704 | C53: Lilian G. | D53: Carlos Benjamín Salazar Batres | E53: 44742 | F53: B2 | G53: 665000 | H53: 665000 | I53: =+G53-H53 -> 0 | J53: 66500 | K53: 4.PLAN DE PAGOS | L53: 5000 | M53: 1000 | N53: 1000 | O53: 1000 | P53: 1000 | Q53: 2738 | R53: 2738 | S53: 2738 | T53: 2738 | U53: 5476 | V53: 0 | W53: 2738 | X53: 2738 | Y53: 2738 | Z53: 2738 | AA53: 2738 | AB53: 2738 | AC53: 2738 | AD53: 2738 | AE53: 2738 | AF53: 2738 | AG53: 2738 | AH53: 2738 | AI53: 2738 | AJ53: 2738 | AK53: 2740 | AL53: 0 | AM53: 0 | AN53: 0 | AO53: 0 | AP53: 0 | AQ53: 0 | AR53: 147395.73 | AS53: 0 | AX53: =SUM(L53:AV53) -> 213895.73 | AY53: =IFERROR((+AX53/BD53),0) -> 3.2164771 | AZ53: =+AX53-BD53 -> 147395.73 | BA53: =IFERROR((+AZ53/BD53),0) -> 2.2164771 | BB53: =+H53-AX53 -> 451104.27 | BC53: =+BB53/H53 -> 0.67835229 | BD53: =IF(BF53="Vendido",J53*1,IF(BF53="Disponible",J53*0,IF(BF53="Enganche Completado",J53*1,IF(BF53="Superávit de Enganche",J53*1,0)))) -> 66500 | BE53: =IF(D53=0,J53*0,BD53-AX53) -> -147395.73 | BF53: =IF(D53=0,"Apartamento Disponible",IF(D53>1,"Vendido",0)) -> Vendido | BG53: =IF(AND(BF53="Vendido",E53>=0,AZ53=0),"Enganche Completado",IF(AND(BF53="Vendido",E53>=0,AZ53>0),"Superávit de Enganche",IF(AND(BF53="Apartamento Disponible",E53=0,AZ53=0),"Disponible","Cliente Atrasado"))) -> Superávit de Enganche | BI53: =COUNTIF(L53:AT53,">0.01") -> 26 | BJ53: =IF(AND(BG53="Cliente Atrasado",COUNTIF(L53:AT53,"<0.01")),DATEDIF(E53,AT$4+1,"m"),0) -> 0
B54: 705 | C54: Lilian G. | D54: Mario Giovanni Paz Ponti | E54: 44750 | F54: B2 | G54: 665000 | H54: 665000 | I54: =+G54-H54 -> 0 | J54: 66500 | K54: 4.PLAN DE PAGOS | L54: 0 | M54: 5000 | N54: 2562.5 | O54: 2562.5 | P54: 2562.5 | Q54: 2562.5 | R54: 2562.5 | S54: 2562.5 | T54: 2562.5 | U54: 2562.5 | V54: 2562.5 | W54: 2562.5 | X54: 2562.5 | Y54: 2562.5 | Z54: 2562.5 | AA54: 2562.5 | AB54: 2562.5 | AC54: 2562.5 | AD54: 2562.5 | AE54: 2562.5 | AF54: 2562.5 | AG54: 2562.5 | AH54: 2562.5 | AI54: 2562.5 | AJ54: 2562.5 | AK54: 2562.5 | AL54: 0 | AM54: 0 | AN54: 0 | AO54: 0 | AP54: 11000 | AQ54: 11000 | AR54: 11000 | AS54: =11000+11000 -> 22000 | AX54: =SUM(L54:AV54) -> 121500 | AY54: =IFERROR((+AX54/BD54),0) -> 1.8270677 | AZ54: =+AX54-BD54 -> 55000 | BA54: =IFERROR((+AZ54/BD54),0) -> 0.82706767 | BB54: =+H54-AX54 -> 543500 | BC54: =+BB54/H54 -> 0.81729323 | BD54: =IF(BF54="Vendido",J54*1,IF(BF54="Disponible",J54*0,IF(BF54="Enganche Completado",J54*1,IF(BF54="Superávit de Enganche",J54*1,0)))) -> 66500 | BE54: =IF(D54=0,J54*0,BD54-AX54) -> -55000 | BF54: =IF(D54=0,"Apartamento Disponible",IF(D54>1,"Vendido",0)) -> Vendido | BG54: =IF(AND(BF54="Vendido",E54>=0,AZ54=0),"Enganche Completado",IF(AND(BF54="Vendido",E54>=0,AZ54>0),"Superávit de Enganche",IF(AND(BF54="Apartamento Disponible",E54=0,AZ54=0),"Disponible","Cliente Atrasado"))) -> Superávit de Enganche | BI54: =COUNTIF(L54:AT54,">0.01") -> 29 | BJ54: =IF(AND(BG54="Cliente Atrasado",COUNTIF(L54:AT54,"<0.01")),DATEDIF(E54,AT$4+1,"m"),0) -> 0
B55: 706 | C55: Paula H. | D55: Marlon Estuardo Cardona y Adriana Sofía Gutierrez | E55: 45367 | F55: A3 | G55: 900000 | H55: 900000 | I55: =+G55-H55 -> 0 | J55: 900000 | K55: 4.PLAN DE PAGOS | L55: 0 | M55: 0 | N55: 0 | O55: 0 | P55: 0 | Q55: 0 | R55: 0 | S55: 0 | T55: 0 | U55: 0 | V55: 0 | W55: 0 | X55: 0 | Y55: 0 | Z55: 0 | AA55: 0 | AB55: 0 | AC55: 0 | AD55: 0 | AE55: 0 | AF55: 0 | AG55: 5000 | AH55: 0 | AI55: 111875 | AJ55: 111875 | AK55: 111875 | AL55: 111875 | AM55: 0 | AN55: 111875 | AO55: 0 | AP55: 0 | AQ55: 111875 | AR55: 111875 | AS55: 0 | AT55: 0 | AX55: =SUM(L55:AV55) -> 788125 | AY55: =IFERROR((+AX55/BD55),0) -> 0.87569444 | AZ55: =+AX55-BD55 -> -111875 | BA55: =IFERROR((+AZ55/BD55),0) -> -0.12430556 | BB55: =+H55-AX55 -> 111875 | BC55: =+BB55/H55 -> 0.12430556 | BD55: =IF(BF55="Vendido",J55*1,IF(BF55="Disponible",J55*0,IF(BF55="Enganche Completado",J55*1,IF(BF55="Superávit de Enganche",J55*1,0)))) -> 900000 | BE55: =IF(D55=0,J55*0,BD55-AX55) -> 111875 | BF55: =IF(D55=0,"Apartamento Disponible",IF(D55>1,"Vendido",0)) -> Vendido | BG55: =IF(AND(BF55="Vendido",E55>=0,AZ55=0),"Enganche Completado",IF(AND(BF55="Vendido",E55>=0,AZ55>0),"Superávit de Enganche",IF(AND(BF55="Apartamento Disponible",E55=0,AZ55=0),"Disponible","Cliente Atrasado"))) -> Cliente Atrasado | BI55: =COUNTIF(L55:AT55,">0.01") -> 8 | BJ55: 6
B56: 707 | C56: Noemi M. | D56: Silvia Elizabeth Guevara Lucas | E56: 44830 | F56: A1 | G56: 697720 | H56: 697720 | I56: =+G56-H56 -> 0 | J56: 76720 | K56: 4.PLAN DE PAGOS | L56: 0 | M56: 0 | N56: 0 | O56: 5000 | P56: 3000 | Q56: 3000 | R56: 3000 | S56: 3000 | T56: 3000 | U56: 3000 | V56: 3000 | W56: 3000 | X56: 3000 | Y56: 3000 | Z56: 3000 | AA56: 3000 | AB56: 3000 | AC56: 3000 | AD56: 3000 | AE56: 3000 | AF56: 6000 | AG56: 0 | AH56: 3000 | AI56: 3000 | AJ56: 3000 | AK56: 8720 | AL56: 0 | AM56: 0 | AN56: 0 | AO56: 0 | AP56: 0 | AQ56: 0 | AR56: 149276.78 | AX56: =SUM(L56:AV56) -> 225996.78 | AY56: =IFERROR((+AX56/BD56),0) -> 2.9457349 | AZ56: =+AX56-BD56 -> 149276.78 | BA56: =IFERROR((+AZ56/BD56),0) -> 1.9457349 | BB56: =+H56-AX56 -> 471723.22 | BC56: =+BB56/H56 -> 0.67609244 | BD56: =IF(BF56="Vendido",J56*1,IF(BF56="Disponible",J56*0,IF(BF56="Enganche Completado",J56*1,IF(BF56="Superávit de Enganche",J56*1,0)))) -> 76720 | BE56: =IF(D56=0,J56*0,BD56-AX56) -> -149276.78 | BF56: =IF(D56=0,"Apartamento Disponible",IF(D56>1,"Vendido",0)) -> Vendido | BG56: =IF(AND(BF56="Vendido",E56>=0,AZ56=0),"Enganche Completado",IF(AND(BF56="Vendido",E56>=0,AZ56>0),"Superávit de Enganche",IF(AND(BF56="Apartamento Disponible",E56=0,AZ56=0),"Disponible","Cliente Atrasado"))) -> Superávit de Enganche | BI56: =COUNTIF(L56:AT56,">0.01") -> 23 | BJ56: =IF(AND(BG56="Cliente Atrasado",COUNTIF(L56:AT56,"<0.01")),DATEDIF(E56,AT$4+1,"m"),0) -> 0
B57: 708 | C57: Noemi M. | D57: Juan José Marroquín Rivera | E57: 44801 | F57: C2 | G57: 498000 | H57: 498000 | I57: =+G57-H57 -> 0 | J57: 49800 | K57: 4.PLAN DE PAGOS | L57: 0 | M57: 0 | N57: 5000 | O57: 2000 | P57: 2000 | Q57: 2000 | R57: 2000 | S57: 2000 | T57: 2000 | U57: 2000 | V57: 2000 | W57: 2000 | X57: 2000 | Y57: 2000 | Z57: 2000 | AA57: 2000 | AB57: 2000 | AC57: 2000 | AD57: 2000 | AE57: 2000 | AF57: 2000 | AG57: 2000 | AH57: 2000 | AI57: 2000 | AJ57: 2800 | AK57: 2000 | AL57: 2000 | AM57: 2000 | AN57: 2000 | AO57: 2000 | AP57: 2000 | AQ57: 0 | AR57: 0 | AS57: 102846.48 | AX57: =SUM(L57:AV57) -> 164646.48 | AY57: =IFERROR((+AX57/BD57),0) -> 3.3061542 | AZ57: =+AX57-BD57 -> 114846.48 | BA57: =IFERROR((+AZ57/BD57),0) -> 2.3061542 | BB57: =+H57-AX57 -> 333353.52 | BC57: =+BB57/H57 -> 0.66938458 | BD57: =IF(BF57="Vendido",J57*1,IF(BF57="Disponible",J57*0,IF(BF57="Enganche Completado",J57*1,IF(BF57="Superávit de Enganche",J57*1,0)))) -> 49800 | BE57: =IF(D57=0,J57*0,BD57-AX57) -> -114846.48 | BF57: =IF(D57=0,"Apartamento Disponible",IF(D57>1,"Vendido",0)) -> Vendido | BG57: =IF(AND(BF57="Vendido",E57>=0,AZ57=0),"Enganche Completado",IF(AND(BF57="Vendido",E57>=0,AZ57>0),"Superávit de Enganche",IF(AND(BF57="Apartamento Disponible",E57=0,AZ57=0),"Disponible","Cliente Atrasado"))) -> Superávit de Enganche | BI57: =COUNTIF(L57:AT57,">0.01") -> 30 | BJ57: =IF(AND(BG57="Cliente Atrasado",COUNTIF(L57:AT57,"<0.01")),DATEDIF(E57,AT$4+1,"m"),0) -> 0
B58: 801 | C58: Francisco S. | D58: Nancy Maricela Velasquez Aguilar | E58: 44739 | F58: C2 | G58: 498000 | H58: 498000 | I58: =+G58-H58 -> 0 | J58: 49800 | K58: 4.PLAN DE PAGOS | L58: 5000 | M58: 1943.83 | N58: 1947.83 | O58: 1951.83 | P58: 1947.83 | Q58: 1947.83 | R58: 1947.83 | S58: 1947.83 | T58: 1947.83 | U58: 1947.83 | V58: 1947.83 | W58: 1947.83 | X58: 2000 | Y58: 2000 | Z58: 1947.83 | AA58: 2000 | AB58: 2000 | AC58: 2000 | AD58: 2000 | AE58: 2000 | AF58: 2000 | AG58: 2000 | AH58: 2000 | AI58: 2000 | AJ58: 0 | AK58: 4000 | AL58: 6000 | AM58: 7000 | AN58: =30000+20626.04 -> 50626.04 | AO58: 0 | AP58: 0 | AQ58: 0 | AR58: 0 | AS58: 71637.09 | AX58: =SUM(L58:AV58) -> 189637.09 | AY58: =IFERROR((+AX58/BD58),0) -> 3.8079737 | AZ58: =+AX58-BD58 -> 139837.09 | BA58: =IFERROR((+AZ58/BD58),0) -> 2.8079737 | BB58: =+H58-AX58 -> 308362.91 | BC58: =+BB58/H58 -> 0.61920263 | BD58: =IF(BF58="Vendido",J58*1,IF(BF58="Disponible",J58*0,IF(BF58="Enganche Completado",J58*1,IF(BF58="Superávit de Enganche",J58*1,0)))) -> 49800 | BE58: =IF(D58=0,J58*0,BD58-AX58) -> -139837.09 | BF58: =IF(D58=0,"Apartamento Disponible",IF(D58>1,"Vendido",0)) -> Vendido | BG58: =IF(AND(BF58="Vendido",E58>=0,AZ58=0),"Enganche Completado",IF(AND(BF58="Vendido",E58>=0,AZ58>0),"Superávit de Enganche",IF(AND(BF58="Apartamento Disponible",E58=0,AZ58=0),"Disponible","Cliente Atrasado"))) -> Superávit de Enganche | BI58: =COUNTIF(L58:AT58,">0.01") -> 29 | BJ58: =IF(AND(BG58="Cliente Atrasado",COUNTIF(L58:AT58,"<0.01")),DATEDIF(E58,AT$4+1,"m"),0) -> 0
B59: 802 | C59: Paula H. | D59: Raúl Arturo De León Juarez | E59: 45136 | F59: A1 | G59: 789500 | H59: 789500 | I59: =+G59-H59 -> 0 | J59: 78950 | K59: 4.PLAN DE PAGOS | L59: 0 | M59: 0 | N59: 0 | O59: 0 | P59: 0 | Q59: 0 | R59: 0 | S59: 0 | T59: 0 | U59: 0 | V59: 0 | W59: 0 | X59: 0 | Y59: 5000 | Z59: 5688.46 | AA59: 5688.46 | AB59: 5688.46 | AC59: 5688.46 | AD59: 5688.46 | AE59: 5688.46 | AF59: 5688.46 | AG59: 0 | AH59: 11376.92 | AI59: 5688.46 | AJ59: 5688.46 | AK59: 0 | AL59: 11376.94 | AM59: 0 | AN59: 0 | AO59: 0 | AP59: 0 | AQ59: 0 | AR59: 0 | AS59: 0 | AX59: =SUM(L59:AV59) -> 78950 | AY59: =IFERROR((+AX59/BD59),0) -> 1 | AZ59: =+AX59-BD59 -> 0 | BA59: =IFERROR((+AZ59/BD59),0) -> 0 | BB59: =+H59-AX59 -> 710550 | BC59: =+BB59/H59 -> 0.9 | BD59: =IF(BF59="Vendido",J59*1,IF(BF59="Disponible",J59*0,IF(BF59="Enganche Completado",J59*1,IF(BF59="Superávit de Enganche",J59*1,0)))) -> 78950 | BE59: =IF(D59=0,J59*0,BD59-AX59) -> 0 | BF59: =IF(D59=0,"Apartamento Disponible",IF(D59>1,"Vendido",0)) -> Vendido | BG59: =IF(AND(BF59="Vendido",E59>=0,AZ59=0),"Enganche Completado",IF(AND(BF59="Vendido",E59>=0,AZ59>0),"Superávit de Enganche",IF(AND(BF59="Apartamento Disponible",E59=0,AZ59=0),"Disponible","Cliente Atrasado"))) -> Enganche Completado | BI59: =COUNTIF(L59:AT59,">0.01") -> 12 | BJ59: =IF(AND(BG59="Cliente Atrasado",COUNTIF(L59:AT59,"<0.01")),DATEDIF(E59,AT$4+1,"m"),0) -> 0
B60: 803 | C60: Paula H. | D60: Rocio Celeste Archila Alfaro / Brian Javier Centeno Archila | E60: 45630 | F60: A3 | G60: 1004617.1 | H60: =720603.67+284013.43 -> 1004617.1 | I60: =+G60-H60 -> 0 | J60: 50317.1 | K60: 4.PLAN DE PAGOS | L60: 0 | M60: 0 | N60: 0 | O60: 0 | P60: 0 | Q60: 0 | R60: 0 | S60: 0 | T60: 0 | U60: 0 | V60: 0 | W60: 0 | X60: 0 | Y60: 0 | Z60: 0 | AA60: 0 | AB60: 0 | AC60: 0 | AD60: 0 | AE60: 0 | AF60: 0 | AG60: 0 | AH60: 0 | AI60: 0 | AJ60: 0 | AK60: 0 | AL60: 0 | AM60: 0 | AN60: 0 | AO60: 0 | AP60: =5000+6611.05+7500 -> 19111.05 | AQ60: 7500 | AR60: 0 | AS60: 0 | AT60: 0 | AU60: 23706.05 | AX60: =SUM(L60:AV60) -> 50317.1 | AY60: =IFERROR((+AX60/BD60),0) -> 1 | AZ60: =+AX60-BD60 -> 0 | BA60: =IFERROR((+AZ60/BD60),0) -> 0 | BB60: =+H60-AX60 -> 954300 | BC60: =+BB60/H60 -> 0.94991415 | BD60: =IF(BF60="Vendido",J60*1,IF(BF60="Disponible",J60*0,IF(BF60="Enganche Completado",J60*1,IF(BF60="Superávit de Enganche",J60*1,0)))) -> 50317.1 | BE60: =IF(D60=0,J60*0,BD60-AX60) -> 0 | BF60: =IF(D60=0,"Apartamento Disponible",IF(D60>1,"Vendido",0)) -> Vendido | BG60: =IF(AND(BF60="Vendido",E60>=0,AZ60=0),"Enganche Completado",IF(AND(BF60="Vendido",E60>=0,AZ60>0),"Superávit de Enganche",IF(AND(BF60="Apartamento Disponible",E60=0,AZ60=0),"Disponible","Cliente Atrasado"))) -> Enganche Completado | BI60: =COUNTIF(L60:AT60,">0.01") -> 2 | BJ60: =IF(AND(BG60="Cliente Atrasado",COUNTIF(L60:AT60,"<0.01")),DATEDIF(E60,AT$4,"m"),0)-1 -> -1
B61: 804 | C61: Paula H. | D61: Pablo Javier Herrera Cabrera | E61: 45348 | F61: B2 | G61: 778400 | H61: 778400 | I61: =+G61-H61 -> 0 | J61: 38900 | K61: 4.PLAN DE PAGOS | L61: 0 | M61: 0 | N61: 0 | O61: 0 | P61: 0 | Q61: 0 | R61: 0 | S61: 0 | T61: 0 | U61: 0 | V61: 0 | W61: 0 | X61: 0 | Y61: 0 | Z61: 0 | AA61: 0 | AB61: 0 | AC61: 0 | AD61: 0 | AE61: 0 | AF61: 5000 | AG61: 3769 | AH61: 7538 | AI61: 3769 | AJ61: 3769 | AK61: 15155 | AL61: 0 | AM61: 0 | AN61: 0 | AO61: 0 | AP61: 0 | AQ61: 0 | AR61: 0 | AS61: 293167.37 | AX61: =SUM(L61:AV61) -> 332167.37 | AY61: =IFERROR((+AX61/BD61),0) -> 8.5390069 | AZ61: =+AX61-BD61 -> 293267.37 | BA61: =IFERROR((+AZ61/BD61),0) -> 7.5390069 | BB61: =+H61-AX61 -> 446232.63 | BC61: =+BB61/H61 -> 0.57326905 | BD61: =IF(BF61="Vendido",J61*1,IF(BF61="Disponible",J61*0,IF(BF61="Enganche Completado",J61*1,IF(BF61="Superávit de Enganche",J61*1,0)))) -> 38900 | BE61: =IF(D61=0,J61*0,BD61-AX61) -> -293267.37 | BF61: =IF(D61=0,"Apartamento Disponible",IF(D61>1,"Vendido",0)) -> Vendido | BG61: =IF(AND(BF61="Vendido",E61>=0,AZ61=0),"Enganche Completado",IF(AND(BF61="Vendido",E61>=0,AZ61>0),"Superávit de Enganche",IF(AND(BF61="Apartamento Disponible",E61=0,AZ61=0),"Disponible","Cliente Atrasado"))) -> Superávit de Enganche | BI61: =COUNTIF(L61:AT61,">0.01") -> 7 | BJ61: =IF(AND(BG61="Cliente Atrasado",COUNTIF(L61:AT61,"<0.01")),DATEDIF(E61,AT$4+1,"m"),0) -> 0
B62: 805 | C62: Noemi M. | D62: Ingrid Lorena Sajmolo Ruiz | E62: 45017 | F62: B2 | G62: 753900 | H62: 753900 | I62: =+G62-H62 -> 0 | J62: 75400 | K62: 4.PLAN DE PAGOS | L62: 0 | M62: 0 | N62: 0 | O62: 0 | P62: 0 | Q62: 0 | R62: 0 | S62: 0 | T62: 0 | U62: 0 | V62: 10000 | W62: 5000 | X62: 6000 | Y62: 8500 | Z62: 5000 | AA62: 5000 | AB62: 5000 | AC62: 5000 | AD62: 5000 | AE62: 5000 | AF62: 6000 | AG62: 6000 | AH62: 6000 | AI62: 6000 | AJ62: 6000 | AK62: 10000 | AL62: 6000 | AM62: 6000 | AN62: 0 | AO62: 0 | AP62: 0 | AQ62: 0 | AR62: 0 | AS62: 0 | AX62: =SUM(L62:AV62) -> 111500 | AY62: =IFERROR((+AX62/BD62),0) -> 1.4787798 | AZ62: =+AX62-BD62 -> 36100 | BA62: =IFERROR((+AZ62/BD62),0) -> 0.47877984 | BB62: =+H62-AX62 -> 642400 | BC62: =+BB62/H62 -> 0.8521024 | BD62: =IF(BF62="Vendido",J62*1,IF(BF62="Disponible",J62*0,IF(BF62="Enganche Completado",J62*1,IF(BF62="Superávit de Enganche",J62*1,0)))) -> 75400 | BE62: =IF(D62=0,J62*0,BD62-AX62) -> -36100 | BF62: =IF(D62=0,"Apartamento Disponible",IF(D62>1,"Vendido",0)) -> Vendido | BG62: =IF(AND(BF62="Vendido",E62>=0,AZ62=0),"Enganche Completado",IF(AND(BF62="Vendido",E62>=0,AZ62>0),"Superávit de Enganche",IF(AND(BF62="Apartamento Disponible",E62=0,AZ62=0),"Disponible","Cliente Atrasado"))) -> Superávit de Enganche | BI62: =COUNTIF(L62:AT62,">0.01") -> 18 | BJ62: =IF(AND(BG62="Cliente Atrasado",COUNTIF(L62:AT62,"<0.01")),DATEDIF(E62,AT$4+1,"m"),0) -> 0
B63: 806 | C63: Paula H. | D63: Wilson Ariel Salvador Tomas | E63: 45267 | F63: A3 | G63: 990800 | H63: 1031600 | I63: =+G63-H63 -> -40800 | J63: 51600 | K63: 4.PLAN DE PAGOS | L63: 0 | M63: 0 | N63: 0 | O63: 0 | P63: 0 | Q63: 0 | R63: 0 | S63: 0 | T63: 0 | U63: 0 | V63: 0 | W63: 0 | X63: 0 | Y63: 0 | Z63: 0 | AA63: 0 | AB63: 0 | AC63: 0 | AD63: 5000 | AE63: 0 | AF63: 46600 | AG63: 0 | AH63: 0 | AI63: 0 | AJ63: 0 | AK63: 0 | AL63: 0 | AM63: 0 | AN63: 0 | AO63: 0 | AP63: 0 | AQ63: 0 | AR63: 0 | AS63: 377824.7 | AX63: =SUM(L63:AV63) -> 429424.7 | AY63: =IFERROR((+AX63/BD63),0) -> 8.3221841 | AZ63: =+AX63-BD63 -> 377824.7 | BA63: =IFERROR((+AZ63/BD63),0) -> 7.3221841 | BB63: =+H63-AX63 -> 602175.3 | BC63: =+BB63/H63 -> 0.58372945 | BD63: =IF(BF63="Vendido",J63*1,IF(BF63="Disponible",J63*0,IF(BF63="Enganche Completado",J63*1,IF(BF63="Superávit de Enganche",J63*1,0)))) -> 51600 | BE63: =IF(D63=0,J63*0,BD63-AX63) -> -377824.7 | BF63: =IF(D63=0,"Apartamento Disponible",IF(D63>1,"Vendido",0)) -> Vendido | BG63: =IF(AND(BF63="Vendido",E63>=0,AZ63=0),"Enganche Completado",IF(AND(BF63="Vendido",E63>=0,AZ63>0),"Superávit de Enganche",IF(AND(BF63="Apartamento Disponible",E63=0,AZ63=0),"Disponible","Cliente Atrasado"))) -> Superávit de Enganche | BI63: =COUNTIF(L63:AT63,">0.01") -> 3 | BJ63: =IF(AND(BG63="Cliente Atrasado",COUNTIF(L63:AT63,"<0.01")),DATEDIF(E63,AT$4+1,"m"),0) -> 0
B64: 807 | C64: Antonio R | D64: Walter Rolando Alvarado García y Ana Leticia Santos Calmo | E64: 45672 | F64: A1 | G64: 850000 | H64: 850000 | I64: =+G64-H64 -> 0 | J64: 250000 | K64: 4.PLAN DE PAGOS | L64: 0 | M64: 0 | N64: 0 | O64: 0 | P64: 0 | Q64: 0 | R64: 0 | S64: 0 | T64: 0 | U64: 0 | V64: 0 | W64: 0 | X64: 0 | Y64: 0 | Z64: 0 | AA64: 0 | AB64: 0 | AC64: 0 | AD64: 0 | AE64: 0 | AF64: 0 | AG64: 0 | AH64: 0 | AI64: 0 | AJ64: 0 | AK64: 0 | AL64: 0 | AM64: 0 | AN64: 0 | AO64: 0 | AP64: 0 | AQ64: 5000 | AR64: 245000 | AS64: 0 | AX64: =SUM(L64:AV64) -> 250000 | AY64: =IFERROR((+AX64/BD64),0) -> 1 | AZ64: =+AX64-BD64 -> 0 | BA64: =IFERROR((+AZ64/BD64),0) -> 0 | BB64: =+H64-AX64 -> 600000 | BC64: =+BB64/H64 -> 0.70588235 | BD64: =IF(BF64="Vendido",J64*1,IF(BF64="Disponible",J64*0,IF(BF64="Enganche Completado",J64*1,IF(BF64="Superávit de Enganche",J64*1,0)))) -> 250000 | BE64: =IF(D64=0,J64*0,BD64-AX64) -> 0 | BF64: =IF(D64=0,"Apartamento Disponible",IF(D64>1,"Vendido",0)) -> Vendido | BG64: =IF(AND(BF64="Vendido",E64>=0,AZ64=0),"Enganche Completado",IF(AND(BF64="Vendido",E64>=0,AZ64>0),"Superávit de Enganche",IF(AND(BF64="Apartamento Disponible",E64=0,AZ64=0),"Disponible","Cliente Atrasado"))) -> Enganche Completado | BI64: =COUNTIF(L64:AT64,">0.01") -> 2 | BJ64: =IF(AND(BG64="Cliente Atrasado",COUNTIF(L64:AT64,"<0.01")),DATEDIF(E64,AT$4+1,"m"),0) -> 0
B65: 808 | C65: Francisco S. | D65: Mainor Alfredo Carias Culajay | E65: 44771 | F65: C2 | G65: 498000 | H65: 498000 | I65: =+G65-H65 -> 0 | J65: 49800 | K65: 4.PLAN DE PAGOS | L65: 0 | M65: 5000 | N65: 1948 | O65: 1948 | P65: 1948 | Q65: 1948 | R65: 1948 | S65: 1948 | T65: 1948 | U65: 1948 | V65: 0 | W65: 3896 | X65: 1948 | Y65: 1948 | Z65: 1948 | AA65: 1948 | AB65: 0 | AC65: 1948 | AD65: 3896 | AE65: 0 | AF65: 0 | AG65: 1948 | AH65: 1948 | AI65: 0 | AJ65: 7788 | AK65: 0 | AL65: 0 | AM65: 0 | AN65: 48200 | AO65: 0 | AP65: 0 | AQ65: 0 | AR65: 0 | AS65: 0 | AX65: =SUM(L65:AV65) -> 98000 | AY65: =IFERROR((+AX65/BD65),0) -> 1.9678715 | AZ65: =+AX65-BD65 -> 48200 | BA65: =IFERROR((+AZ65/BD65),0) -> 0.96787149 | BB65: =+H65-AX65 -> 400000 | BC65: =+BB65/H65 -> 0.80321285 | BD65: =IF(BF65="Vendido",J65*1,IF(BF65="Disponible",J65*0,IF(BF65="Enganche Completado",J65*1,IF(BF65="Superávit de Enganche",J65*1,0)))) -> 49800 | BE65: =IF(D65=0,J65*0,BD65-AX65) -> -48200 | BF65: =IF(D65=0,"Apartamento Disponible",IF(D65>1,"Vendido",0)) -> Vendido | BG65: =IF(AND(BF65="Vendido",E65>=0,AZ65=0),"Enganche Completado",IF(AND(BF65="Vendido",E65>=0,AZ65>0),"Superávit de Enganche",IF(AND(BF65="Apartamento Disponible",E65=0,AZ65=0),"Disponible","Cliente Atrasado"))) -> Superávit de Enganche | BI65: =COUNTIF(L65:AT65,">0.01") -> 20 | BJ65: =IF(AND(BG65="Cliente Atrasado",COUNTIF(L65:AT65,"<0.01")),DATEDIF(E65,AT$4+1,"m"),0) -> 0
B66: 901 | C66: Noemi M. | D66: Misraim Antonio Osuna López | E66: 44783 | F66: C2 | G66: 498000 | H66: 498000 | I66: =+G66-H66 -> 0 | J66: 49800 | K66: 4.PLAN DE PAGOS | L66: 0 | M66: 0 | N66: 2000 | O66: 3000 | P66: 3000 | Q66: 3000 | R66: 109.08 | S66: 3000 | T66: 2000 | U66: 3000 | V66: 3000 | W66: 0 | X66: 3000 | Y66: 3000 | Z66: 0 | AA66: 3000 | AB66: 3000 | AC66: 3000 | AD66: 3000 | AE66: 3000 | AF66: 5000 | AG66: 5000 | AH66: 21170.41 | AI66: 5400 | AJ66: 4000 | AK66: 4045 | AL66: 9775.51 | AM66: 2500 | AN66: 0 | AO66: 0 | AP66: 0 | AQ66: 0 | AR66: 0 | AS66: 60556.23 | AX66: =SUM(L66:AV66) -> 160556.23 | AY66: =IFERROR((+AX66/BD66),0) -> 3.2240207 | AZ66: =+AX66-BD66 -> 110756.23 | BA66: =IFERROR((+AZ66/BD66),0) -> 2.2240207 | BB66: =+H66-AX66 -> 337443.77 | BC66: =+BB66/H66 -> 0.67759793 | BD66: =IF(BF66="Vendido",J66*1,IF(BF66="Disponible",J66*0,IF(BF66="Enganche Completado",J66*1,IF(BF66="Superávit de Enganche",J66*1,0)))) -> 49800 | BE66: =IF(D66=0,J66*0,BD66-AX66) -> -110756.23 | BF66: =IF(D66=0,"Apartamento Disponible",IF(D66>1,"Vendido",0)) -> Vendido | BG66: =IF(AND(BF66="Vendido",E66>=0,AZ66=0),"Enganche Completado",IF(AND(BF66="Vendido",E66>=0,AZ66>0),"Superávit de Enganche",IF(AND(BF66="Apartamento Disponible",E66=0,AZ66=0),"Disponible","Cliente Atrasado"))) -> Superávit de Enganche | BI66: =COUNTIF(L66:AT66,">0.01") -> 25 | BJ66: =IF(AND(BG66="Cliente Atrasado",COUNTIF(L66:AT66,"<0.01")),DATEDIF(E66,AT$4+1,"m"),0) -> 0
B67: 902 | C67: Paula H. | D67: Danilo Otoniel Gomez Guzman | E67: 45254 | F67: A1 | G67: 788400 | H67: 788400 | I67: =+G67-H67 -> 0 | J67: 39500 | K67: 4.PLAN DE PAGOS | L67: 0 | M67: 0 | N67: 0 | O67: 0 | P67: 0 | Q67: 0 | R67: 0 | S67: 0 | T67: 0 | U67: 0 | V67: 0 | W67: 0 | X67: 0 | Y67: 0 | Z67: 0 | AA67: 0 | AB67: 0 | AC67: 3000 | AD67: 3041 | AE67: 3041 | AF67: 3041 | AG67: 3041 | AH67: 3041 | AI67: 0 | AJ67: 3041 | AK67: 0 | AL67: 6082 | AM67: 3041 | AN67: 6082 | AO67: 0 | AP67: 3041 | AQ67: 8 | AR67: 0 | AS67: 0 | AX67: =SUM(L67:AV67) -> 39500 | AY67: =IFERROR((+AX67/BD67),0) -> 1 | AZ67: =+AX67-BD67 -> 0 | BA67: =IFERROR((+AZ67/BD67),0) -> 0 | BB67: =+H67-AX67 -> 748900 | BC67: =+BB67/H67 -> 0.94989853 | BD67: =IF(BF67="Vendido",J67*1,IF(BF67="Disponible",J67*0,IF(BF67="Enganche Completado",J67*1,IF(BF67="Superávit de Enganche",J67*1,0)))) -> 39500 | BE67: =IF(D67=0,J67*0,BD67-AX67) -> 0 | BF67: =IF(D67=0,"Apartamento Disponible",IF(D67>1,"Vendido",0)) -> Vendido | BG67: =IF(AND(BF67="Vendido",E67>=0,AZ67=0),"Enganche Completado",IF(AND(BF67="Vendido",E67>=0,AZ67>0),"Superávit de Enganche",IF(AND(BF67="Apartamento Disponible",E67=0,AZ67=0),"Disponible","Cliente Atrasado"))) -> Enganche Completado | BI67: =COUNTIF(L67:AT67,">0.01") -> 12 | BJ67: =IF(AND(BG67="Cliente Atrasado",COUNTIF(L67:AT67,"<0.01")),DATEDIF(E67,AT$4+1,"m"),0) -> 0
B68: 903 | C68: Paula H. | D68: Rosybel Alheli Suchini | E68: 45321 | F68: A3 | G68: 1033420 | H68: 1074220 | I68: =+G68-H68 -> -40800 | J68: 200020 | K68: 4.PLAN DE PAGOS | L68: 0 | M68: 0 | N68: 0 | O68: 0 | P68: 0 | Q68: 0 | R68: 0 | S68: 0 | T68: 0 | U68: 0 | V68: 0 | W68: 0 | X68: 0 | Y68: 0 | Z68: 0 | AA68: 0 | AB68: 0 | AC68: 0 | AD68: 0 | AE68: 5000 | AF68: 3564.5 | AG68: 3575.5 | AH68: 3575 | AI68: 3575 | AJ68: 3575 | AK68: 3691 | AL68: 6000 | AM68: 6000 | AN68: 6000 | AO68: 6000 | AP68: 149580 | AR68: 0 | AS68: 329301.71 | AX68: =SUM(L68:AV68) -> 529437.71 | AY68: =IFERROR((+AX68/BD68),0) -> 2.6469239 | AZ68: =+AX68-BD68 -> 329417.71 | BA68: =IFERROR((+AZ68/BD68),0) -> 1.6469239 | BB68: =+H68-AX68 -> 544782.29 | BC68: =+BB68/H68 -> 0.5071422 | BD68: =IF(BF68="Vendido",J68*1,IF(BF68="Disponible",J68*0,IF(BF68="Enganche Completado",J68*1,IF(BF68="Superávit de Enganche",J68*1,0)))) -> 200020 | BE68: =IF(D68=0,J68*0,BD68-AX68) -> -329417.71 | BF68: =IF(D68=0,"Apartamento Disponible",IF(D68>1,"Vendido",0)) -> Vendido | BG68: =IF(AND(BF68="Vendido",E68>=0,AZ68=0),"Enganche Completado",IF(AND(BF68="Vendido",E68>=0,AZ68>0),"Superávit de Enganche",IF(AND(BF68="Apartamento Disponible",E68=0,AZ68=0),"Disponible","Cliente Atrasado"))) -> Superávit de Enganche | BI68: =COUNTIF(L68:AT68,">0.01") -> 13 | BJ68: =IF(AND(BG68="Cliente Atrasado",COUNTIF(L68:AT68,"<0.01")),DATEDIF(E68,AT$4+1,"m"),0) -> 0
B69: 904 | C69: Paula H. | D69: Mario Domingo | E69: 45434 | F69: B2 | G69: 770000 | H69: 770000 | I69: =+G69-H69 -> 0 | J69: 770000 | K69: 4.PLAN DE PAGOS | L69: 0 | M69: 0 | N69: 0 | O69: 0 | P69: 0 | Q69: 0 | R69: 0 | S69: 0 | T69: 0 | U69: 0 | V69: 0 | W69: 0 | X69: 0 | Y69: 0 | Z69: 0 | AA69: 0 | AB69: 0 | AC69: 0 | AD69: 0 | AE69: 0 | AF69: 0 | AG69: 0 | AH69: 0 | AI69: 5000 | AJ69: 20000 | AK69: 0 | AL69: 0 | AM69: 0 | AN69: 0 | AO69: 0 | AP69: 0 | AQ69: 741479.55 | AR69: 0 | AS69: 0 | AT69: 0 | AX69: =SUM(L69:AV69) -> 766479.55 | AY69: =IFERROR((+AX69/BD69),0) -> 0.99542799 | AZ69: =+AX69-BD69 -> -3520.45 | BA69: =IFERROR((+AZ69/BD69),0) -> -0.004572013 | BB69: =+H69-AX69 -> 3520.45 | BC69: =+BB69/H69 -> 0.004572013 | BD69: =IF(BF69="Vendido",J69*1,IF(BF69="Disponible",J69*0,IF(BF69="Enganche Completado",J69*1,IF(BF69="Superávit de Enganche",J69*1,0)))) -> 770000 | BE69: =IF(D69=0,J69*0,BD69-AX69) -> 3520.45 | BF69: =IF(D69=0,"Apartamento Disponible",IF(D69>1,"Vendido",0)) -> Vendido | BG69: =IF(AND(BF69="Vendido",E69>=0,AZ69=0),"Enganche Completado",IF(AND(BF69="Vendido",E69>=0,AZ69>0),"Superávit de Enganche",IF(AND(BF69="Apartamento Disponible",E69=0,AZ69=0),"Disponible","Cliente Atrasado"))) -> Cliente Atrasado | BI69: =COUNTIF(L69:AT69,">0.01") -> 3 | BJ69: 1
B70: 905 | C70: Noemi M. | D70: Xiomara Cristina Barrios Castellanos | E70: 44992 | F70: B2 | G70: 753900 | H70: 753900 | I70: =+G70-H70 -> 0 | J70: 75400 | K70: 4.PLAN DE PAGOS | L70: 0 | M70: 0 | N70: 0 | O70: 0 | P70: 0 | Q70: 0 | R70: 0 | S70: 0 | T70: 0 | U70: 5000 | V70: 4400 | W70: 4400 | X70: 4400 | Y70: 13200 | Z70: 0 | AA70: 0 | AB70: 4400 | AC70: 0 | AD70: 17600 | AE70: 4400 | AF70: 0 | AG70: 4400 | AH70: 0 | AI70: 4400 | AJ70: 8800 | AK70: 0 | AL70: 0 | AM70: 0 | AN70: 0 | AO70: 0 | AP70: 0 | AQ70: 0 | AR70: 0 | AS70: 221962.96 | AX70: =SUM(L70:AV70) -> 297362.96 | AY70: =IFERROR((+AX70/BD70),0) -> 3.9438058 | AZ70: =+AX70-BD70 -> 221962.96 | BA70: =IFERROR((+AZ70/BD70),0) -> 2.9438058 | BB70: =+H70-AX70 -> 456537.04 | BC70: =+BB70/H70 -> 0.6055671 | BD70: =IF(BF70="Vendido",J70*1,IF(BF70="Disponible",J70*0,IF(BF70="Enganche Completado",J70*1,IF(BF70="Superávit de Enganche",J70*1,0)))) -> 75400 | BE70: =IF(D70=0,J70*0,BD70-AX70) -> -221962.96 | BF70: =IF(D70=0,"Apartamento Disponible",IF(D70>1,"Vendido",0)) -> Vendido | BG70: =IF(AND(BF70="Vendido",E70>=0,AZ70=0),"Enganche Completado",IF(AND(BF70="Vendido",E70>=0,AZ70>0),"Superávit de Enganche",IF(AND(BF70="Apartamento Disponible",E70=0,AZ70=0),"Disponible","Cliente Atrasado"))) -> Superávit de Enganche | BI70: =COUNTIF(L70:AT70,">0.01") -> 12 | BJ70: =IF(AND(BG70="Cliente Atrasado",COUNTIF(L70:AT70,"<0.01")),DATEDIF(E70,AT$4+1,"m"),0) -> 0
B71: 906 | C71: Paula H. | D71: Byron Victoriano Mazariegos Mejía | E71: 45166 | F71: A3 | G71: 1011600 | H71: 1011600 | I71: =+G71-H71 -> 0 | J71: 101160 | K71: 4.PLAN DE PAGOS | L71: 0 | M71: 0 | N71: 0 | O71: 0 | P71: 0 | Q71: 0 | R71: 0 | S71: 0 | T71: 0 | U71: 0 | V71: 0 | W71: 0 | X71: 0 | Y71: 0 | Z71: 5000 | AA71: 8741 | AB71: 8741 | AC71: 8741 | AD71: 8741 | AE71: 8741 | AF71: 8741 | AG71: 8741 | AH71: 8741 | AI71: 8741 | AJ71: 8741 | AK71: 8741 | AL71: 9 | AM71: 0 | AN71: 0 | AO71: 0 | AP71: 0 | AQ71: 0 | AR71: 0 | AS71: 0 | AU71: 40 | AX71: =SUM(L71:AV71) -> 101200 | AY71: =IFERROR((+AX71/BD71),0) -> 1.0003954 | AZ71: =+AX71-BD71 -> 40 | BA71: =IFERROR((+AZ71/BD71),0) -> 0.00039541321 | BB71: =+H71-AX71 -> 910400 | BC71: =+BB71/H71 -> 0.89996046 | BD71: =IF(BF71="Vendido",J71*1,IF(BF71="Disponible",J71*0,IF(BF71="Enganche Completado",J71*1,IF(BF71="Superávit de Enganche",J71*1,0)))) -> 101160 | BE71: =IF(D71=0,J71*0,BD71-AX71) -> -40 | BF71: =IF(D71=0,"Apartamento Disponible",IF(D71>1,"Vendido",0)) -> Vendido | BG71: =IF(AND(BF71="Vendido",E71>=0,AZ71=0),"Enganche Completado",IF(AND(BF71="Vendido",E71>=0,AZ71>0),"Superávit de Enganche",IF(AND(BF71="Apartamento Disponible",E71=0,AZ71=0),"Disponible","Cliente Atrasado"))) -> Superávit de Enganche | BI71: =COUNTIF(L71:AT71,">0.01") -> 13 | BJ71: =IF(AND(BG71="Cliente Atrasado",COUNTIF(L71:AT71,"<0.01")),DATEDIF(E71,AT$4+1,"m"),0) -> 0
B72: 907 | C72: Lilian G. | D72: María Del Rocio Pinto Gómez de Liaño | E72: 44890 | F72: A1 | G72: 678182.1 | H72: 678182.1 | I72: =+G72-H72 -> 0 | J72: 678182.1 | K72: 4.PLAN DE PAGOS | L72: 0 | M72: 0 | N72: 0 | O72: 0 | P72: 0 | Q72: 0 | R72: 678182.1 | S72: 0 | T72: 0 | U72: 0 | V72: 0 | W72: 0 | X72: 0 | Y72: 0 | Z72: 0 | AA72: 0 | AB72: 0 | AC72: 0 | AD72: 0 | AE72: 0 | AF72: 0 | AG72: 0 | AH72: 0 | AI72: 0 | AJ72: 0 | AK72: 0 | AL72: 0 | AM72: 0 | AN72: 0 | AO72: 0 | AP72: 0 | AQ72: 0 | AR72: 0 | AS72: 0 | AX72: =SUM(L72:AV72) -> 678182.1 | AY72: =IFERROR((+AX72/BD72),0) -> 1 | AZ72: =+AX72-BD72 -> 0 | BA72: =IFERROR((+AZ72/BD72),0) -> 0 | BB72: =+H72-AX72 -> 0 | BC72: =+BB72/H72 -> 0 | BD72: =IF(BF72="Vendido",J72*1,IF(BF72="Disponible",J72*0,IF(BF72="Enganche Completado",J72*1,IF(BF72="Superávit de Enganche",J72*1,0)))) -> 678182.1 | BE72: =IF(D72=0,J72*0,BD72-AX72) -> 0 | BF72: =IF(D72=0,"Apartamento Disponible",IF(D72>1,"Vendido",0)) -> Vendido | BG72: =IF(AND(BF72="Vendido",E72>=0,AZ72=0),"Enganche Completado",IF(AND(BF72="Vendido",E72>=0,AZ72>0),"Superávit de Enganche",IF(AND(BF72="Apartamento Disponible",E72=0,AZ72=0),"Disponible","Cliente Atrasado"))) -> Enganche Completado | BI72: =COUNTIF(L72:AT72,">0.01") -> 1 | BJ72: =IF(AND(BG72="Cliente Atrasado",COUNTIF(L72:AT72,"<0.01")),DATEDIF(E72,AT$4+1,"m"),0) -> 0
B73: 908 | C73: Paula H. | D73: Isaias Gabriele Barrios Orozco | E73: 45760 | F73: C2 | G73: 498000 | H73: 690000 | I73: =+G73-H73 -> -192000 | J73: 49800 | K73: 2.RESERVADO | L73: 0 | M73: 0 | N73: 0 | O73: 0 | P73: 0 | Q73: 0 | R73: 0 | S73: 0 | T73: 0 | U73: 0 | V73: 0 | W73: 0 | X73: 0 | Y73: 0 | Z73: 0 | AA73: 0 | AB73: 0 | AC73: 0 | AD73: 0 | AE73: 0 | AF73: 0 | AG73: 0 | AH73: 0 | AI73: 0 | AJ73: 0 | AK73: 0 | AL73: 0 | AM73: 0 | AN73: 0 | AO73: 0 | AP73: 0 | AQ73: 0 | AR73: 0 | AS73: 0 | AX73: =SUM(L73:AV73) -> 0 | AY73: =IFERROR((+AX73/BD73),0) -> 0 | AZ73: =+AX73-BD73 -> -49800 | BA73: =IFERROR((+AZ73/BD73),0) -> -1 | BB73: =+H73-AX73 -> 690000 | BC73: =+BB73/H73 -> 1 | BD73: =IF(BF73="Vendido",J73*1,IF(BF73="Disponible",J73*0,IF(BF73="Enganche Completado",J73*1,IF(BF73="Superávit de Enganche",J73*1,0)))) -> 49800 | BE73: =IF(D73=0,J73*0,BD73-AX73) -> 49800 | BF73: =IF(D73=0,"Apartamento Disponible",IF(D73>1,"Vendido",0)) -> Vendido | BG73: =IF(AND(BF73="Vendido",E73>=0,AZ73=0),"Enganche Completado",IF(AND(BF73="Vendido",E73>=0,AZ73>0),"Superávit de Enganche",IF(AND(BF73="Apartamento Disponible",E73=0,AZ73=0),"Disponible","Cliente Atrasado"))) -> Cliente Atrasado | BI73: =COUNTIF(L73:AT73,">0.01") -> 0 | BJ73: =IF(AND(BG73="Cliente Atrasado",COUNTIF(L73:AT73,"<0.01")),DATEDIF(E73,AT$4+1,"m"),0) -> 0 | BK73: Dep. Reserva | BM73: Sin promesa firmada
B74: 1001 | C74: Francisco S. | D74: Jose Julio Grave Cos | E74: 44760 | F74: C2 | G74: 498000 | H74: 498000 | I74: 0 | J74: 49800 | K74: 4.PLAN DE PAGOS | L74: 0 | M74: 6947.93 | N74: 1947.93 | O74: 1947.93 | P74: 1947.93 | Q74: 1947.93 | R74: 1947.93 | S74: 1947.93 | T74: 1947.93 | U74: 1947.93 | V74: 1947.93 | W74: 1947.93 | X74: 1947.93 | Y74: 1947.93 | Z74: 1947.93 | AA74: 1947.93 | AB74: 1947.93 | AC74: 0 | AD74: 3895.86 | AE74: 1947.93 | AF74: 1947.93 | AG74: 1947.93 | AH74: 1947.83 | AI74: 1947.83 | AJ74: 0 | AK74: 0 | AL74: 0 | AM74: 0 | AN74: 0 | AO74: 0 | AP74: 0 | AQ74: 0 | AR74: 0 | AS74: 0 | AX74: =SUM(L74:AV74) -> 49802.19 | AY74: =IFERROR((+AX74/BD74),0) -> 1.000044 | AZ74: =+AX74-BD74 -> 2.19 | BA74: =IFERROR((+AZ74/BD74),0) -> 4.3975904e-05 | BB74: =+H74-AX74 -> 448197.81 | BC74: =+BB74/H74 -> 0.8999956 | BD74: =IF(BF74="Vendido",J74*1,IF(BF74="Disponible",J74*0,IF(BF74="Enganche Completado",J74*1,IF(BF74="Superávit de Enganche",J74*1,0)))) -> 49800 | BE74: =IF(D74=0,J74*0,BD74-AX74) -> -2.19 | BF74: =IF(D74=0,"Apartamento Disponible",IF(D74>1,"Vendido",0)) -> Vendido | BG74: =IF(AND(BF74="Vendido",E74>=0,AZ74=0),"Enganche Completado",IF(AND(BF74="Vendido",E74>=0,AZ74>0),"Superávit de Enganche",IF(AND(BF74="Apartamento Disponible",E74=0,AZ74=0),"Disponible","Cliente Atrasado"))) -> Superávit de Enganche | BI74: =COUNTIF(L74:AT74,">0.01") -> 22 | BJ74: =IF(AND(BG74="Cliente Atrasado",COUNTIF(L74:AT74,"<0.01")),DATEDIF(E74,AT$4+1,"m"),0) -> 0
B75: 1002 | C75: Noemi M. | D75: Josue Othoniel Andrade de la Cruz | E75: 44997 | F75: A1 | G75: 788400 | H75: 788400 | I75: =+G75-H75 -> 0 | J75: 78900 | K75: 4.PLAN DE PAGOS | L75: 0 | M75: 0 | N75: 0 | O75: 0 | P75: 0 | Q75: 0 | R75: 0 | S75: 0 | T75: 0 | U75: 78900 | V75: 0 | W75: 0 | X75: 0 | Y75: 0 | Z75: 0 | AA75: 0 | AB75: 0 | AC75: 0 | AD75: 0 | AE75: 0 | AF75: 0 | AG75: 0 | AH75: 0 | AI75: 0 | AJ75: 0 | AK75: 0 | AL75: 0 | AM75: 0 | AN75: 0 | AO75: 0 | AP75: 0 | AQ75: 0 | AR75: 0 | AS75: 236316.76 | AX75: =SUM(L75:AV75) -> 315216.76 | AY75: =IFERROR((+AX75/BD75),0) -> 3.9951427 | AZ75: =+AX75-BD75 -> 236316.76 | BA75: =IFERROR((+AZ75/BD75),0) -> 2.9951427 | BB75: =+H75-AX75 -> 473183.24 | BC75: =+BB75/H75 -> 0.60018168 | BD75: =IF(BF75="Vendido",J75*1,IF(BF75="Disponible",J75*0,IF(BF75="Enganche Completado",J75*1,IF(BF75="Superávit de Enganche",J75*1,0)))) -> 78900 | BE75: =IF(D75=0,J75*0,BD75-AX75) -> -236316.76 | BF75: =IF(D75=0,"Apartamento Disponible",IF(D75>1,"Vendido",0)) -> Vendido | BG75: =IF(AND(BF75="Vendido",E75>=0,AZ75=0),"Enganche Completado",IF(AND(BF75="Vendido",E75>=0,AZ75>0),"Superávit de Enganche",IF(AND(BF75="Apartamento Disponible",E75=0,AZ75=0),"Disponible","Cliente Atrasado"))) -> Superávit de Enganche | BI75: =COUNTIF(L75:AT75,">0.01") -> 2 | BJ75: =IF(AND(BG75="Cliente Atrasado",COUNTIF(L75:AT75,"<0.01")),DATEDIF(E75,AT$4+1,"m"),0) -> 0
B76: 1003 | C76: Paula H. | D76: Wendy Azucena Aguilar Chávez | E76: 45626 | F76: A7 | G76: 498000 | H76: 1300000 | I76: =+G76-H76 -> -802000 | J76: 63000 | K76: 4.PLAN DE PAGOS | L76: 0 | M76: 0 | N76: 0 | O76: 0 | P76: 0 | Q76: 0 | R76: 0 | S76: 0 | T76: 0 | U76: 0 | V76: 0 | W76: 0 | X76: 0 | Y76: 0 | Z76: 0 | AA76: 0 | AB76: 0 | AC76: 0 | AD76: 0 | AE76: 0 | AF76: 0 | AG76: 0 | AH76: 0 | AI76: 0 | AJ76: 0 | AK76: 0 | AL76: 0 | AM76: 0 | AN76: 0 | AO76: 2500 | AP76: 0 | AQ76: 0 | AR76: 0 | AS76: 100000 | AT76: 100000 | AX76: =SUM(L76:AV76) -> 202500 | AY76: =IFERROR((+AX76/BD76),0) -> 3.2142857 | AZ76: =+AX76-BD76 -> 139500 | BA76: =IFERROR((+AZ76/BD76),0) -> 2.2142857 | BB76: =+H76-AX76 -> 1097500 | BC76: =+BB76/H76 -> 0.84423077 | BD76: =IF(BF76="Vendido",J76*1,IF(BF76="Disponible",J76*0,IF(BF76="Enganche Completado",J76*1,IF(BF76="Superávit de Enganche",J76*1,0)))) -> 63000 | BE76: =IF(D76=0,J76*0,BD76-AX76) -> -139500 | BF76: =IF(D76=0,"Apartamento Disponible",IF(D76>1,"Vendido",0)) -> Vendido | BG76: =IF(AND(BF76="Vendido",E76>=0,AZ76=0),"Enganche Completado",IF(AND(BF76="Vendido",E76>=0,AZ76>0),"Superávit de Enganche",IF(AND(BF76="Apartamento Disponible",E76=0,AZ76=0),"Disponible","Cliente Atrasado"))) -> Superávit de Enganche | BI76: =COUNTIF(L76:AT76,">0.01") -> 3 | BJ76: =IF(AND(BG76="Cliente Atrasado",COUNTIF(L76:AT76,"<0.01")),DATEDIF(E76,AT$4+1,"m"),0) -> 0
B77: L1 | C77: Paula H. | D77: Helbert Emmanuel Blanco Argueta | E77: 45723 | G77: 255060 | H77: 255060 | I77: =+G77-H77 -> 0 | J77: 25506 | K77: 2.RESERVADO | L77: 0 | M77: 0 | N77: 0 | O77: 0 | P77: 0 | Q77: 0 | R77: 0 | S77: 0 | T77: 0 | U77: 0 | V77: 0 | W77: 0 | X77: 0 | Y77: 0 | Z77: 0 | AA77: 0 | AB77: 0 | AC77: 0 | AD77: 0 | AE77: 0 | AF77: 0 | AG77: 0 | AH77: 0 | AI77: 0 | AJ77: 0 | AK77: 0 | AL77: 0 | AM77: 0 | AN77: 0 | AO77: 0 | AP77: 0 | AQ77: 0 | AR77: 0 | AS77: 2500 | AT77: 0 | AX77: =SUM(L77:AV77) -> 2500 | AY77: =IFERROR((+AX77/BD77),0) -> 0.098016153 | AZ77: =+AX77-BD77 -> -23006 | BA77: =IFERROR((+AZ77/BD77),0) -> -0.90198385 | BB77: =+H77-AX77 -> 252560 | BC77: =+BB77/H77 -> 0.99019838 | BD77: =IF(BF77="Vendido",J77*1,IF(BF77="Disponible",J77*0,IF(BF77="Enganche Completado",J77*1,IF(BF77="Superávit de Enganche",J77*1,0)))) -> 25506 | BE77: =IF(D77=0,J77*0,BD77-AX77) -> 23006 | BF77: =IF(D77=0,"Apartamento Disponible",IF(D77>1,"Vendido",0)) -> Vendido | BG77: =IF(AND(BF77="Vendido",E77>=0,AZ77=0),"Enganche Completado",IF(AND(BF77="Vendido",E77>=0,AZ77>0),"Superávit de Enganche",IF(AND(BF77="Apartamento Disponible",E77=0,AZ77=0),"Disponible","Cliente Atrasado"))) -> Cliente Atrasado | BI77: =COUNTIF(L77:AT77,">0.01") -> 1 | BJ77: =IF(AND(BG77="Cliente Atrasado",COUNTIF(L77:AT77,"<0.01")),DATEDIF(E77,AT$4+1,"m"),0) -> 1
B78: L2 | C78: Paula H. | D78: Helbert Emmanuel Blanco Argueta | E78: 45723 | G78: 318960 | H78: 318960 | I78: =+G78-H78 -> 0 | J78: 31896 | K78: 2.RESERVADO | L78: 0 | M78: 0 | N78: 0 | O78: 0 | P78: 0 | Q78: 0 | R78: 0 | S78: 0 | T78: 0 | U78: 0 | V78: 0 | W78: 0 | X78: 0 | Y78: 0 | Z78: 0 | AA78: 0 | AB78: 0 | AC78: 0 | AD78: 0 | AE78: 0 | AF78: 0 | AG78: 0 | AH78: 0 | AI78: 0 | AJ78: 0 | AK78: 0 | AL78: 0 | AM78: 0 | AN78: 0 | AO78: 0 | AP78: 0 | AQ78: 0 | AR78: 0 | AS78: 2500 | AT78: 0 | AX78: =SUM(L78:AV78) -> 2500 | AY78: =IFERROR((+AX78/BD78),0) -> 0.078379734 | AZ78: =+AX78-BD78 -> -29396 | BA78: =IFERROR((+AZ78/BD78),0) -> -0.92162027 | BB78: =+H78-AX78 -> 316460 | BC78: =+BB78/H78 -> 0.99216203 | BD78: =IF(BF78="Vendido",J78*1,IF(BF78="Disponible",J78*0,IF(BF78="Enganche Completado",J78*1,IF(BF78="Superávit de Enganche",J78*1,0)))) -> 31896 | BE78: =IF(D78=0,J78*0,BD78-AX78) -> 29396 | BF78: =IF(D78=0,"Apartamento Disponible",IF(D78>1,"Vendido",0)) -> Vendido | BG78: =IF(AND(BF78="Vendido",E78>=0,AZ78=0),"Enganche Completado",IF(AND(BF78="Vendido",E78>=0,AZ78>0),"Superávit de Enganche",IF(AND(BF78="Apartamento Disponible",E78=0,AZ78=0),"Disponible","Cliente Atrasado"))) -> Cliente Atrasado | BI78: =COUNTIF(L78:AT78,">0.01") -> 1 | BJ78: =IF(AND(BG78="Cliente Atrasado",COUNTIF(L78:AT78,"<0.01")),DATEDIF(E78,AT$4+1,"m"),0) -> 1
B79: L3 | C79: Eder Veliz | D79: Jorge Antonio Sanchez Sipaque | E79: 45761 | G79: 457740 | H79: 460000 | I79: =+G79-H79 -> -2260 | J79: 92000 | K79: 2.RESERVADO | L79: 0 | M79: 0 | N79: 0 | O79: 0 | P79: 0 | Q79: 0 | R79: 0 | S79: 0 | T79: 0 | U79: 0 | V79: 0 | W79: 0 | X79: 0 | Y79: 0 | Z79: 0 | AA79: 0 | AB79: 0 | AC79: 0 | AD79: 0 | AE79: 0 | AF79: 0 | AG79: 0 | AH79: 0 | AI79: 0 | AJ79: 0 | AK79: 0 | AL79: 0 | AM79: 0 | AN79: 0 | AO79: 0 | AP79: 0 | AQ79: 0 | AR79: 0 | AS79: 0 | AT79: 0 | AX79: =SUM(L79:AV79) -> 0 | AY79: =IFERROR((+AX79/BD79),0) -> 0 | AZ79: =+AX79-BD79 -> -92000 | BA79: =IFERROR((+AZ79/BD79),0) -> -1 | BB79: =+H79-AX79 -> 460000 | BC79: =+BB79/H79 -> 1 | BD79: =IF(BF79="Vendido",J79*1,IF(BF79="Disponible",J79*0,IF(BF79="Enganche Completado",J79*1,IF(BF79="Superávit de Enganche",J79*1,0)))) -> 92000 | BE79: =IF(D79=0,J79*0,BD79-AX79) -> 92000 | BF79: =IF(D79=0,"Apartamento Disponible",IF(D79>1,"Vendido",0)) -> Vendido | BG79: =IF(AND(BF79="Vendido",E79>=0,AZ79=0),"Enganche Completado",IF(AND(BF79="Vendido",E79>=0,AZ79>0),"Superávit de Enganche",IF(AND(BF79="Apartamento Disponible",E79=0,AZ79=0),"Disponible","Cliente Atrasado"))) -> Cliente Atrasado | BI79: =COUNTIF(L79:AT79,">0.01") -> 0 | BJ79: =IF(AND(BG79="Cliente Atrasado",COUNTIF(L79:AT79,"<0.01")),DATEDIF(E79,AT$4+1,"m"),0) -> 0 | BK79: Dep. Reserva | BM79: Sin promesa firmada
B80: TOTAL COBROS DE CARTERA DE CLIENTES | G80: =SUM(G5:G79) -> 54714740 | H80: =SUM(H5:H79) -> 56150229 | I80: =SUM(I5:I79) -> -1435489.1 | J80: =SUM(J5:J79) -> 10443691 | L80: =SUM(L5:L79) -> 15000 | M80: =SUM(M5:M79) -> 23326.54 | N80: =SUM(N5:N79) -> 34841.04 | O80: =SUM(O5:O79) -> 225855.04 | P80: =SUM(P5:P79) -> 386608.87 | Q80: =SUM(Q5:Q79) -> 52830.6 | R80: =SUM(R5:R79) -> 726307.13 | S80: =SUM(S5:S79) -> 79220.6 | ... AV80: =SUM(AV5:AV79) -> 0 | AX80: =SUM(L80:AV80) -> 15652148 | AY80: =IFERROR((+AX80/BD80),0) -> 1.5081042 | AZ80: =SUM(AZ5:AZ79) -> 5273456.6 | BA80: =IFERROR((+AZ80/BD80),0) -> 0.50810419 | BB80: =SUM(BB5:BB79) -> 40498081 | BC80: =+BB80/H80 -> 0.72124516 | BD80: =SUM(BD5:BD79) -> 10378691 | BE80: =SUM(BE5:BE79) -> -5273456.6
AS81: 3765866
AS82: =+AS80-AS81 -> 20000 | AX82: =+AX80-RESUMEN!#REF! -> #REF! | BD82: =+BD80-RESUMEN!#REF! -> #REF! | BE82: =+BE80-RESUMEN!#REF! -> #REF!
B84: Desestimientos
B85: 302 | C85: Noemi M. | D85: Elizabeth Ramírez Rodríguez | E85: 44846 | F85: A1 | G85: 698000 | H85: 698000 | I85: =+G85-H85 -> 0 | J85: 166000 | K85: 4.PLAN DE PAGOS | L85: 0 | M85: 0 | N85: 0 | O85: 0 | P85: 40000 | Q85: 6000 | R85: 6000 | S85: 6000 | T85: 6000 | U85: 6000 | V85: 6000 | W85: 0 | X85: 6000 | Y85: 6000 | Z85: 0 | AA85: 0 | AB85: 0 | AC85: 0 | AD85: 6000 | AE85: 0 | AF85: 0 | AG85: 0 | AH85: 3000 | AI85: 0 | AJ85: 0 | AK85: 0 | AL85: 0 | AM85: 0 | AN85: 0 | AO85: 0 | AP85: 0 | AQ85: 0 | AR85: 0 | AS85: 0 | AT85: 0 | AX85: =SUM(L85:AT85) -> 97000
B86: 308 | C86: Noemí Menendez | D86: Oscar Sincal | L86: 0 | M86: 0 | N86: 0 | O86: 0 | P86: 0 | Q86: 0 | R86: 0 | S86: 0 | T86: 5000 | AG86: 0 | AH86: 0 | AI86: 0 | AJ86: 0 | AK86: 0 | AL86: 0 | AX86: =SUM(L86:AP86) -> 5000
B87: 604 | C87: Paula H. | D87: Geovanni Chain | E87: 45322 | F87: B2 | H87: 665000 | J87: 66500 | K87: 4.PLAN DE PAGOS | L87: 0 | M87: 0 | N87: 0 | O87: 5000 | P87: 1500 | Q87: 1500 | R87: 1500 | S87: 5500 | T87: 4500 | U87: 5000 | V87: 3000 | W87: 1500 | X87: 3000 | Y87: 4500 | Z87: 3000 | AA87: 0 | AB87: 0 | AC87: 0 | AD87: 0 | AX87: =SUM(L87:AP87) -> 39500
B88: 508 | C88: Paula H. | D88: Andrea Maria Calderon | E88: 45438 | F88: C2 | H88: 547800 | J88: 54780 | K88: 4.PLAN DE PAGOS | L88: 0 | M88: 0 | N88: 0 | O88: 0 | P88: 0 | Q88: 5000 | R88: 1000 | S88: 1000 | T88: 1000 | U88: 1000 | V88: 1000 | W88: 1000 | X88: 0 | Y88: 0 | Z88: 0 | AA88: 0 | AB88: 0 | AC88: 0 | AD88: 0 | AE88: 0 | AF88: 0 | AG88: 0 | AH88: 0 | AI88: 0 | AJ88: 0 | AK88: 0 | AL88: 0 | AM88: 0 | AX88: =SUM(L88:AP88) -> 11000
B89: 606 | C89: Paula H. | D89: Wilby Miguel Batz | E89: 45384 | F89: A3 | H89: 948800 | J89: 49400 | K89: 4.PLAN DE PAGOS | L89: 0 | M89: 0 | N89: 0 | O89: 0 | P89: 0 | Q89: 0 | R89: 0 | S89: 0 | T89: 0 | U89: 0 | V89: 0 | W89: 0 | X89: 0 | Y89: 0 | Z89: 0 | AA89: 0 | AB89: 0 | AC89: 0 | AD89: 0 | AE89: 0 | AF89: 0 | AG89: 0 | AH89: 5000 | AI89: 6000 | AJ89: 6000 | AK89: 0 | AL89: 0 | AM89: 0 | AX89: =SUM(L89:AP89) -> 17000
B90: 605 | C90: Noemi M. | D90: Bruno Antonio Zeissig Pineda | E90: 44778 | F90: B2 | H90: 665000 | J90: 66500 | K90: 4.PLAN DE PAGOS | L90: 0 | M90: 0 | N90: 7673.91 | O90: 2673.913 | P90: 2673.913 | Q90: 2673.913 | R90: 2673.913 | S90: 2673.913 | T90: 2673.913 | U90: 2673.91 | V90: 0 | W90: 5347.82 | X90: 2673.91 | Y90: 2673.91 | Z90: 2673.91 | AA90: 2673.91 | AB90: 2673.91 | AC90: 2673.91 | AD90: 2673.91 | AE90: 2673.91 | AF90: 2673.91 | AG90: 0 | AH90: 2673.91 | AI90: 5347.82 | AJ90: 2673.98 | AK90: 0 | AL90: 0 | AM90: 0 | AX90: =SUM(L90:AP90) -> 66500.018
B91: 508 | C91: Paula H. | D91: Ingrid Marisol Palacios Argueta / Jose Luis Enrique Rezzio Armas | E91: 45438 | F91: C2 | H91: =627000+33000 -> 660000 | J91: 33000 | K91: 4.PLAN DE PAGOS | L91: 0 | M91: 0 | N91: 0 | O91: 0 | P91: 0 | Q91: 0 | R91: 0 | S91: 0 | T91: 0 | U91: 0 | V91: 0 | W91: 0 | X91: 0 | Y91: 0 | Z91: 0 | AA91: 0 | AB91: 0 | AC91: 0 | AD91: 0 | AE91: 0 | AF91: 0 | AG91: 0 | AH91: 0 | AI91: 5000 | AJ91: 0 | AK91: 5000 | AL91: 0 | AM91: 0 | AX91: =SUM(L91:AP91) -> 10000
B92: 908 | C92: Francisco S. | D92: Marta Eugenia Gálvez Alburez de Marroquín | E92: 44803 | F92: C2 | H92: 498000 | J92: 49800 | K92: 4.PLAN DE PAGOS | L92: 0 | M92: 0 | N92: 20000 | O92: 1300 | P92: 1300 | Q92: 0 | R92: 1300 | S92: 1300 | T92: 0 | U92: 1300 | V92: 1300 | W92: 0 | X92: 1350 | Y92: 0 | Z92: 1350 | AA92: 0 | AB92: 0 | AC92: 0 | AD92: 0 | AE92: 0 | AF92: 0 | AG92: 2700 | AH92: 2371.43 | AI92: 2371.43 | AJ92: 0 | AK92: 0 | AL92: 0 | AM92: 0 | AX92: =SUM(L92:AP92) -> 37942.86
B93: 307 | C93: Noemi M. | D93: Kimberly Mariel Lemus López | E93: 44958 | F93: A1 | H93: 680000 | J93: 68000 | K93: 4.PLAN DE PAGOS | L93: 0 | M93: 0 | N93: 0 | O93: 0 | P93: 0 | Q93: 0 | R93: 0 | S93: 0 | T93: 5000 | U93: 0 | V93: 7400 | W93: 0 | X93: 7400 | Y93: 3700 | Z93: 0 | AA93: 0 | AB93: 0 | AC93: 0 | AD93: 0 | AE93: 0 | AF93: 0 | AG93: 4900 | AH93: 0 | AI93: 0 | AJ93: 9800 | AK93: 0 | AL93: 0 | AM93: 0 | AX93: =SUM(L93:AP93) -> 38200
B94: 807 | C94: Paula H. | D94: Lourdes Lorena Reyes Fajardo y Glenda Marissela Cueva Serrano | E94: 45514 | F94: A1 | H94: 812900 | J94: 40645 | K94: 4.PLAN DE PAGOS | L94: 0 | M94: 0 | N94: 0 | O94: 0 | P94: 0 | Q94: 0 | R94: 0 | S94: 0 | T94: 0 | U94: 0 | V94: 0 | W94: 0 | X94: 0 | Y94: 0 | Z94: 0 | AA94: 0 | AB94: 0 | AC94: 0 | AD94: 0 | AE94: 0 | AF94: 0 | AG94: 0 | AH94: 0 | AI94: 0 | AJ94: 0 | AK94: 0 | AL94: 5000 | AM94: 0 | AX94: =SUM(L94:AP94) -> 5000
B95: 403 | C95: Efren Sanchez | D95: Cristian David Pérez Maldonado | E95: 45635 | F95: A3 | G95: 948800 | H95: 964442 | I95: -15642 | J95: 48242 | K95: 2.RESERVADO | L95: 0 | M95: 0 | N95: 0 | O95: 0 | P95: 0 | Q95: 0 | R95: 0 | S95: 0 | T95: 0 | U95: 0 | V95: 0 | W95: 0 | X95: 0 | Y95: 0 | AA95: 0 | AB95: 0 | AC95: 0 | AD95: 0 | AE95: 0 | AF95: 0 | AG95: 0 | AH95: 0 | AI95: 0 | AJ95: 0 | AK95: 0 | AL95: 0 | AP95: 5000 | AX95: 5000
B96: 807 | C96: Andrea G. | D96: Eri Giovani Ibarra López | E96: 45635 | F96: A1 | G96: 850000 | H96: 850000 | I96: 0 | J96: 85000 | K96: 2.RESERVADO | L96: 0 | M96: 0 | N96: 0 | O96: 0 | P96: 0 | Q96: 0 | R96: 0 | S96: 0 | T96: 0 | U96: 0 | V96: 0 | W96: 0 | X96: 0 | Y96: 0 | Z96: 0 | AA96: 0 | AB96: 0 | AC96: 0 | AD96: 0 | AE96: 0 | AF96: 0 | AG96: 0 | AH96: 0 | AI96: 0 | AJ96: 0 | AK96: 0 | AL96: 0 | AM96: 0 | AP96: 5000 | AX96: 5000
B97: 904 | C97: Paula H. | D97: Jose Adolfo Aguilar | E97: 45434 | F97: B2 | H97: 753900 | J97: 37700 | K97: 4.PLAN DE PAGOS | L97: 0 | M97: 0 | N97: 0 | O97: 0 | P97: 0 | Q97: 0 | R97: 0 | S97: 0 | T97: 0 | U97: 0 | V97: 0 | W97: 0 | X97: 0 | Y97: 0 | Z97: 0 | AA97: 0 | AB97: 0 | AC97: 0 | AD97: 1018.45 | AE97: 0 | AF97: 0 | AG97: 0 | AH97: 2502 | AI97: 0 | AJ97: 0 | AK97: 0 | AL97: 0 | AM97: 0 | AX97: =SUM(L97:AP97) -> 3520.45
B98: 1003 | C98: Paula H. | D98: Wendy Azucena Aguilar Chavez | E98: 45649 | F98: A7 | G98: 498000 | H98: 1300000 | I98: =+G98-H98 -> -802000 | J98: 63000 | K98: 1.DISPONIBLE | L98: 0 | M98: 0 | N98: 0 | O98: 0 | P98: 0 | Q98: 0 | R98: 0 | S98: 0 | T98: 0 | U98: 0 | V98: 0 | W98: 0 | X98: 0 | Y98: 0 | Z98: 0 | AA98: 0 | AB98: 0 | AC98: 0 | AD98: 0 | AE98: 0 | AF98: 0 | AG98: 0 | AH98: 0 | AI98: 0 | AJ98: 0 | AK98: 0 | AL98: 0 | AM98: 0 | AO98: 2500 | AX98: =SUM(L98:AR98) -> 2500
B99: 1001 | C99: Francisco S. | D99: Jose Julio Grave Cos | E99: 44760 | F99: C2 | G99: 1132000 | H99: 1132000 | I99: =+G99-H99 -> 0 | J99: 113200 | K99: 4.PLAN DE PAGOS | L99: 0 | M99: 0 | N99: 0 | O99: 5000 | P99: 4918 | Q99: 4922 | R99: 4920 | S99: 4918.18 | T99: 4920 | U99: 4918.18 | V99: 4918 | W99: 4918 | X99: 4918 | Y99: 4918.18 | Z99: 4919 | AA99: 4919 | AB99: 4919 | AC99: 4919 | AD99: 4919 | AE99: 4919 | AF99: 4919 | AG99: 4919 | AH99: 4919 | AI99: 4919 | AJ99: 4919 | AK99: 4919 | AL99: 0 | AM99: 0 | AX99: =SUM(L99:AQ99) -> 113216.54
B100: L3 | C100: Eder Veliz | D100: Rosibel Suchini Morales | E100: 45709 | G100: 457740 | H100: 457740 | I100: =+G100-H100 -> 0 | J100: 45774 | K100: 2.RESERVADO | L100: 0 | M100: 0 | N100: 0 | O100: 0 | P100: 0 | Q100: 0 | R100: 0 | S100: 0 | T100: 0 | U100: 0 | V100: 0 | W100: 0 | X100: 0 | Y100: 0 | Z100: 0 | AA100: 0 | AB100: 0 | AC100: 0 | AD100: 0 | AE100: 0 | AF100: 0 | AG100: 0 | AH100: 0 | AI100: 0 | AJ100: 0 | AK100: 0 | AL100: 0 | AM100: 0 | AN100: 0 | AO100: 0 | AP100: 0 | AQ100: 0 | AR100: 5000 | AS100: 0 | AT100: 0 | AX100: =SUM(L100:AT100) -> 5000
B101: TOTAL COBROS DE DESESTIMIENTOS | L101: =SUM(L85:L100) -> 0 | M101: =SUM(M85:M100) -> 0 | N101: =SUM(N85:N100) -> 27673.91 | O101: =SUM(O85:O100) -> 13973.913 | P101: =SUM(P85:P100) -> 50391.913 | Q101: =SUM(Q85:Q100) -> 20095.913 | R101: =SUM(R85:R100) -> 17393.913 | S101: =SUM(S85:S100) -> 21392.093 | ... AR101: =SUM(AR85:AR100) -> 5000 | AX101: =SUM(AX85:AX100) -> 461379.87
...

Sheet SANTA ELISA PPTO
A2: 1 | B2: =+A2+1 -> 2 | C2: =+B2+1 -> 3 | D2: =+C2+1 -> 4 | E2: =+D2+1 -> 5 | F2: =+E2+1 -> 6 | G2: =+F2+1 -> 7 | H2: =+G2+1 -> 8 | I2: =+H2+1 -> 9 | ... AI2: =+AH2+1 -> 35 | AM2: =+AI2+1 -> 36 | AN2: =+AM2+1 -> 37
A4: Apto | B4: jun.22 | C4: jul.22 | D4: ago.22 | E4: sep.22 | F4: oct.22 | G4: nov.22 | H4: dic.22 | I4: ene.23 | J4: feb.23 | K4: mar.23 | L4: abr.23 | M4: may.23 | N4: jun.23 | O4: jul.23 | P4: ago.23 | Q4: sep.23 | R4: oct.23 | S4: nov.23 | T4: dic.23 | U4: ene.24 | V4: feb.24 | W4: mar.24 | X4: abr.24 | Y4: may.24 | Z4: jun.24 | AA4: jul.24 | AB4: ago.24 | AC4: sept.24 | AD4: Oct.24 | AE4: Nov.24 | AF4: Dic.24 | AG4: 45658 | AH4: 45689 | AI4: 45717 | AJ4: 45748 | AK4: 45778 | AL4: 45809 | AM4: TOTAL | AN4: Variación | AO4: Acumulado | AP4: Estatus
A5: 101 | D5: 5000 | E5: 3285 | F5: 3285 | G5: 3285 | H5: 3285 | I5: 3285 | J5: 3285 | K5: 3285 | L5: 3285 | M5: 3285 | N5: 3285 | O5: 3285 | P5: 3285 | Q5: 3285 | R5: 3285 | S5: 3285 | T5: 3285 | U5: 3285 | V5: 3285 | W5: 3285 | X5: 3285 | Y5: 3285 | Z5: 3285 | AA5: 3330 | AM5: =SUM(B5:AL5) -> 80600 | AN5: =+AM5-'SANTA ELISA'!J5 -> 0 | AO5: =SUM(B5:AI5) -> 80600 | AP5: =VLOOKUP(A5,'SANTA ELISA'!$B$4:$BG$79,53,0) -> 725400
A6: 102 | I6: 5000 | J6: 4240 | K6: 4240 | L6: 4240 | M6: 4240 | N6: 4240 | O6: 4240 | P6: 4240 | Q6: 4240 | R6: 4240 | S6: 4240 | T6: 4240 | U6: 4240 | V6: 4240 | W6: 4240 | X6: 4240 | Y6: 4240 | Z6: 4240 | AA6: 4320 | AM6: =SUM(B6:AL6) -> 81400 | AN6: =+AM6-'SANTA ELISA'!J6 -> 0 | AO6: =SUM(B6:AI6) -> 81400 | AP6: =VLOOKUP(A6,'SANTA ELISA'!$B$4:$BG$79,53,0) -> 652330.22
A7: 103 | AC7: 5000 | AD7: 5000 | AE7: 5000 | AF7: 5000 | AG7: 21650 | AH7: 21650 | AM7: =SUM(B7:AL7) -> 63300 | AN7: =+AM7-'SANTA ELISA'!J7 -> 0 | AO7: =SUM(B7:AI7) -> 63300 | AP7: =VLOOKUP(A7,'SANTA ELISA'!$B$4:$BG$79,53,0) -> 1201700
A8: 104 | AE8: 5000 | AF8: 50100 | AM8: =SUM(B8:AL8) -> 55100 | AN8: =+AM8-'SANTA ELISA'!J8 -> 0 | AO8: =SUM(B8:AI8) -> 55100 | AP8: =VLOOKUP(A8,'SANTA ELISA'!$B$4:$BG$79,53,0) -> 1045100
A9: 105 | J9: 5000 | K9: 2500 | L9: 2500 | M9: 3000 | N9: 1000 | O9: 1000 | P9: 2500 | Q9: 2500 | R9: 6000 | S9: 6000 | T9: 6000 | U9: 6000 | V9: 2500 | W9: 2500 | X9: 2500 | Y9: 2500 | Z9: 5000 | AA9: 5000 | AM9: =SUM(B9:AL9) -> 64000 | AN9: =+AM9-'SANTA ELISA'!J9 -> 0 | AO9: =SUM(B9:AI9) -> 64000 | AP9: =VLOOKUP(A9,'SANTA ELISA'!$B$4:$BG$79,53,0) -> 575700
A10: 201 | AH10: 5000 | AI10: 645000 | AM10: =SUM(B10:AL10) -> 650000 | AN10: =+AM10-'SANTA ELISA'!J10 -> 0 | AO10: =SUM(B10:AI10) -> 650000 | AP10: =VLOOKUP(A10,'SANTA ELISA'!$B$4:$BG$79,53,0) -> 645000
A11: 202 | X11: 5000 | Y11: 3500 | Z11: 3500 | AA11: 3500 | AB11: 3500 | AC11: 3500 | AD11: 3500 | AE11: 74000 | AM11: =SUM(B11:AL11) -> 100000 | AN11: =+AM11-'SANTA ELISA'!J11 -> 0 | AO11: =SUM(B11:AI11) -> 100000 | AP11: =VLOOKUP(A11,'SANTA ELISA'!$B$4:$BG$79,53,0) -> 705400
A12: 203 | B12: 5000 | C12: 3434.78 | D12: 3434.78 | E12: 3434.78 | F12: 3434.78 | G12: 3434.78 | H12: 3434.78 | I12: 3434.78 | J12: 3434.78 | K12: 3434.78 | L12: 3434.78 | M12: 3434.78 | N12: 3434.78 | O12: 3434.78 | P12: 3434.78 | Q12: 3434.78 | R12: 3434.78 | S12: 3434.78 | T12: 3434.78 | U12: 3434.78 | V12: 3434.78 | W12: 3434.78 | X12: 3434.78 | Y12: 3434.84 | AM12: =SUM(B12:AL12) -> 84000 | AN12: =+AM12-'SANTA ELISA'!J12 -> 0 | AO12: =SUM(B12:AI12) -> 84000 | AP12: =VLOOKUP(A12,'SANTA ELISA'!$B$4:$BG$79,53,0) -> 689591.49
A13: 204 | W13: 3000 | X13: 4500 | Y13: 2500 | Z13: 2500 | AA13: 2500 | AB13: 2500 | AC13: 6500 | AD13: 6500 | AE13: 6600 | AM13: =SUM(B13:AL13) -> 37100 | AN13: =+AM13-'SANTA ELISA'!J13 -> 0 | AO13: =SUM(B13:AI13) -> 37100 | AP13: =VLOOKUP(A13,'SANTA ELISA'!$B$4:$BG$79,53,0) -> 445693.09
A14: 205 | P14: 6000 | Q14: 5610 | R14: 5610 | S14: 5610 | T14: 5610 | U14: 5610 | V14: 5610 | W14: 5610 | X14: 5610 | Y14: 5610 | Z14: 5610 | AA14: 5610 | AB14: 5610 | AM14: =SUM(B14:AL14) -> 73320 | AN14: =+AM14-'SANTA ELISA'!J14 -> 0 | AO14: =SUM(B14:AI14) -> 73320 | AP14: =VLOOKUP(A14,'SANTA ELISA'!$B$4:$BG$79,53,0) -> 435029.72
A15: 206 | AF15: 5000 | AG15: 21250 | AH15: 21250 | AM15: =SUM(B15:AL15) -> 47500 | AN15: =+AM15-'SANTA ELISA'!J15 -> 0 | AO15: =SUM(B15:AI15) -> 47500 | AP15: =VLOOKUP(A15,'SANTA ELISA'!$B$4:$BG$79,53,0) -> 923800
A16: 207 | V16: 5000 | W16: 3700 | X16: 3700 | Y16: 3700 | Z16: 3700 | AA16: 3700 | AB16: 3700 | AC16: 3700 | AD16: 3700 | AE16: 3900 | AM16: =SUM(B16:AL16) -> 38500 | AN16: =+AM16-'SANTA ELISA'!J16 -> 0 | AO16: =SUM(B16:AI16) -> 38500 | AP16: =VLOOKUP(A16,'SANTA ELISA'!$B$4:$BG$79,53,0) -> 468690.28
A17: 208 | AM17: =SUM(B17:AL17) -> 0 | AN17: =+AM17-'SANTA ELISA'!J17 -> -65000 | AO17: =SUM(B17:AI17) -> 0 | AP17: =VLOOKUP(A17,'SANTA ELISA'!$B$4:$BG$79,53,0) -> 650000
A18: 301 | K18: 5000 | L18: 2500 | M18: 3365 | N18: 3365 | O18: 3365 | P18: 3365 | Q18: 3365 | R18: 3365 | S18: 3365 | T18: 3365 | U18: 3365 | V18: 3365 | W18: 3365 | X18: 3365 | Y18: 3365 | Z18: 3365 | AA18: 3390 | AM18: =SUM(B18:AL18) -> 58000 | AN18: =+AM18-'SANTA ELISA'!J18 -> 0 | AO18: =SUM(B18:AI18) -> 58000 | AP18: =VLOOKUP(A18,'SANTA ELISA'!$B$4:$BG$79,53,0) -> 309477.87
A19: 302 | F19: 40000 | G19: 6000 | H19: 6000 | I19: 6000 | J19: 6000 | K19: 6000 | L19: 6000 | M19: 6000 | N19: 6000 | O19: 6000 | P19: 6000 | Q19: 6000 | R19: 6000 | S19: 6000 | T19: 6000 | U19: 6000 | V19: 6000 | W19: 6000 | X19: 6000 | Y19: 6000 | Z19: 6000 | AA19: 6000 | AM19: =SUM(B19:AL19) -> 166000 | AN19: =+AM19-'SANTA ELISA'!J19 -> -34000 | AO19: =SUM(B19:AI19) -> 166000 | AP19: =VLOOKUP(A19,'SANTA ELISA'!$B$4:$BG$79,53,0) -> 717500
A20: 303 | AD20: 5000 | AE20: 21533 | AF20: 21533 | AM20: =SUM(B20:AL20) -> 48066 | AN20: =+AM20-'SANTA ELISA'!J20 -> 0 | AO20: =SUM(B20:AI20) -> 48066 | AP20: =VLOOKUP(A20,'SANTA ELISA'!$B$4:$BG$79,53,0) -> 546878.68
A21: 304 | J21: 70500 | K21: 3500 | L21: 3500 | M21: 3500 | N21: 3500 | O21: 3500 | P21: 3500 | Q21: 3500 | R21: 3500 | S21: 3500 | T21: 3500 | U21: 3500 | V21: 3500 | W21: 3500 | X21: 3500 | Y21: 3500 | Z21: 3500 | AA21: 3500 | AM21: =SUM(B21:AL21) -> 130000 | AN21: =+AM21-'SANTA ELISA'!J21 -> 0 | AO21: =SUM(B21:AI21) -> 130000 | AP21: =VLOOKUP(A21,'SANTA ELISA'!$B$4:$BG$79,53,0) -> 456605.45
A22: 305 | I22: 5000 | J22: 5275 | K22: 5275 | L22: 5275 | M22: 5275 | N22: 5275 | O22: 5275 | P22: 5275 | Q22: 5275 | R22: 5275 | S22: 5275 | T22: 5275 | U22: 5275 | V22: 5275 | W22: 5275 | X22: 5275 | Y22: 5275 | Z22: 5275 | AA22: 5325 | AM22: =SUM(B22:AL22) -> 100000 | AN22: =+AM22-'SANTA ELISA'!J22 -> 0 | AO22: =SUM(B22:AI22) -> 100000 | AP22: =VLOOKUP(A22,'SANTA ELISA'!$B$4:$BG$79,53,0) -> 435029.72
A23: 306 | AF23: 5000 | AG23: 42500 | AM23: =SUM(B23:AL23) -> 47500 | AN23: =+AM23-'SANTA ELISA'!J23 -> 0 | AO23: =SUM(B23:AI23) -> 47500 | AP23: =VLOOKUP(A23,'SANTA ELISA'!$B$4:$BG$79,53,0) -> 915700
A24: 307 | AF24: 5000 | AG24: 17750 | AH24: 17750 | AM24: =SUM(B24:AL24) -> 40500 | AN24: =+AM24-'SANTA ELISA'!J24 -> 0 | AO24: =SUM(B24:AI24) -> 40500 | AP24: =VLOOKUP(A24,'SANTA ELISA'!$B$4:$BG$79,53,0) -> 590900
A25: 308 | AF25: 5000 | AG25: 29000 | AM25: =SUM(B25:AL25) -> 34000 | AN25: =+AM25-'SANTA ELISA'!J25 -> 0 | AO25: =SUM(B25:AI25) -> 34000 | AP25: =VLOOKUP(A25,'SANTA ELISA'!$B$4:$BG$79,53,0) -> 615000
A26: 401 | G26: 5000 | H26: 2480 | I26: 2480 | J26: 2480 | K26: 2480 | L26: 2480 | M26: 2480 | N26: 2480 | O26: 2480 | P26: 2480 | Q26: 2480 | R26: 2480 | S26: 2480 | T26: 2480 | U26: 2480 | V26: 2480 | W26: 2480 | X26: 2480 | Y26: 2480 | Z26: 2480 | AA26: 2660 | AM26: =SUM(B26:AL26) -> 54780 | AN26: =+AM26-'SANTA ELISA'!J26 -> 0 | AO26: =SUM(B26:AI26) -> 54780 | AP26: =VLOOKUP(A26,'SANTA ELISA'!$B$4:$BG$79,53,0) -> 483000
A27: 402 | O27: 5000 | P27: 5449.17 | Q27: 5449.17 | R27: 5449.17 | S27: 5449.17 | T27: 5449.17 | U27: 5449.17 | V27: 5449.17 | W27: 5449.17 | X27: 5449.17 | Y27: 5449.17 | Z27: 5449.17 | AA27: 5449.13 | AM27: =SUM(B27:AL27) -> 70390 | AN27: =+AM27-'SANTA ELISA'!J27 -> 0 | AO27: =SUM(B27:AI27) -> 70390 | AP27: =VLOOKUP(A27,'SANTA ELISA'!$B$4:$BG$79,53,0) -> 422900
A28: 403 | AM28: =SUM(B28:AL28) -> 0 | AN28: =+AM28-'SANTA ELISA'!J28 -> -48242 | AO28: =SUM(B28:AI28) -> 0 | AP28: =VLOOKUP(A28,'SANTA ELISA'!$B$4:$BG$79,53,0) -> 942821
A29: 404 | J29: 5000 | K29: 3500 | L29: 3500 | M29: 3500 | N29: 3500 | O29: 3500 | P29: 3500 | Q29: 3500 | R29: 3500 | S29: 3500 | T29: 3500 | U29: 3500 | V29: 3500 | W29: 3500 | X29: 3500 | Y29: 3500 | Z29: 3500 | AA29: 4500 | AM29: =SUM(B29:AL29) -> 65500 | AN29: =+AM29-'SANTA ELISA'!J29 -> 0 | AO29: =SUM(B29:AI29) -> 65500 | AP29: =VLOOKUP(A29,'SANTA ELISA'!$B$4:$BG$79,53,0) -> 589500
A30: 405 | I30: 5000 | J30: 3500 | K30: 3500 | L30: 3500 | M30: 3500 | N30: 3500 | O30: 3500 | P30: 3500 | Q30: 3500 | R30: 3500 | S30: 3500 | T30: 3500 | U30: 3500 | V30: 3500 | W30: 3500 | X30: 3500 | Y30: 3500 | Z30: 3500 | AA30: 350000 | AM30: =SUM(B30:AL30) -> 414500 | AN30: =+AM30-'SANTA ELISA'!J30 -> 0 | AO30: =SUM(B30:AI30) -> 414500 | AP30: =VLOOKUP(A30,'SANTA ELISA'!$B$4:$BG$79,53,0) -> 175000
A31: 406 | AE31: =5000+22250 -> 27250 | AF31: 22250 | AM31: =SUM(B31:AL31) -> 49500 | AN31: =+AM31-'SANTA ELISA'!J31 -> 0 | AO31: =SUM(B31:AI31) -> 49500 | AP31: =VLOOKUP(A31,'SANTA ELISA'!$B$4:$BG$79,53,0) -> 899300
A32: 407 | I32: 5000 | J32: 3500 | K32: 3500 | L32: 3500 | M32: 3500 | N32: 3500 | O32: 3500 | P32: 3500 | Q32: 3500 | R32: 3500 | S32: 3500 | T32: 3500 | U32: 3500 | V32: 3500 | W32: 3500 | X32: 3500 | Y32: 3500 | Z32: 3500 | AA32: 3500 | AM32: =SUM(B32:AL32) -> 68000 | AN32: =+AM32-'SANTA ELISA'!J32 -> 0 | AO32: =SUM(B32:AI32) -> 68000 | AP32: =VLOOKUP(A32,'SANTA ELISA'!$B$4:$BG$79,53,0) -> 488991.83
A33: 408 | G33: 5000 | H33: 2480 | I33: 2480 | J33: 2480 | K33: 2480 | L33: 2480 | M33: 2480 | N33: 2480 | O33: 2480 | P33: 2480 | Q33: 2480 | R33: 2480 | S33: 2480 | T33: 2480 | U33: 2480 | V33: 2480 | W33: 2480 | X33: 2480 | Y33: 2480 | Z33: 2480 | AA33: 2660 | AM33: =SUM(B33:AL33) -> 54780 | AN33: =+AM33-'SANTA ELISA'!J33 -> 0 | AO33: =SUM(B33:AI33) -> 54780 | AP33: =VLOOKUP(A33,'SANTA ELISA'!$B$4:$BG$79,53,0) -> 492984.65
A34: 501 | E34: 5000 | F34: 2260 | G34: 2260 | H34: 2260 | I34: 2260 | J34: 2260 | K34: 2260 | L34: 2260 | M34: 2260 | N34: 2260 | O34: 2260 | P34: 2260 | Q34: 2260 | R34: 2260 | S34: 2260 | T34: 2260 | U34: 2260 | V34: 2260 | W34: 2260 | X34: 2260 | Y34: 2260 | Z34: 2260 | AA34: 2240 | AM34: =SUM(B34:AL34) -> 54700 | AN34: =+AM34-'SANTA ELISA'!J34 -> 0 | AO34: =SUM(B34:AI34) -> 54700 | AP34: =VLOOKUP(A34,'SANTA ELISA'!$B$4:$BG$79,53,0) -> 335086.45
A35: 502 | I35: 5000 | J35: 3555 | K35: 3555 | L35: 3555 | M35: 3555 | N35: 3555 | O35: 3555 | P35: 3555 | Q35: 3555 | R35: 3555 | S35: 3555 | T35: 3555 | U35: 3555 | V35: 3555 | W35: 3555 | X35: 3555 | Y35: 3555 | Z35: 3555 | AA35: 3365 | AM35: =SUM(B35:AL35) -> 68800 | AN35: =+AM35-'SANTA ELISA'!J35 -> 0 | AO35: =SUM(B35:AI35) -> 68800 | AP35: =VLOOKUP(A35,'SANTA ELISA'!$B$4:$BG$79,53,0) -> 497324.27
A36: 503 | V36: 5000 | W36: 4900 | X36: 4900 | Y36: 4900 | Z36: 4900 | AA36: 4900 | AB36: 4900 | AC36: 4900 | AD36: 4900 | AE36: 5300 | AM36: =SUM(B36:AL36) -> 49500 | AN36: =+AM36-'SANTA ELISA'!J36 -> 0 | AO36: =SUM(B36:AI36) -> 49500 | AP36: =VLOOKUP(A36,'SANTA ELISA'!$B$4:$BG$79,53,0) -> 930000
A37: 504 | F37: 5000 | G37: 2673 | H37: 2673 | I37: 2673 | J37: 2673 | K37: 2673 | L37: 2673 | M37: 2673 | N37: 2673 | O37: 2673 | P37: 2673 | Q37: 2673 | R37: 2673 | S37: 2673 | T37: 2673 | U37: 2673 | V37: 2673 | W37: 2673 | X37: 2673 | Y37: 2673 | Z37: 2673 | AA37: 2673 | AB37: 2673 | AC37: 2694 | AM37: =SUM(B37:AL37) -> 66500 | AN37: =+AM37-'SANTA ELISA'!J37 -> 0 | AO37: =SUM(B37:AI37) -> 66500 | AP37: =VLOOKUP(A37,'SANTA ELISA'!$B$4:$BG$79,53,0) -> 403500
A38: 505 | AF38: 5000 | AG38: 17750 | AH38: 17750 | AM38: =SUM(B38:AL38) -> 40500 | AN38: =+AM38-'SANTA ELISA'!J38 -> 0 | AO38: =SUM(B38:AI38) -> 40500 | AP38: =VLOOKUP(A38,'SANTA ELISA'!$B$4:$BG$79,53,0) -> 764500
A39: 506 | Z39: 5000 | AA39: 8500 | AB39: 8500 | AC39: 8500 | AD39: 8500 | AE39: 8500 | AM39: =SUM(B39:AL39) -> 47500 | AN39: =+AM39-'SANTA ELISA'!J39 -> 0 | AO39: =SUM(B39:AI39) -> 47500 | AP39: =VLOOKUP(A39,'SANTA ELISA'!$B$4:$BG$79,53,0) -> 869929.1
A40: 507 | I40: 5000 | J40: 3550 | K40: 3550 | L40: 3550 | M40: 3550 | N40: 3550 | O40: 3550 | P40: 3550 | Q40: 3550 | R40: 3550 | S40: 3550 | T40: 3550 | U40: 3550 | V40: 3550 | W40: 3550 | X40: 3550 | Y40: 3550 | Z40: 3550 | AA40: 3650 | AM40: =SUM(B40:AL40) -> 69000 | AN40: =+AM40-'SANTA ELISA'!J40 -> 0 | AO40: =SUM(B40:AI40) -> 69000 | AP40: =VLOOKUP(A40,'SANTA ELISA'!$B$4:$BG$79,53,0) -> 445000
A41: 508 | AF41: 5000 | AG41: 29000 | AM41: =SUM(B41:AL41) -> 34000 | AN41: =+AM41-'SANTA ELISA'!J41 -> 0 | AO41: =SUM(B41:AI41) -> 34000 | AP41: =VLOOKUP(A41,'SANTA ELISA'!$B$4:$BG$79,53,0) -> 615000
A42: 601 | E42: 5000 | F42: 1947.83 | G42: 1947.83 | H42: 1947.83 | I42: 1947.83 | J42: 1947.83 | K42: 1947.83 | L42: 1947.83 | M42: 1947.83 | N42: 1947.83 | O42: 1947.83 | P42: 1947.83 | Q42: 1947.83 | R42: 1947.83 | S42: 1947.83 | T42: 1947.83 | U42: 1947.83 | V42: 1947.83 | W42: 1947.83 | X42: 1947.83 | Y42: 1947.83 | Z42: 1947.83 | AA42: 1947.83 | AB42: 1947.74 | AM42: =SUM(B42:AL42) -> 49800 | AN42: =+AM42-'SANTA ELISA'!J42 -> 0 | AO42: =SUM(B42:AI42) -> 49800 | AP42: =VLOOKUP(A42,'SANTA ELISA'!$B$4:$BG$79,53,0) -> 333187.37
A43: 602 | G43: 5000 | H43: 3240 | I43: 3240 | J43: 3240 | K43: 3240 | L43: 3240 | M43: 3240 | N43: 3240 | O43: 3240 | P43: 3240 | Q43: 3240 | R43: 3240 | S43: 3240 | T43: 3240 | U43: 3240 | V43: 3240 | W43: 3240 | X43: 3240 | Y43: 3240 | Z43: 3240 | AA43: 3240 | AM43: =SUM(B43:AL43) -> 69800 | AN43: =+AM43-'SANTA ELISA'!J43 -> 0 | AO43: =SUM(B43:AI43) -> 69800 | AP43: =VLOOKUP(A43,'SANTA ELISA'!$B$4:$BG$79,53,0) -> 468282.11
A44: 603 | AD44: 66582.4 | AE44: 7050 | AF44: 7050 | AM44: =SUM(B44:AL44) -> 80682.4 | AN44: =+AM44-'SANTA ELISA'!J44 -> 0 | AO44: =SUM(B44:AI44) -> 80682.4 | AP44: =VLOOKUP(A44,'SANTA ELISA'!$B$4:$BG$79,53,0) -> 671165.65
A45: 604 | V45: 5000 | W45: 3500 | X45: 3500 | Y45: 3500 | Z45: 3500 | AA45: 728264 | AM45: =SUM(B45:AL45) -> 747264 | AN45: =+AM45-'SANTA ELISA'!J45 -> 0 | AO45: =SUM(B45:AI45) -> 747264 | AP45: =VLOOKUP(A45,'SANTA ELISA'!$B$4:$BG$79,53,0) -> 0
A46: 605 | AF46: 5000 | AG46: 35900 | AM46: =SUM(B46:AL46) -> 40900 | AN46: =+AM46-'SANTA ELISA'!J46 -> 0 | AO46: =SUM(B46:AI46) -> 40900 | AP46: =VLOOKUP(A46,'SANTA ELISA'!$B$4:$BG$79,53,0) -> 809100
A47: 606 | AB47: 5000 | AC47: 14800 | AD47: 14800 | AE47: 14800 | AM47: =SUM(B47:AL47) -> 49400 | AN47: =+AM47-'SANTA ELISA'!J47 -> 0 | AO47: =SUM(B47:AI47) -> 49400 | AP47: =VLOOKUP(A47,'SANTA ELISA'!$B$4:$BG$79,53,0) -> 591706.96
A48: 607 | F48: 338100 | Z48: 338100 | AM48: =SUM(B48:AL48) -> 676200 | AN48: =+AM48-'SANTA ELISA'!J48 -> 0 | AO48: =SUM(B48:AI48) -> 676200 | AP48: =VLOOKUP(A48,'SANTA ELISA'!$B$4:$BG$79,53,0) -> -5000
A49: 608 | D49: 5000 | E49: 2000 | F49: 2000 | G49: 2000 | H49: 2000 | I49: 2000 | J49: 2000 | K49: 2000 | L49: 2000 | M49: 2000 | N49: 2000 | O49: 2000 | P49: 2000 | Q49: 2000 | R49: 2000 | S49: 2000 | T49: 2000 | U49: 2000 | V49: 2000 | W49: 2000 | X49: 2000 | Y49: 2000 | Z49: 2800 | AM49: =SUM(B49:AL49) -> 49800 | AN49: =+AM49-'SANTA ELISA'!J49 -> 0 | AO49: =SUM(B49:AI49) -> 49800 | AP49: =VLOOKUP(A49,'SANTA ELISA'!$B$4:$BG$79,53,0) -> 333014.03
A50: 701 | D50: 5000 | E50: 2725 | F50: 185000 | G50: 2725 | H50: 2725 | I50: 2725 | J50: 2725 | K50: 2725 | L50: 2725 | M50: 2725 | N50: 2725 | O50: 2725 | P50: 2725 | Q50: 2725 | R50: 2725 | S50: 2725 | T50: 2725 | U50: 2725 | V50: 2725 | W50: 2725 | X50: 2725 | Y50: 2725 | Z50: 2725 | AA50: 2775 | AM50: =SUM(B50:AL50) -> 250000 | AN50: =+AM50-'SANTA ELISA'!J50 -> 0 | AO50: =SUM(B50:AI50) -> 250000 | AP50: =VLOOKUP(A50,'SANTA ELISA'!$B$4:$BG$79,53,0) -> 248000
A51: 702 | F51: 5000 | G51: 3085 | H51: 3085 | I51: 3085 | J51: 3085 | K51: 3085 | L51: 3085 | M51: 3085 | N51: 3085 | O51: 3085 | P51: 3085 | Q51: 3085 | R51: 3085 | S51: 3085 | T51: 3085 | U51: 3085 | V51: 3085 | W51: 3085 | X51: 3085 | Y51: 3085 | Z51: 3085 | AA51: 3100 | AM51: =SUM(B51:AL51) -> 69800 | AN51: =+AM51-'SANTA ELISA'!J51 -> 0 | AO51: =SUM(B51:AI51) -> 69800 | AP51: =VLOOKUP(A51,'SANTA ELISA'!$B$4:$BG$79,53,0) -> 628200
A52: 703 | Y52: 896715.83 | AM52: =SUM(B52:AL52) -> 896715.83 | AN52: =+AM52-'SANTA ELISA'!J52 -> 0 | AO52: =SUM(B52:AI52) -> 896715.83 | AP52: =VLOOKUP(A52,'SANTA ELISA'!$B$4:$BG$79,53,0) -> 0
A53: 704 | B53: 5000 | C53: 1000 | D53: 1000 | E53: 1000 | F53: 1000 | G53: 2738 | H53: 2738 | I53: 2738 | J53: 2738 | K53: 2738 | L53: 2738 | M53: 2738 | N53: 2738 | O53: 2738 | P53: 2738 | Q53: 2738 | R53: 2738 | S53: 2738 | T53: 2738 | U53: 2738 | V53: 2738 | W53: 2738 | X53: 2738 | Y53: 2738 | Z53: 2738 | AA53: 2740 | AM53: =SUM(B53:AL53) -> 66500 | AN53: =+AM53-'SANTA ELISA'!J53 -> 0 | AO53: =SUM(B53:AI53) -> 66500 | AP53: =VLOOKUP(A53,'SANTA ELISA'!$B$4:$BG$79,53,0) -> 451104.27
A54: 705 | C54: 5000 | D54: 2562.5 | E54: 2562.5 | F54: 2562.5 | G54: 2562.5 | H54: 2562.5 | I54: 2562.5 | J54: 2562.5 | K54: 2562.5 | L54: 2562.5 | M54: 2562.5 | N54: 2562.5 | O54: 2562.5 | P54: 2562.5 | Q54: 2562.5 | R54: 2562.5 | S54: 2562.5 | T54: 2562.5 | U54: 2562.5 | V54: 2562.5 | W54: 2562.5 | X54: 2562.5 | Y54: 2562.5 | Z54: 2562.5 | AA54: 2562.5 | AM54: =SUM(B54:AL54) -> 66500 | AN54: =+AM54-'SANTA ELISA'!J54 -> 0 | AO54: =SUM(B54:AI54) -> 66500 | AP54: =VLOOKUP(A54,'SANTA ELISA'!$B$4:$BG$79,53,0) -> 543500
A55: 706 | W55: 5000 | X55: 111875 | Y55: 111875 | Z55: 111875 | AA55: 111875 | AB55: 111875 | AC55: 111875 | AD55: 111875 | AE55: 111875 | AM55: =SUM(B55:AL55) -> 900000 | AN55: =+AM55-'SANTA ELISA'!J55 -> 0 | AO55: =SUM(B55:AI55) -> 900000 | AP55: =VLOOKUP(A55,'SANTA ELISA'!$B$4:$BG$79,53,0) -> 111875
A56: 707 | E56: 5000 | F56: 3000 | G56: 3000 | H56: 3000 | I56: 3000 | J56: 3000 | K56: 3000 | L56: 3000 | M56: 3000 | N56: 3000 | O56: 3000 | P56: 3000 | Q56: 3000 | R56: 3000 | S56: 3000 | T56: 3000 | U56: 3000 | V56: 3000 | W56: 3000 | X56: 3000 | Y56: 3000 | Z56: 3000 | AA56: 8720 | AM56: =SUM(B56:AL56) -> 76720 | AN56: =+AM56-'SANTA ELISA'!J56 -> 0 | AO56: =SUM(B56:AI56) -> 76720 | AP56: =VLOOKUP(A56,'SANTA ELISA'!$B$4:$BG$79,53,0) -> 471723.22
A57: 708 | D57: 5000 | E57: 2000 | F57: 2000 | G57: 2000 | H57: 2000 | I57: 2000 | J57: 2000 | K57: 2000 | L57: 2000 | M57: 2000 | N57: 2000 | O57: 2000 | P57: 2000 | Q57: 2000 | R57: 2000 | S57: 2000 | T57: 2000 | U57: 2000 | V57: 2000 | W57: 2000 | X57: 2000 | Y57: 2000 | Z57: 2800 | AM57: =SUM(B57:AL57) -> 49800 | AN57: =+AM57-'SANTA ELISA'!J57 -> 0 | AO57: =SUM(B57:AI57) -> 49800 | AP57: =VLOOKUP(A57,'SANTA ELISA'!$B$4:$BG$79,53,0) -> 333353.52
A58: 801 | B58: 5000 | C58: 1947.83 | D58: 1947.83 | E58: 1947.83 | F58: 1947.83 | G58: 1947.83 | H58: 1947.83 | I58: 1947.83 | J58: 1947.83 | K58: 1947.83 | L58: 1947.83 | M58: 1947.83 | N58: 1947.83 | O58: 1947.83 | P58: 1947.83 | Q58: 1947.83 | R58: 1947.83 | S58: 1947.83 | T58: 1947.83 | U58: 1947.83 | V58: 1947.83 | W58: 1947.83 | X58: 1947.83 | Y58: 1947.74 | AM58: =SUM(B58:AL58) -> 49800 | AN58: =+AM58-'SANTA ELISA'!J58 -> 0 | AO58: =SUM(B58:AI58) -> 49800 | AP58: =VLOOKUP(A58,'SANTA ELISA'!$B$4:$BG$79,53,0) -> 308362.91
A59: 802 | O59: 5000 | P59: 5688.46 | Q59: 5688.46 | R59: 5688.46 | S59: 5688.46 | T59: 5688.46 | U59: 5688.46 | V59: 5688.46 | W59: 5688.46 | X59: 5688.46 | Y59: 5688.46 | Z59: 5688.46 | AA59: 5688.46 | AB59: 5688.48 | AM59: =SUM(B59:AL59) -> 78950 | AN59: =+AM59-'SANTA ELISA'!J59 -> 0 | AO59: =SUM(B59:AI59) -> 78950 | AP59: =VLOOKUP(A59,'SANTA ELISA'!$B$4:$BG$79,53,0) -> 710550
A60: 803 | AE60: 5000 | AF60: 22658.55 | AG60: 22658.55 | AM60: =SUM(B60:AL60) -> 50317.1 | AN60: =+AM60-'SANTA ELISA'!J60 -> 0 | AO60: =SUM(B60:AI60) -> 50317.1 | AP60: =VLOOKUP(A60,'SANTA ELISA'!$B$4:$BG$79,53,0) -> 954300
A61: 804 | V61: 5000 | W61: 3760 | X61: 3760 | Y61: 3760 | Z61: 3760 | AA61: 3760 | AB61: 3760 | AC61: 3760 | AD61: 3760 | AE61: 3820 | AM61: =SUM(B61:AL61) -> 38900 | AN61: =+AM61-'SANTA ELISA'!J61 -> 0 | AO61: =SUM(B61:AI61) -> 38900 | AP61: =VLOOKUP(A61,'SANTA ELISA'!$B$4:$BG$79,53,0) -> 446232.63
A62: 805 | K62: 5000 | L62: 4400 | M62: 4400 | N62: 4400 | O62: 4400 | P62: 4400 | Q62: 4400 | R62: 4400 | S62: 4400 | T62: 4400 | U62: 4400 | V62: 4400 | W62: 4400 | X62: 4400 | Y62: 4400 | Z62: 4400 | AA62: 4400 | AM62: =SUM(B62:AL62) -> 75400 | AN62: =+AM62-'SANTA ELISA'!J62 -> 0 | AO62: =SUM(B62:AI62) -> 75400 | AP62: =VLOOKUP(A62,'SANTA ELISA'!$B$4:$BG$79,53,0) -> 642400
A63: 806 | T63: 5000 | U63: 4236 | V63: 4236 | W63: 4236 | X63: 4236 | Y63: 4236 | Z63: 4236 | AA63: 4236 | AB63: 4236 | AC63: 4236 | AD63: 4236 | AE63: 4240 | AM63: =SUM(B63:AL63) -> 51600 | AN63: =+AM63-'SANTA ELISA'!J63 -> 0 | AO63: =SUM(B63:AI63) -> 51600 | AP63: =VLOOKUP(A63,'SANTA ELISA'!$B$4:$BG$79,53,0) -> 602175.3
A64: 807 | AG64: 5000 | AH64: 245000 | AM64: =SUM(B64:AL64) -> 250000 | AN64: =+AM64-'SANTA ELISA'!J64 -> 0 | AO64: =SUM(B64:AI64) -> 250000 | AP64: =VLOOKUP(A64,'SANTA ELISA'!$B$4:$BG$79,53,0) -> 600000
A65: 808 | C65: 3000 | D65: 3947.83 | E65: 1947.83 | F65: 1947.83 | G65: 1947.83 | H65: 1947.83 | I65: 1947.83 | J65: 1947.83 | K65: 1947.83 | L65: 1947.83 | M65: 1947.83 | N65: 1947.83 | O65: 1947.83 | P65: 1947.83 | Q65: 1947.83 | R65: 1947.83 | S65: 1947.83 | T65: 1947.83 | U65: 1947.83 | V65: 1947.83 | W65: 1947.83 | X65: 1947.83 | Y65: 1947.83 | Z65: 1947.74 | AM65: =SUM(B65:AL65) -> 49800 | AN65: =+AM65-'SANTA ELISA'!J65 -> 0 | AO65: =SUM(B65:AI65) -> 49800 | AP65: =VLOOKUP(A65,'SANTA ELISA'!$B$4:$BG$79,53,0) -> 400000
A66: 901 | D66: 2000 | E66: 3000 | F66: 2036.36 | G66: 2036.36 | H66: 2036.36 | I66: 2036.36 | J66: 2036.36 | K66: 2036.36 | L66: 2036.36 | M66: 2036.36 | N66: 2036.36 | O66: 2036.36 | P66: 2036.36 | Q66: 2036.36 | R66: 2036.36 | S66: 2036.36 | T66: 2036.36 | U66: 2036.36 | V66: 2036.36 | W66: 2036.36 | X66: 2036.36 | Y66: 2036.36 | Z66: 2036.36 | AA66: 2036.44 | AM66: =SUM(B66:AL66) -> 49800 | AN66: =+AM66-'SANTA ELISA'!J66 -> 0 | AO66: =SUM(B66:AI66) -> 49800 | AP66: =VLOOKUP(A66,'SANTA ELISA'!$B$4:$BG$79,53,0) -> 337443.77
A67: 902 | S67: 3000 | T67: 3041 | U67: 3041 | V67: 3041 | W67: 3041 | X67: 3041 | Y67: 3041 | Z67: 3041 | AA67: 3041 | AB67: 3041 | AC67: 3041 | AD67: 3041 | AE67: 3049 | AM67: =SUM(B67:AL67) -> 39500 | AN67: =+AM67-'SANTA ELISA'!J67 -> 0 | AO67: =SUM(B67:AI67) -> 39500 | AP67: =VLOOKUP(A67,'SANTA ELISA'!$B$4:$BG$79,53,0) -> 748900
A68: 903 | AA68: 26440 | AB68: 6000 | AC68: 6000 | AD68: 6000 | AE68: 155580 | AM68: =SUM(B68:AL68) -> 200020 | AN68: =+AM68-'SANTA ELISA'!J68 -> 0 | AO68: =SUM(B68:AI68) -> 200020 | AP68: =VLOOKUP(A68,'SANTA ELISA'!$B$4:$BG$79,53,0) -> 544782.29
A69: 904 | Y69: 5000 | Z69: 4000 | AA69: 4000 | AB69: 4000 | AC69: 4000 | AD69: 4000 | AE69: 745000 | AM69: =SUM(B69:AL69) -> 770000 | AN69: =+AM69-'SANTA ELISA'!J69 -> 0 | AO69: =SUM(B69:AI69) -> 770000 | AP69: =VLOOKUP(A69,'SANTA ELISA'!$B$4:$BG$79,53,0) -> 3520.45
A70: 905 | K70: 5000 | L70: 4400 | M70: 4400 | N70: 4400 | O70: 4400 | P70: 4400 | Q70: 4400 | R70: 4400 | S70: 4400 | T70: 4400 | U70: 4400 | V70: 4400 | W70: 4400 | X70: 4400 | Y70: 4400 | Z70: 4400 | AA70: 4400 | AM70: =SUM(B70:AL70) -> 75400 | AN70: =+AM70-'SANTA ELISA'!J70 -> 0 | AO70: =SUM(B70:AI70) -> 75400 | AP70: =VLOOKUP(A70,'SANTA ELISA'!$B$4:$BG$79,53,0) -> 456537.04
A71: 906 | P71: 5000 | Q71: 8741 | R71: 8741 | S71: 8741 | T71: 8741 | U71: 8741 | V71: 8741 | W71: 8741 | X71: 8741 | Y71: 8741 | Z71: 8741 | AA71: 8750 | AM71: =SUM(B71:AL71) -> 101160 | AN71: =+AM71-'SANTA ELISA'!J71 -> 0 | AO71: =SUM(B71:AI71) -> 101160 | AP71: =VLOOKUP(A71,'SANTA ELISA'!$B$4:$BG$79,53,0) -> 910400
A72: 907 | G72: 678182.1 | AM72: =SUM(B72:AL72) -> 678182.1 | AN72: =+AM72-'SANTA ELISA'!J72 -> 0 | AO72: =SUM(B72:AI72) -> 678182.1 | AP72: =VLOOKUP(A72,'SANTA ELISA'!$B$4:$BG$79,53,0) -> 0
A73: 908 | AM73: =SUM(B73:AL73) -> 0 | AN73: =+AM73-'SANTA ELISA'!J73 -> -49800 | AO73: =SUM(B73:AI73) -> 0 | AP73: =VLOOKUP(A73,'SANTA ELISA'!$B$4:$BG$79,53,0) -> 690000
A74: 1001 | B74: 5000 | C74: 1947.83 | D74: 1947.83 | E74: 1947.83 | F74: 1947.83 | G74: 1947.83 | H74: 1947.83 | I74: 1947.83 | J74: 1947.83 | K74: 1947.83 | L74: 1947.83 | M74: 1947.83 | N74: 1947.83 | O74: 1947.83 | P74: 1947.83 | Q74: 1947.83 | R74: 1947.83 | S74: 1947.83 | T74: 1947.83 | U74: 1947.83 | V74: 1947.83 | W74: 1947.83 | X74: 1947.83 | Y74: 1947.74 | AM74: =SUM(B74:AL74) -> 49800 | AN74: =+AM74-'SANTA ELISA'!J74 -> 0 | AO74: =SUM(B74:AI74) -> 49800 | AP74: =VLOOKUP(A74,'SANTA ELISA'!$B$4:$BG$79,53,0) -> 448197.81
A75: 1002 | K75: 5000 | L75: 4620 | M75: 4620 | N75: 4620 | O75: 4620 | P75: 4620 | Q75: 4620 | R75: 4620 | S75: 4620 | T75: 4620 | U75: 4620 | V75: 4620 | W75: 4620 | X75: 4620 | Y75: 4620 | Z75: 4620 | AA75: 4600 | AM75: =SUM(B75:AL75) -> 78900 | AN75: =+AM75-'SANTA ELISA'!J75 -> 0 | AO75: =SUM(B75:AI75) -> 78900 | AP75: =VLOOKUP(A75,'SANTA ELISA'!$B$4:$BG$79,53,0) -> 473183.24
A76: 1003 | AE76: 5000 | AF76: 29000 | AG76: 29000 | AM76: =SUM(B76:AL76) -> 63000 | AN76: =+AM76-'SANTA ELISA'!J76 -> 0 | AO76: =SUM(B76:AI76) -> 63000 | AP76: =VLOOKUP(A76,'SANTA ELISA'!$B$4:$BG$79,53,0) -> 1097500
A77: L1 | AM77: =SUM(B77:AL77) -> 0 | AN77: =+AM77-'SANTA ELISA'!J77 -> -25506 | AO77: =SUM(B77:AI77) -> 0 | AP77: =VLOOKUP(A77,'SANTA ELISA'!$B$4:$BG$79,53,0) -> 252560
A78: L2 | AM78: =SUM(B78:AL78) -> 0 | AN78: =+AM78-'SANTA ELISA'!J78 -> -31896 | AO78: =SUM(B78:AI78) -> 0 | AP78: =VLOOKUP(A78,'SANTA ELISA'!$B$4:$BG$79,53,0) -> 316460
A79: L3 | AM79: =SUM(B79:AL79) -> 0 | AN79: =+AM79-'SANTA ELISA'!J79 -> -92000 | AO79: =SUM(B79:AI79) -> 0 | AP79: =VLOOKUP(A79,'SANTA ELISA'!$B$4:$BG$79,53,0) -> 460000
B80: =SUM(B5:B79) -> 20000 | C80: =SUM(C5:C79) -> 16330.44 | D80: =SUM(D5:D79) -> 36840.77 | E80: =SUM(E5:E79) -> 40850.77 | F80: =SUM(F5:F79) -> 602469.96 | G80: =SUM(G5:G79) -> 738773.06 | H80: =SUM(H5:H79) -> 53790.96 | I80: =SUM(I5:I79) -> 83790.96 | ... AN80: =SUM(AN5:AN79) -> -346444
B81: =+B80 -> 20000 | C81: =+C80+B81 -> 36330.44 | D81: =+D80+C81 -> 73171.21 | E81: =+E80+D81 -> 114021.98 | F81: =+F80+E81 -> 716491.94 | G81: =+G80+F81 -> 1455265 | H81: =+H80+G81 -> 1509056 | I81: =+I80+H81 -> 1592846.9 | J81: =+J80+I81 -> 1750757.9 | ... AL81: =+AL80+AK81 -> 10097247

Sheet ANÁLISIS
A1: Apto. | B1: Notas | C1: Cliente | D1: Fecha Reserva | E1: Estatus | F1: Precio de Venta | G1: Enganche | H1: TOTAL ENGANCHES Y RESERVAS | I1: SALDO PENDIENTE ENGANCHE | J1: % PENDIENTE | K1: SALDO A FINANCIAR POR EL BANCO | L1: % A FINANCIAR | M1: Proyección de Cobros (S/ Modelo Financiero)
A2: 608 | B2: Plan de pagos especiales | C2: Alfonso Videche Rodriguez | D2: 45324 | E2: 4.Plan de pagos | F2: 1183693 | G2: 118393 | H2: 85000 | I2: -33393 | J2: -0.28205215 | K2: 1098693 | L2: 0.92819084 | M2: 118393
A3: 708 | B3: Plan de pagos especiales | C3: Alfonso Videche Rrodriguez | D3: 45321 | E3: 4.Plan de pagos | F3: 1183693 | G3: 118393 | H3: 84600 | I3: -33793 | J3: -0.28543073 | K3: 1099093 | L3: 0.92852877 | M3: 118393

Sheet BOULEVARD 5
AT1: **Actualizar la columna AT meses sin pago | BB1: SI(Y(BA127="Vendido",G127>=0,BJ127<=AS127,AS127<AZ127),"Cliente al día",SI(Y(BA127="Vendido",G127>=0,BJ127<=AS127,AS127=AZ127),"Enganche Completado",SI(Y(BA127="Vendido",G127>=0,BJ127<AS127,AS127>AZ127),"Superávit de Enganche",SI(Y(BA127="Apartamento Disponible",G127=0,AV127=0),"Disponible","Cliente Atrasado")))))
B2: INMOBILIARIA EL GRAN JAGUAR, S.A.
B3: BOULEVARD 5 | D3: 46048 | AT3: 61140
B4: ="REPORTE DE RESERVAS Y COBROS AL "&UPPER(TEXT(_xlfn.XLOOKUP(D3,J6:AS6,J6:AS6),"dd mmmm yyyy")) -> #N/A | AT4: =+AT3-AT7 -> -1670
B5: 1 | C5: =B5+1 -> 2 | D5: =C5+1 -> 3 | E5: =D5+1 -> 4 | F5: =E5+1 -> 5 | G5: =F5+1 -> 6 | H5: =G5+1 -> 7 | I5: =H5+1 -> 8 | J5: =I5+1 -> 9 | ... AS5: =AR5+1 -> 44 | AU5: Enganche Completado | BF5: ** | BG5: ** | BH5: ** | BI5: ** | BY5: VALORES QUE DEBE ESCRITURARSE
B6: Apto. | C6: Tipo. | D6: Notas | E6: Vendedor | F6: Cliente | G6: Fecha Reserva | H6: Estatus | I6: Precio de Venta | J6: Enganche | K6: 45016 | L6: 45046 | M6: 45077 | N6: 45107 | O6: 45138 | P6: 45169 | Q6: 45199 | R6: 45230 | S6: 45260 | T6: 45291 | U6: 45322 | V6: 45351 | W6: 45382 | X6: 45412 | Y6: 45443 | Z6: 45473 | AA6: 45504 | AB6: 45535 | AC6: 45565 | AD6: 45596 | AE6: 45626 | AF6: 45657 | AG6: 45688 | AH6: 45716 | AI6: 45747 | AJ6: 45777 | AK6: 45808 | AL6: 45838 | AM6: 45869 | AN6: 45900 | AO6: 45930 | AP6: 45961 | AQ6: 45991 | AR6: 46022 | AS6: 46053 | AT6: TOTAL ENGANCHES Y RESERVAS | AU6: % COBROS | AV6: SALDO PENDIENTE ENGANCHE | AW6: % PENDIENTE COBRO | AX6: SALDO A FINANCIAR POR EL BANCO | AY6: % A FINANCIAR | AZ6: Proyección de Cobros (S/ Modelo Financiero) | BA6: Status inmueble | BB6: ESTATUS CLIENTE | BC6: Cuotas Pactadas | BD6: Cuota de Enganche | BE6: Total cuotas pactadas | BF6: Monto de Reserva Pactado | BG6: Monto de Cuota Pactada | BH6: Cuotas Pagadas | BI6: Cantidad de cuotas que deben estar pagadas por el cliente | BJ6: Monto que debe estar cancelado a la fecha | BK6: Monto pagado de cuotas a la fecha | BL6: Enganche + Cuotas Extraordinarias Pagadas | BM6: Diferencia | BN6: Cobro adicional a lo pactado | BO6: Cobro no realizado según lo pactado | BP6: Cuotas | BQ6: Caso Especial / F&F | BR6: Observaciones | BY6: BASE 70% | BZ6: BASE 30% | CA6: IVA | CB6: TIMBRES | CC6: VALOR FACTURA | CD6: ACCIONES | CE6: VALOR A ESCRITURARSE | CF6: DIF.
B7: 101 | C7: A7.1 | E7: Jose Franco | F7: Karla Michelle Abril Valencia De Galicia | G7: 45012 | H7: 4.Plan de pagos | I7: 644800 | J7: 64500 | K7: 6000 | L7: 1670 | M7: 1670 | N7: 1670 | O7: 1700 | P7: 1670 | Q7: 1670 | R7: 1670 | S7: 1670 | T7: 1670 | U7: 1670 | V7: 1670 | W7: 1670 | X7: 1670 | Y7: 1670 | Z7: 1670 | AA7: 1670 | AB7: 1670 | AC7: 1670 | AD7: 1670 | AE7: 1670 | AF7: 1670 | AG7: 1670 | AH7: 1670 | AI7: 1670 | AJ7: 1670 | AK7: 1670 | AL7: 1670 | AM7: 1670 | AN7: 1670 | AO7: 1670 | AP7: 1670 | AQ7: 1670 | AR7: 1670 | AS7: 1670 | AT7: =SUM(K7:AS7) -> 62810 | AU7: =IFERROR((+AT7/J7),0) -> 0.97379845 | AV7: =+AT7-AZ7 -> -1690 | AW7: =+AV7/J7 -> -0.02620155 | AX7: =+I7-AT7 -> 581990 | AY7: =+AX7/I7 -> 0.90258995 | AZ7: =IF(BA7="Vendido",J7*1,IF(BA7="Disponible",J7*0,IF(BA7="Enganche Completado",J7*1,IF(BA7="Superávit de Enganche",J7*1,0)))) -> 64500 | BA7: =IF(F7=0,"Disponible",IF(F7>1,"Vendido",0)) -> Vendido | BB7: =IF(AND(BA7="Vendido",G7>=0,BJ7<=AT7,AT7<AZ7),"Cliente al día",IF(AND(BA7="Vendido",G7>=0,BJ7<=AT7,AT7=AZ7),"Enganche Completado",IF(AND(BA7="Vendido",G7>=0,BJ7<AT7,AT7>AZ7),"Superávit de Enganche",IF(AND(BA7="Disponible",G7=0,AV7=0),"Disponible","Cliente Atrasado")))) -> Cliente al día | BC7: 35 | BD7: =IF(BC7>1,1,0) -> 1 | BE7: =+BC7+BD7 -> 36 | BF7: 6000 | BG7: 1670 | BH7: =COUNTIFS(K7:AS7,">0.01",K7:AS7,"<" & BF7) -> 34 | BI7: =IF($G7>0,DATEDIF($G7,$D$3,"M"),0) -> 33 | BJ7: =(BI7*BG7)+BF7 -> 61110 | BK7: =SUMIF(K7:AS7,"<=" & BG7,K7:AS7) -> 55110 | BL7: =SUMIF(K7:AS7,">" & BG7,K7:AS7) -> 7700 | BM7: =AT7-BK7-BL7 -> 0 | BN7: =IF(AT7>BJ7,AT7-BJ7,0) -> 1700 | BO7: =IF(AT7<BJ7,BJ7-AT7,0) -> 0 | BP7: =IFERROR(IF(AND(BQ7="F&F","CE"),"",ROUNDUP(IF(G7="",0,SUM(BO7/BG7)),0)),"") -> 0 | BT7: =+AT7-BJ7 -> 1700 | BU7: =+BN7-BO7 -> 1700 | BV7: =+BT7-BU7 -> 0 | BY7: =ROUND(I7/1.093*70%,3) -> 412955.17 | BZ7: =ROUND(I7/1.093*30%,3) -> 176980.79 | CA7: =ROUND(BY7*12%,2) -> 49554.62 | CB7: =ROUND(BZ7*3%,2) -> 5309.42 | CC7: =ROUND(BY7+CA7,2) -> 462509.79 | CD7: =ROUND(BZ7+CB7,2) -> 182290.21 | CE7: =ROUND(CC7+CD7,2) -> 644800 | CF7: =CE7-I7 -> 0
B8: 102 | C8: B4.1 | E8: Erwin Cardona | F8: Irma Leticia Villatoro Bucaro | G8: 46012 | H8: 2.Reserva | I8: 1154100 | J8: 80800 | K8: 0 | L8: 0 | M8: 0 | N8: 0 | O8: 0 | P8: 0 | Q8: 0 | R8: 0 | S8: 0 | T8: 0 | U8: 0 | V8: 0 | W8: 0 | X8: 0 | Y8: 0 | Z8: 0 | AA8: 0 | AB8: 0 | AC8: 0 | AD8: 0 | AE8: 0 | AF8: 0 | AG8: 0 | AH8: 0 | AI8: 0 | AJ8: 0 | AN8: 0 | AO8: 0 | AP8: 0 | AQ8: 0 | AR8: 9589.29 | AT8: =SUM(K8:AS8) -> 9589.29 | AU8: =IFERROR((+AT8/J8),0) -> 0.11867933 | AV8: =+AT8-AZ8 -> -71210.71 | AW8: =+AV8/J8 -> -0.88132067 | AX8: =+I8-AT8 -> 1144510.7 | AY8: =+AX8/I8 -> 0.99169111 | AZ8: =IF(BA8="Vendido",J8*1,IF(BA8="Disponible",J8*0,IF(BA8="Enganche Completado",J8*1,IF(BA8="Superávit de Enganche",J8*1,0)))) -> 80800 | BA8: =IF(F8=0,"Disponible",IF(F8>1,"Vendido",0)) -> Vendido | BB8: =IF(AND(BA8="Vendido",G8>=0,BJ8<=AT8,AT8<AZ8),"Cliente al día",IF(AND(BA8="Vendido",G8>=0,BJ8<=AT8,AT8=AZ8),"Enganche Completado",IF(AND(BA8="Vendido",G8>=0,BJ8<AT8,AT8>AZ8),"Superávit de Enganche",IF(AND(BA8="Disponible",G8=0,AV8=0),"Disponible","Cliente Atrasado")))) -> Cliente al día | BD8: =IF(BC8>1,1,0) -> 0 | BE8: =+BC8+BD8 -> 0 | BH8: =COUNTIFS(K8:AS8,">0.01",K8:AS8,"<" & BF8) -> 0 | BI8: =IF($G8>0,DATEDIF($G8,$D$3,"M"),0) -> 1 | BJ8: =(BI8*BG8)+BF8 -> 0 | BK8: =SUMIF(K8:AS8,"<=" & BG8,K8:AS8) -> 0 | BL8: =SUMIF(K8:AS8,">" & BG8,K8:AS8) -> 0 | BM8: =AT8-BK8-BL8 -> 9589.29 | BN8: =IF(AT8>BJ8,AT8-BJ8,0) -> 9589.29 | BO8: =IF(AT8<BJ8,BJ8-AT8,0) -> 0 | BP8: =IFERROR(IF(AND(BQ8="F&F","CE"),"",ROUNDUP(IF(G8="",0,SUM(BO8/BG8)),0)),"") | BT8: =+AT8-BJ8 -> 9589.29 | BU8: =+BN8-BO8 -> 9589.29 | BV8: =+BT8-BU8 -> 0 | BY8: =ROUND(I8/1.093*70%,3) -> 739130.83 | BZ8: =ROUND(I8/1.093*30%,3) -> 316770.36 | CA8: =ROUND(BY8*12%,2) -> 88695.7 | CB8: =ROUND(BZ8*3%,2) -> 9503.11 | CC8: =ROUND(BY8+CA8,2) -> 827826.53 | CD8: =ROUND(BZ8+CB8,2) -> 326273.47 | CE8: =ROUND(CC8+CD8,2) -> 1154100 | CF8: =CE8-I8 -> 0
A9: F&F | B9: 103 | C9: E1.1 | E9: Ronaldo | F9: International Coffee Industry, S.A | G9: 45300 | H9: 4.Plan de pagos | I9: 1533200 | J9: =+I9*0.1 -> 153320 | K9: 0 | L9: 0 | M9: 0 | N9: 0 | O9: 0 | P9: 0 | Q9: 0 | R9: 0 | S9: 0 | T9: 0 | U9: 0 | V9: 0 | W9: 0 | X9: 0 | Y9: 0 | Z9: 0 | AA9: 0 | AB9: 0 | AC9: 0 | AD9: 0 | AE9: 0 | AF9: 0 | AG9: 0 | AH9: 0 | AI9: 0 | AJ9: 0 | AN9: 0 | AO9: 0 | AP9: 0 | AQ9: 0 | AT9: =SUM(K9:AS9) -> 0 | AU9: =IFERROR((+AT9/J9),0) -> 0 | AV9: =+AT9-AZ9 -> -153320 | AW9: =+AV9/J9 -> -1 | AX9: =+I9-AT9 -> 1533200 | AY9: =+AX9/I9 -> 1 | AZ9: =IF(BA9="Vendido",J9*1,IF(BA9="Disponible",J9*0,IF(BA9="Enganche Completado",J9*1,IF(BA9="Superávit de Enganche",J9*1,0)))) -> 153320 | BA9: =IF(F9=0,"Disponible",IF(F9>1,"Vendido",0)) -> Vendido | BB9: =IF(AND(BA9="Vendido",G9>=0,BJ9<=AT9,AT9<AZ9),"Cliente al día",IF(AND(BA9="Vendido",G9>=0,BJ9<=AT9,AT9=AZ9),"Enganche Completado",IF(AND(BA9="Vendido",G9>=0,BJ9<AT9,AT9>AZ9),"Superávit de Enganche",IF(AND(BA9="Disponible",G9=0,AV9=0),"Disponible","Cliente Atrasado")))) -> Cliente Atrasado | BC9: 27 | BD9: =IF(BC9>1,1,0) -> 1 | BE9: =+BC9+BD9 -> 28 | BF9: 6000 | BG9: 5261 | BH9: =COUNTIFS(K9:AS9,">0.01",K9:AS9,"<" & BF9) -> 0 | BI9: =IF($G9>0,DATEDIF($G9,$D$3,"M"),0) -> 24 | BJ9: =(BI9*BG9)+BF9 -> 132264 | BK9: =SUMIF(K9:AS9,"<=" & BG9,K9:AS9) -> 0 | BL9: =SUMIF(K9:AS9,">" & BG9,K9:AS9) -> 0 | BM9: =AT9-BK9-BL9 -> 0 | BN9: =IF(AT9>BJ9,AT9-BJ9,0) -> 0 | BO9: =IF(AT9<BJ9,BJ9-AT9,0) -> 132264 | BP9: =IFERROR(IF(AND(BQ9="F&F","CE"),"",ROUNDUP(IF(G9="",0,SUM(BO9/BG9)),0)),"") | BQ9: F&F | BT9: =+AT9-BJ9 -> -132264 | BU9: =+BN9-BO9 -> -132264 | BV9: =+BT9-BU9 -> 0 | BY9: =ROUND(I9/1.093*70%,3) -> 981921.32 | BZ9: =ROUND(I9/1.093*30%,3) -> 420823.42 | CA9: =ROUND(BY9*12%,2) -> 117830.56 | CB9: =ROUND(BZ9*3%,2) -> 12624.7 | CC9: =ROUND(BY9+CA9,2) -> 1099751.9 | CD9: =ROUND(BZ9+CB9,2) -> 433448.12 | CE9: =ROUND(CC9+CD9,2) -> 1533200 | CF9: =CE9-I9 -> 0
B10: 104 | C10: A4.1 | E10: Antonio Rada | F10: Jonathan José Morales Salazar | G10: 45140 | H10: 4.Plan de pagos | I10: 727800 | J10: 145600 | K10: 0 | L10: 0 | M10: 0 | N10: 0 | O10: 0 | P10: 6000 | Q10: 94000 | R10: 1824 | S10: 1824 | T10: 1824 | U10: 1824 | V10: 1824 | W10: 1824 | X10: 1824 | Y10: 1824 | Z10: 1824 | AA10: 1824 | AB10: 1824 | AC10: 1824 | AD10: 1824 | AE10: 1824 | AF10: 1824 | AG10: 1824 | AH10: 1824 | AI10: 1824 | AJ10: 1824 | AK10: 1824 | AL10: 1824 | AM10: 1824 | AN10: 1824 | AO10: 1824 | AP10: 1824 | AQ10: 0 | AT10: =SUM(K10:AS10) -> 145600 | AU10: =IFERROR((+AT10/J10),0) -> 1 | AV10: =+AT10-AZ10 -> 0 | AW10: =+AV10/J10 -> 0 | AX10: =+I10-AT10 -> 582200 | AY10: =+AX10/I10 -> 0.79994504 | AZ10: =IF(BA10="Vendido",J10*1,IF(BA10="Disponible",J10*0,IF(BA10="Enganche Completado",J10*1,IF(BA10="Superávit de Enganche",J10*1,0)))) -> 145600 | BA10: =IF(F10=0,"Disponible",IF(F10>1,"Vendido",0)) -> Vendido | BB10: =IF(AND(BA10="Vendido",G10>=0,BJ10<=AT10,AT10<AZ10),"Cliente al día",IF(AND(BA10="Vendido",G10>=0,BJ10<=AT10,AT10=AZ10),"Enganche Completado",IF(AND(BA10="Vendido",G10>=0,BJ10<AT10,AT10>AZ10),"Superávit de Enganche",IF(AND(BA10="Disponible",G10=0,AV10=0),"Disponible","Cliente Atrasado")))) -> Cliente Atrasado | BC10: 25 | BD10: =IF(BC10>1,1,0) -> 1 | BE10: =+BC10+BD10 -> 26 | BF10: 100000 | BG10: 1824 | BH10: =COUNTIFS(K10:AS10,">0.01",K10:AS10,"<" & BF10) -> 27 | BI10: =IF($G10>0,DATEDIF($G10,$D$3,"M"),0) -> 29 | BJ10: =(BI10*BG10)+BF10 -> 152896 | BK10: =SUMIF(K10:AS10,"<=" & BG10,K10:AS10) -> 45600 | BL10: =SUMIF(K10:AS10,">" & BG10,K10:AS10) -> 100000 | BM10: =AT10-BK10-BL10 -> 0 | BN10: =IF(AT10>BJ10,AT10-BJ10,0) -> 0 | BO10: =IF(AT10<BJ10,BJ10-AT10,0) -> 7296 | BP10: =IFERROR(IF(AND(BQ10="F&F","CE"),"",ROUNDUP(IF(G10="",0,SUM(BO10/BG10)),0)),"") -> 4 | BR10: *Revisado, al finalizar del enganche pagará la cuota pendiente. | BT10: =+AT10-BJ10 -> -7296 | BU10: =+BN10-BO10 -> -7296 | BV10: =+BT10-BU10 -> 0 | BY10: =ROUND(I10/1.093*70%,3) -> 466111.62 | BZ10: =ROUND(I10/1.093*30%,3) -> 199762.12 | CA10: =ROUND(BY10*12%,2) -> 55933.39 | CB10: =ROUND(BZ10*3%,2) -> 5992.86 | CC10: =ROUND(BY10+CA10,2) -> 522045.01 | CD10: =ROUND(BZ10+CB10,2) -> 205754.98 | CE10: =ROUND(CC10+CD10,2) -> 727799.99 | CF10: =CE10-I10 -> -0.01
B11: 105 | C11: B7.1 | E11: Erwin Cardona | F11: Nery Adolfo Ortíz Alvarez | G11: 46000 | H11: 2.Reserva | I11: 1192700 | J11: 83500 | K11: 0 | L11: 0 | M11: 0 | N11: 0 | O11: 0 | P11: 0 | Q11: 0 | R11: 0 | S11: 0 | T11: 0 | U11: 0 | V11: 0 | W11: 0 | X11: 0 | Y11: 0 | Z11: 0 | AA11: 0 | AB11: 0 | AC11: 0 | AD11: 0 | AE11: 0 | AF11: 0 | AG11: 0 | AH11: 0 | AI11: 0 | AJ11: 0 | AN11: 0 | AO11: 0 | AP11: 0 | AQ11: 0 | AR11: 10000 | AT11: =SUM(K11:AS11) -> 10000 | AU11: =IFERROR((+AT11/J11),0) -> 0.11976048 | AV11: =+AT11-AZ11 -> -73500 | AW11: =+AV11/J11 -> -0.88023952 | AX11: =+I11-AT11 -> 1182700 | AY11: =+AX11/I11 -> 0.99161566 | AZ11: =IF(BA11="Vendido",J11*1,IF(BA11="Disponible",J11*0,IF(BA11="Enganche Completado",J11*1,IF(BA11="Superávit de Enganche",J11*1,0)))) -> 83500 | BA11: =IF(F11=0,"Disponible",IF(F11>1,"Vendido",0)) -> Vendido | BB11: =IF(AND(BA11="Vendido",G11>=0,BJ11<=AT11,AT11<AZ11),"Cliente al día",IF(AND(BA11="Vendido",G11>=0,BJ11<=AT11,AT11=AZ11),"Enganche Completado",IF(AND(BA11="Vendido",G11>=0,BJ11<AT11,AT11>AZ11),"Superávit de Enganche",IF(AND(BA11="Disponible",G11=0,AV11=0),"Disponible","Cliente Atrasado")))) -> Cliente al día | BD11: =IF(BC11>1,1,0) -> 0 | BE11: =+BC11+BD11 -> 0 | BH11: =COUNTIFS(K11:AS11,">0.01",K11:AS11,"<" & BF11) -> 0 | BI11: =IF($G11>0,DATEDIF($G11,$D$3,"M"),0) -> 1 | BJ11: =(BI11*BG11)+BF11 -> 0 | BK11: =SUMIF(K11:AS11,"<=" & BG11,K11:AS11) -> 0 | BL11: =SUMIF(K11:AS11,">" & BG11,K11:AS11) -> 0 | BM11: =AT11-BK11-BL11 -> 10000 | BN11: =IF(AT11>BJ11,AT11-BJ11,0) -> 10000 | BO11: =IF(AT11<BJ11,BJ11-AT11,0) -> 0 | BP11: =IFERROR(IF(AND(BQ11="F&F","CE"),"",ROUNDUP(IF(G11="",0,SUM(BO11/BG11)),0)),"") | BT11: =+AT11-BJ11 -> 10000 | BU11: =+BN11-BO11 -> 10000 | BV11: =+BT11-BU11 -> 0 | BY11: =ROUND(I11/1.093*70%,3) -> 763851.78 | BZ11: =ROUND(I11/1.093*30%,3) -> 327365.05 | CA11: =ROUND(BY11*12%,2) -> 91662.21 | CB11: =ROUND(BZ11*3%,2) -> 9820.95 | CC11: =ROUND(BY11+CA11,2) -> 855513.99 | CD11: =ROUND(BZ11+CB11,2) -> 337186 | CE11: =ROUND(CC11+CD11,2) -> 1192700 | CF11: =CE11-I11 -> -0.01
B12: 106 | C12: B2.1 | E12: Erwin Cardona | F12: Claudia Ruth Marianella Paiz Herrera de Alvarez | G12: 46013 | H12: 2.Reserva | I12: 1348900 | J12: 94400 | K12: 0 | L12: 0 | M12: 0 | N12: 0 | O12: 0 | P12: 0 | Q12: 0 | R12: 0 | S12: 0 | T12: 0 | U12: 0 | V12: 0 | W12: 0 | X12: 0 | Y12: 0 | Z12: 0 | AA12: 0 | AB12: 0 | AC12: 0 | AD12: 0 | AE12: 0 | AF12: 0 | AG12: 0 | AH12: 0 | AI12: 0 | AJ12: 0 | AN12: 0 | AO12: 0 | AP12: 0 | AQ12: 0 | AR12: 10000 | AS12: 14100 | AT12: =SUM(K12:AS12) -> 24100 | AU12: =IFERROR((+AT12/J12),0) -> 0.25529661 | AV12: =+AT12-AZ12 -> -70300 | AW12: =+AV12/J12 -> -0.74470339 | AX12: =+I12-AT12 -> 1324800 | AY12: =+AX12/I12 -> 0.98213359 | AZ12: =IF(BA12="Vendido",J12*1,IF(BA12="Disponible",J12*0,IF(BA12="Enganche Completado",J12*1,IF(BA12="Superávit de Enganche",J12*1,0)))) -> 94400 | BA12: =IF(F12=0,"Disponible",IF(F12>1,"Vendido",0)) -> Vendido | BB12: =IF(AND(BA12="Vendido",G12>=0,BJ12<=AT12,AT12<AZ12),"Cliente al día",IF(AND(BA12="Vendido",G12>=0,BJ12<=AT12,AT12=AZ12),"Enganche Completado",IF(AND(BA12="Vendido",G12>=0,BJ12<AT12,AT12>AZ12),"Superávit de Enganche",IF(AND(BA12="Disponible",G12=0,AV12=0),"Disponible","Cliente Atrasado")))) -> Cliente al día | BD12: =IF(BC12>1,1,0) -> 0 | BE12: =+BC12+BD12 -> 0 | BH12: =COUNTIFS(K12:AS12,">0.01",K12:AS12,"<" & BF12) -> 0 | BI12: =IF($G12>0,DATEDIF($G12,$D$3,"M"),0) -> 1 | BJ12: =(BI12*BG12)+BF12 -> 0 | BK12: =SUMIF(K12:AS12,"<=" & BG12,K12:AS12) -> 0 | BL12: =SUMIF(K12:AS12,">" & BG12,K12:AS12) -> 0 | BM12: =AT12-BK12-BL12 -> 24100 | BN12: =IF(AT12>BJ12,AT12-BJ12,0) -> 24100 | BO12: =IF(AT12<BJ12,BJ12-AT12,0) -> 0 | BP12: =IFERROR(IF(AND(BQ12="F&F","CE"),"",ROUNDUP(IF(G12="",0,SUM(BO12/BG12)),0)),"") | BT12: =+AT12-BJ12 -> 24100 | BU12: =+BN12-BO12 -> 24100 | BV12: =+BT12-BU12 -> 0 | BY12: =ROUND(I12/1.093*70%,3) -> 863888.38 | BZ12: =ROUND(I12/1.093*30%,3) -> 370237.88 | CA12: =ROUND(BY12*12%,2) -> 103666.61 | CB12: =ROUND(BZ12*3%,2) -> 11107.14 | CC12: =ROUND(BY12+CA12,2) -> 967554.99 | CD12: =ROUND(BZ12+CB12,2) -> 381345.02 | CE12: =ROUND(CC12+CD12,2) -> 1348900 | CF12: =CE12-I12 -> 0.01
B13: 107 | C13: B6.1 | H13: 1.Disponible | I13: 1135500 | J13: 79500 | K13: 0 | L13: 0 | M13: 0 | N13: 0 | O13: 0 | P13: 0 | Q13: 0 | R13: 0 | S13: 0 | T13: 0 | U13: 0 | V13: 0 | W13: 0 | X13: 0 | Y13: 0 | Z13: 0 | AA13: 0 | AB13: 0 | AC13: 0 | AD13: 0 | AE13: 0 | AF13: 0 | AG13: 0 | AH13: 0 | AI13: 0 | AJ13: 0 | AN13: 0 | AO13: 0 | AP13: 0 | AQ13: 0 | AT13: =SUM(K13:AS13) -> 0 | AU13: =IFERROR((+AT13/J13),0) -> 0 | AV13: =+AT13-AZ13 -> 0 | AW13: =+AV13/J13 -> 0 | AX13: =+I13-AT13 -> 1135500 | AY13: =+AX13/I13 -> 1 | AZ13: =IF(BA13="Vendido",J13*1,IF(BA13="Disponible",J13*0,IF(BA13="Enganche Completado",J13*1,IF(BA13="Superávit de Enganche",J13*1,0)))) -> 0 | BA13: =IF(F13=0,"Disponible",IF(F13>1,"Vendido",0)) -> Disponible | BB13: =IF(AND(BA13="Vendido",G13>=0,BJ13<=AT13,AT13<AZ13),"Cliente al día",IF(AND(BA13="Vendido",G13>=0,BJ13<=AT13,AT13=AZ13),"Enganche Completado",IF(AND(BA13="Vendido",G13>=0,BJ13<AT13,AT13>AZ13),"Superávit de Enganche",IF(AND(BA13="Disponible",G13=0,AV13=0),"Disponible","Cliente Atrasado")))) -> Disponible | BD13: =IF(BC13>1,1,0) -> 0 | BE13: =+BC13+BD13 -> 0 | BH13: =COUNTIFS(K13:AS13,">0.01",K13:AS13,"<" & BF13) -> 0 | BI13: =IF($G13>0,DATEDIF($G13,$D$3,"M"),0) -> 0 | BJ13: =(BI13*BG13)+BF13 -> 0 | BK13: =SUMIF(K13:AS13,"<=" & BG13,K13:AS13) -> 0 | BL13: =SUMIF(K13:AS13,">" & BG13,K13:AS13) -> 0 | BM13: =AT13-BK13-BL13 -> 0 | BN13: =IF(AT13>BJ13,AT13-BJ13,0) -> 0 | BO13: =IF(AT13<BJ13,BJ13-AT13,0) -> 0 | BP13: =IFERROR(IF(AND(BQ13="F&F","CE"),"",ROUNDUP(IF(G13="",0,SUM(BO13/BG13)),0)),"") -> 0 | BT13: =+AT13-BJ13 -> 0 | BU13: =+BN13-BO13 -> 0 | BV13: =+BT13-BU13 -> 0 | BY13: =ROUND(I13/1.093*70%,3) -> 727218.66 | BZ13: =ROUND(I13/1.093*30%,3) -> 311665.14 | CA13: =ROUND(BY13*12%,2) -> 87266.24 | CB13: =ROUND(BZ13*3%,2) -> 9349.95 | CC13: =ROUND(BY13+CA13,2) -> 814484.9 | CD13: =ROUND(BZ13+CB13,2) -> 321015.09 | CE13: =ROUND(CC13+CD13,2) -> 1135500 | CF13: =CE13-I13 -> -0.01
B14: 108 | C14: B1.1 | H14: 1.Disponible | I14: 1319300 | J14: 92400 | K14: 0 | L14: 0 | M14: 0 | N14: 0 | O14: 0 | P14: 0 | Q14: 0 | R14: 0 | S14: 0 | T14: 0 | U14: 0 | V14: 0 | W14: 0 | X14: 0 | Y14: 0 | Z14: 0 | AA14: 0 | AB14: 0 | AC14: 0 | AD14: 0 | AE14: 0 | AF14: 0 | AG14: 0 | AH14: 0 | AI14: 0 | AJ14: 0 | AN14: 0 | AO14: 0 | AP14: 0 | AQ14: 0 | AT14: =SUM(K14:AS14) -> 0 | AU14: =IFERROR((+AT14/J14),0) -> 0 | AV14: =+AT14-AZ14 -> 0 | AW14: =+AV14/J14 -> 0 | AX14: =+I14-AT14 -> 1319300 | AY14: =+AX14/I14 -> 1 | AZ14: =IF(BA14="Vendido",J14*1,IF(BA14="Disponible",J14*0,IF(BA14="Enganche Completado",J14*1,IF(BA14="Superávit de Enganche",J14*1,0)))) -> 0 | BA14: =IF(F14=0,"Disponible",IF(F14>1,"Vendido",0)) -> Disponible | BB14: =IF(AND(BA14="Vendido",G14>=0,BJ14<=AT14,AT14<AZ14),"Cliente al día",IF(AND(BA14="Vendido",G14>=0,BJ14<=AT14,AT14=AZ14),"Enganche Completado",IF(AND(BA14="Vendido",G14>=0,BJ14<AT14,AT14>AZ14),"Superávit de Enganche",IF(AND(BA14="Disponible",G14=0,AV14=0),"Disponible","Cliente Atrasado")))) -> Disponible | BD14: =IF(BC14>1,1,0) -> 0 | BE14: =+BC14+BD14 -> 0 | BH14: =COUNTIFS(K14:AS14,">0.01",K14:AS14,"<" & BF14) -> 0 | BI14: =IF($G14>0,DATEDIF($G14,$D$3,"M"),0) -> 0 | BJ14: =(BI14*BG14)+BF14 -> 0 | BK14: =SUMIF(K14:AS14,"<=" & BG14,K14:AS14) -> 0 | BL14: =SUMIF(K14:AS14,">" & BG14,K14:AS14) -> 0 | BM14: =AT14-BK14-BL14 -> 0 | BN14: =IF(AT14>BJ14,AT14-BJ14,0) -> 0 | BO14: =IF(AT14<BJ14,BJ14-AT14,0) -> 0 | BP14: =IFERROR(IF(AND(BQ14="F&F","CE"),"",ROUNDUP(IF(G14="",0,SUM(BO14/BG14)),0)),"") -> 0 | BT14: =+AT14-BJ14 -> 0 | BU14: =+BN14-BO14 -> 0 | BV14: =+BT14-BU14 -> 0 | BY14: =ROUND(I14/1.093*70%,3) -> 844931.38 | BZ14: =ROUND(I14/1.093*30%,3) -> 362113.45 | CA14: =ROUND(BY14*12%,2) -> 101391.77 | CB14: =ROUND(BZ14*3%,2) -> 10863.4 | CC14: =ROUND(BY14+CA14,2) -> 946323.15 | CD14: =ROUND(BZ14+CB14,2) -> 372976.85 | CE14: =ROUND(CC14+CD14,2) -> 1319300 | CF14: =CE14-I14 -> 0
B15: 109 | C15: E2.1 | E15: Antonio Rada | F15: Laura Elisa Ovalle Gonzalez | G15: 45471 | H15: 4.Plan de pagos | I15: 1486576 | J15: 148676 | K15: 0 | L15: 0 | M15: 0 | N15: 0 | O15: 0 | P15: 0 | Q15: 0 | R15: 0 | S15: 0 | T15: 0 | U15: 0 | V15: 0 | W15: 0 | X15: 0 | Y15: 0 | Z15: 5000 | AA15: 5000 | AB15: 7704 | AC15: 7704 | AD15: 7704 | AE15: 7704 | AF15: 7704 | AG15: 7704 | AH15: 7704 | AI15: 7704 | AJ15: 7704 | AK15: 7704 | AL15: 7704 | AM15: 7704 | AN15: 7704 | AO15: 7704 | AP15: 0 | AQ15: 7704 | AR15: =7704+7704 -> 15408 | AS15: 7704 | AT15: =SUM(K15:AS15) -> 148672 | AU15: =IFERROR((+AT15/J15),0) -> 0.9999731 | AV15: =+AT15-AZ15 -> -4 | AW15: =+AV15/J15 -> -2.6904141e-05 | AX15: =+I15-AT15 -> 1337904 | AY15: =+AX15/I15 -> 0.89999031 | AZ15: =IF(BA15="Vendido",J15*1,IF(BA15="Disponible",J15*0,IF(BA15="Enganche Completado",J15*1,IF(BA15="Superávit de Enganche",J15*1,0)))) -> 148676 | BA15: =IF(F15=0,"Disponible",IF(F15>1,"Vendido",0)) -> Vendido | BB15: =IF(AND(BA15="Vendido",G15>=0,BJ15<=AT15,AT15<AZ15),"Cliente al día",IF(AND(BA15="Vendido",G15>=0,BJ15<=AT15,AT15=AZ15),"Enganche Completado",IF(AND(BA15="Vendido",G15>=0,BJ15<AT15,AT15>AZ15),"Superávit de Enganche",IF(AND(BA15="Disponible",G15=0,AV15=0),"Disponible","Cliente Atrasado")))) -> Cliente al día | BC15: 18 | BD15: =IF(BC15>1,1,0) -> 1 | BE15: =+BC15+BD15 -> 19 | BF15: 10000 | BG15: 7704 | BH15: =COUNTIFS(K15:AS15,">0.01",K15:AS15,"<" & BF15) -> 18 | BI15: =IF($G15>0,DATEDIF($G15,$D$3,"M"),0) -> 18 | BJ15: =(BI15*BG15)+BF15 -> 148672 | BK15: =SUMIF(K15:AS15,"<=" & BG15,K15:AS15) -> 133264 | BL15: =SUMIF(K15:AS15,">" & BG15,K15:AS15) -> 15408 | BM15: =AT15-BK15-BL15 -> 0 | BN15: =IF(AT15>BJ15,AT15-BJ15,0) -> 0 | BO15: =IF(AT15<BJ15,BJ15-AT15,0) -> 0 | BP15: =IFERROR(IF(AND(BQ15="F&F","CE"),"",ROUNDUP(IF(G15="",0,SUM(BO15/BG15)),0)),"") -> 0 | BR15: *Revisado, al finalizar del enganche pagará la cuota pendiente. | BT15: =+AT15-BJ15 -> 0 | BU15: =+BN15-BO15 -> 0 | BV15: =+BT15-BU15 -> 0 | BY15: =ROUND(I15/1.093*70%,3) -> 952061.48 | BZ15: =ROUND(I15/1.093*30%,3) -> 408026.35 | CA15: =ROUND(BY15*12%,2) -> 114247.38 | CB15: =ROUND(BZ15*3%,2) -> 12240.79 | CC15: =ROUND(BY15+CA15,2) -> 1066308.9 | CD15: =ROUND(BZ15+CB15,2) -> 420267.14 | CE15: =ROUND(CC15+CD15,2) -> 1486576 | CF15: =CE15-I15 -> 0
B16: 110 | C16: A2.1 | E16: Antonio Rada | F16: Karla Suzel Ruiz Sanchinelli De Alonzo | G16: 45088 | H16: 4.Plan de pagos | I16: 680900 | J16: 68100 | K16: 0 | L16: 0 | M16: 0 | N16: 6000 | O16: 0 | P16: 2388 | Q16: 2388 | R16: 2388 | S16: 2388 | T16: 2388 | U16: 2388 | V16: 2388 | W16: 2388 | X16: 2388 | Y16: 2388 | Z16: 2388 | AA16: 2388 | AB16: 2388 | AC16: 2388 | AD16: 2388 | AE16: 2388 | AF16: 2388 | AG16: 2388 | AH16: 2388 | AI16: 2388 | AJ16: 2388 | AK16: 2388 | AL16: 2388 | AM16: 2388 | AN16: 2388 | AO16: 2388 | AP16: 2388 | AQ16: 2388 | AR16: 2388 | AT16: =SUM(K16:AS16) -> 75252 | AU16: =IFERROR((+AT16/J16),0) -> 1.105022 | AV16: =+AT16-AZ16 -> 7152 | AW16: =+AV16/J16 -> 0.10502203 | AX16: =+I16-AT16 -> 605648 | AY16: =+AX16/I16 -> 0.88948157 | AZ16: =IF(BA16="Vendido",J16*1,IF(BA16="Disponible",J16*0,IF(BA16="Enganche Completado",J16*1,IF(BA16="Superávit de Enganche",J16*1,0)))) -> 68100 | BA16: =IF(F16=0,"Disponible",IF(F16>1,"Vendido",0)) -> Vendido | BB16: =IF(AND(BA16="Vendido",G16>=0,BJ16<=AT16,AT16<AZ16),"Cliente al día",IF(AND(BA16="Vendido",G16>=0,BJ16<=AT16,AT16=AZ16),"Enganche Completado",IF(AND(BA16="Vendido",G16>=0,BJ16<AT16,AT16>AZ16),"Superávit de Enganche",IF(AND(BA16="Disponible",G16=0,AV16=0),"Disponible","Cliente Atrasado")))) -> Cliente Atrasado | BC16: 26 | BD16: =IF(BC16>1,1,0) -> 1 | BE16: =+BC16+BD16 -> 27 | BF16: 6000 | BG16: 2388 | BH16: =COUNTIFS(K16:AS16,">0.01",K16:AS16,"<" & BF16) -> 29 | BI16: =IF($G16>0,DATEDIF($G16,$D$3,"M"),0) -> 31 | BJ16: =(BI16*BG16)+BF16 -> 80028 | BK16: =SUMIF(K16:AS16,"<=" & BG16,K16:AS16) -> 69252 | BL16: =SUMIF(K16:AS16,">" & BG16,K16:AS16) -> 6000 | BM16: =AT16-BK16-BL16 -> 0 | BN16: =IF(AT16>BJ16,AT16-BJ16,0) -> 0 | BO16: =IF(AT16<BJ16,BJ16-AT16,0) -> 4776 | BP16: =IFERROR(IF(AND(BQ16="F&F","CE"),"",ROUNDUP(IF(G16="",0,SUM(BO16/BG16)),0)),"") -> 2 | BR16: *Revisado, al finalizar del enganche pagará la cuota pendiente. | BT16: =+AT16-BJ16 -> -4776 | BU16: =+BN16-BO16 -> -4776 | BV16: =+BT16-BU16 -> 0 | BY16: =ROUND(I16/1.093*70%,3) -> 436075.02 | BZ16: =ROUND(I16/1.093*30%,3) -> 186889.3 | CA16: =ROUND(BY16*12%,2) -> 52329 | CB16: =ROUND(BZ16*3%,2) -> 5606.68 | CC16: =ROUND(BY16+CA16,2) -> 488404.02 | CD16: =ROUND(BZ16+CB16,2) -> 192495.98 | CE16: =ROUND(CC16+CD16,2) -> 680900 | CF16: =CE16-I16 -> 0
B17: 111 | C17: A6.1 | E17: Jose Franco | F17: Jonathan José Morales Salazar / Ingrid Liseth Barillas López | G17: 45012 | H17: 4.Plan de pagos | I17: 696700 | J17: 69700 | K17: 6000 | L17: 0 | M17: 2820 | N17: 1820 | O17: 1820 | P17: 1820 | Q17: 1820 | R17: 1820 | S17: 1820 | T17: 1820 | U17: 1820 | V17: 1820 | W17: 1820 | X17: 1820 | Y17: 1820 | Z17: 1820 | AA17: 1820 | AB17: 1820 | AC17: 1820 | AD17: 1820 | AE17: 1820 | AF17: 1820 | AG17: 1820 | AH17: 1820 | AI17: 1820 | AJ17: 1820 | AK17: 1820 | AL17: 1820 | AM17: 1820 | AN17: 1820 | AO17: 1820 | AP17: 1820 | AQ17: 1820 | AR17: 1820 | AS17: 1820 | AT17: =SUM(K17:AS17) -> 67060 | AU17: =IFERROR((+AT17/J17),0) -> 0.96212339 | AV17: =+AT17-AZ17 -> -2640 | AW17: =+AV17/J17 -> -0.037876614 | AX17: =+I17-AT17 -> 629640 | AY17: =+AX17/I17 -> 0.90374623 | AZ17: =IF(BA17="Vendido",J17*1,IF(BA17="Disponible",J17*0,IF(BA17="Enganche Completado",J17*1,IF(BA17="Superávit de Enganche",J17*1,0)))) -> 69700 | BA17: =IF(F17=0,"Disponible",IF(F17>1,"Vendido",0)) -> Vendido | BB17: =IF(AND(BA17="Vendido",G17>=0,BJ17<=AT17,AT17<AZ17),"Cliente al día",IF(AND(BA17="Vendido",G17>=0,BJ17<=AT17,AT17=AZ17),"Enganche Completado",IF(AND(BA17="Vendido",G17>=0,BJ17<AT17,AT17>AZ17),"Superávit de Enganche",IF(AND(BA17="Disponible",G17=0,AV17=0),"Disponible","Cliente Atrasado")))) -> Cliente al día | BC17: 35 | BD17: =IF(BC17>1,1,0) -> 1 | BE17: =+BC17+BD17 -> 36 | BF17: 6000 | BG17: 1820 | BH17: =COUNTIFS(K17:AS17,">0.01",K17:AS17,"<" & BF17) -> 33 | BI17: =IF($G17>0,DATEDIF($G17,$D$3,"M"),0) -> 33 | BJ17: =(BI17*BG17)+BF17 -> 66060 | BK17: =SUMIF(K17:AS17,"<=" & BG17,K17:AS17) -> 58240 | BL17: =SUMIF(K17:AS17,">" & BG17,K17:AS17) -> 8820 | BM17: =AT17-BK17-BL17 -> 0 | BN17: =IF(AT17>BJ17,AT17-BJ17,0) -> 1000 | BO17: =IF(AT17<BJ17,BJ17-AT17,0) -> 0 | BP17: =IFERROR(IF(AND(BQ17="F&F","CE"),"",ROUNDUP(IF(G17="",0,SUM(BO17/BG17)),0)),"") -> 0 | BT17: =+AT17-BJ17 -> 1000 | BU17: =+BN17-BO17 -> 1000 | BV17: =+BT17-BU17 -> 0 | BY17: =ROUND(I17/1.093*70%,3) -> 446193.96 | BZ17: =ROUND(I17/1.093*30%,3) -> 191225.98 | CA17: =ROUND(BY17*12%,2) -> 53543.28 | CB17: =ROUND(BZ17*3%,2) -> 5736.78 | CC17: =ROUND(BY17+CA17,2) -> 499737.24 | CD17: =ROUND(BZ17+CB17,2) -> 196962.76 | CE17: =ROUND(CC17+CD17,2) -> 696700 | CF17: =CE17-I17 -> 0
B18: 112 | C18: A3.1 | E18: Brenda Búcaro | F18: Herbert Osiel Ramos Alfaro / Paula María Vásquez Cifuentes | G18: 45006 | H18: 4.Plan de pagos | I18: 698900 | J18: 69900 | K18: 6000 | L18: 1826 | M18: 1826 | N18: 1826 | O18: 1826 | P18: 1826 | Q18: 1826 | R18: 1826 | S18: 1826 | T18: 1826 | U18: 1826 | V18: 1826 | W18: 1826 | X18: 1826 | Y18: 1826 | Z18: 1826 | AA18: 1826 | AB18: 1826 | AC18: 1826 | AD18: 1826 | AE18: 1826 | AF18: 1826 | AG18: =1826+150 -> 1976 | AH18: =1676+1826 -> 3502 | AJ18: 1826 | AK18: 1826 | AL18: =1826+1826 -> 3652 | AN18: 1826 | AO18: 1826 | AP18: 1826 | AQ18: 1826 | AR18: 1826 | AS18: 1826 | AT18: =SUM(K18:AS18) -> 68084 | AU18: =IFERROR((+AT18/J18),0) -> 0.97402003 | AV18: =+AT18-AZ18 -> -1816 | AW18: =+AV18/J18 -> -0.025979971 | AX18: =+I18-AT18 -> 630816 | AY18: =+AX18/I18 -> 0.90258406 | AZ18: =IF(BA18="Vendido",J18*1,IF(BA18="Disponible",J18*0,IF(BA18="Enganche Completado",J18*1,IF(BA18="Superávit de Enganche",J18*1,0)))) -> 69900 | BA18: =IF(F18=0,"Disponible",IF(F18>1,"Vendido",0)) -> Vendido | BB18: =IF(AND(BA18="Vendido",G18>=0,BJ18<=AT18,AT18<AZ18),"Cliente al día",IF(AND(BA18="Vendido",G18>=0,BJ18<=AT18,AT18=AZ18),"Enganche Completado",IF(AND(BA18="Vendido",G18>=0,BJ18<AT18,AT18>AZ18),"Superávit de Enganche",IF(AND(BA18="Disponible",G18=0,AV18=0),"Disponible","Cliente Atrasado")))) -> Cliente al día | BC18: 35 | BD18: =IF(BC18>1,1,0) -> 1 | BE18: =+BC18+BD18 -> 36 | BF18: 6000 | BG18: 1826 | BH18: =COUNTIFS(K18:AS18,">0.01",K18:AS18,"<" & BF18) -> 32 | BI18: =IF($G18>0,DATEDIF($G18,$D$3,"M"),0) -> 34 | BJ18: =(BI18*BG18)+BF18 -> 68084 | BK18: =SUMIF(K18:AS18,"<=" & BG18,K18:AS18) -> 52954 | BL18: =SUMIF(K18:AS18,">" & BG18,K18:AS18) -> 15130 | BM18: =AT18-BK18-BL18 -> 0 | BN18: =IF(AT18>BJ18,AT18-BJ18,0) -> 0 | BO18: =IF(AT18<BJ18,BJ18-AT18,0) -> 0 | BP18: =IFERROR(IF(AND(BQ18="F&F","CE"),"",ROUNDUP(IF(G18="",0,SUM(BO18/BG18)),0)),"") -> 0 | BT18: =+AT18-BJ18 -> 0 | BU18: =+BN18-BO18 -> 0 | BV18: =+BT18-BU18 -> 0 | BY18: =ROUND(I18/1.093*70%,3) -> 447602.93 | BZ18: =ROUND(I18/1.093*30%,3) -> 191829.83 | CA18: =ROUND(BY18*12%,2) -> 53712.35 | CB18: =ROUND(BZ18*3%,2) -> 5754.89 | CC18: =ROUND(BY18+CA18,2) -> 501315.28 | CD18: =ROUND(BZ18+CB18,2) -> 197584.72 | CE18: =ROUND(CC18+CD18,2) -> 698900 | CF18: =CE18-I18 -> 0
B19: 113 | C19: C3.1 | D19: ENGANCHE CANCELADO | E19: Antonio Rada | F19: Rodrigo Rodas Pazos | G19: 45616 | H19: 4.Plan de pagos | I19: =922656.85+363649.19 -> 1286306 | J19: 480000 | K19: 0 | L19: 0 | M19: 0 | N19: 0 | O19: 0 | P19: 0 | Q19: 0 | R19: 0 | S19: 0 | T19: 0 | U19: 0 | V19: 0 | W19: 0 | X19: 0 | Y19: 0 | Z19: 0 | AA19: 0 | AB19: 0 | AC19: 0 | AD19: 0 | AE19: 10000 | AF19: =20000+450000 -> 470000 | AG19: 0 | AH19: 0 | AI19: 0 | AJ19: 0 | AN19: 0 | AO19: 0 | AP19: 0 | AQ19: 0 | AT19: =SUM(K19:AS19) -> 480000 | AU19: =IFERROR((+AT19/J19),0) -> 1 | AV19: =+AT19-AZ19 -> 0 | AW19: =+AV19/J19 -> 0 | AX19: =+I19-AT19 -> 806306.04 | AY19: =+AX19/I19 -> 0.62683842 | AZ19: =IF(BA19="Vendido",J19*1,IF(BA19="Disponible",J19*0,IF(BA19="Enganche Completado",J19*1,IF(BA19="Superávit de Enganche",J19*1,0)))) -> 480000 | BA19: =IF(F19=0,"Disponible",IF(F19>1,"Vendido",0)) -> Vendido | BB19: =IF(AND(BA19="Vendido",G19>=0,BJ19<=AT19,AT19<AZ19),"Cliente al día",IF(AND(BA19="Vendido",G19>=0,BJ19<=AT19,AT19=AZ19),"Enganche Completado",IF(AND(BA19="Vendido",G19>=0,BJ19<AT19,AT19>AZ19),"Superávit de Enganche",IF(AND(BA19="Disponible",G19=0,AV19=0),"Disponible","Cliente Atrasado")))) -> Cliente Atrasado | BC19: 1 | BD19: =IF(BC19>1,1,0) -> 0 | BE19: =+BC19+BD19 -> 1 | BF19: 10000 | BG19: 470000 | BH19: =COUNTIFS(K19:AS19,">0.01",K19:AS19,"<" & BF19) -> 0 | BI19: =IF($G19>0,DATEDIF($G19,$D$3,"M"),0) -> 14 | BJ19: =(BI19*BG19)+BF19 -> 6590000 | BK19: =SUMIF(K19:AS19,"<=" & BG19,K19:AS19) -> 480000 | BL19: =SUMIF(K19:AS19,">" & BG19,K19:AS19) -> 0 | BM19: =AT19-BK19-BL19 -> 0 | BN19: =IF(AT19>BJ19,AT19-BJ19,0) -> 0 | BO19: 0 | BP19: =IFERROR(IF(AND(BQ19="F&F","CE"),"",ROUNDUP(IF(G19="",0,SUM(BO19/BG19)),0)),"") -> 0 | BQ19: CE | BT19: =+AT19-BJ19 -> -6110000 | BU19: =+BN19-BO19 -> 0 | BV19: =+BT19-BU19 -> -6110000 | BY19: =ROUND(I19/1.093*70%,3) -> 823800.76 | BZ19: =ROUND(I19/1.093*30%,3) -> 353057.47 | CA19: =ROUND(BY19*12%,2) -> 98856.09 | CB19: =ROUND(BZ19*3%,2) -> 10591.72 | CC19: =ROUND(BY19+CA19,2) -> 922656.85 | CD19: =ROUND(BZ19+CB19,2) -> 363649.19 | CE19: =ROUND(CC19+CD19,2) -> 1286306 | CF19: =CE19-I19 -> 0
A20: F&F | B20: 114 | C20: C2.1 | E20: Antonio Rada | F20: Mauricio Arimany Monzon | G20: 45012 | H20: 4.Plan de pagos | I20: 993625.75 | J20: 99425.75 | K20: 6000 | L20: 2669 | M20: 2669 | N20: 2669 | O20: 2669 | P20: 2669 | Q20: 2669 | R20: 2669 | S20: 2669 | T20: 2669 | U20: 2669 | V20: 2669 | W20: 2669 | X20: 2669 | Y20: 2669 | Z20: 2669 | AA20: 2669 | AB20: 2669 | AC20: 5338 | AD20: 0 | AE20: 2669 | AF20: 2669 | AG20: 2669 | AH20: 0 | AI20: 0 | AJ20: 0 | AN20: 0 | AO20: 0 | AP20: 0 | AQ20: 0 | AT20: =SUM(K20:AS20) -> 64718 | AU20: =IFERROR((+AT20/J20),0) -> 0.6509179 | AV20: =+AT20-AZ20 -> -34707.75 | AW20: =+AV20/J20 -> -0.3490821 | AX20: =+I20-AT20 -> 928907.75 | AY20: =+AX20/I20 -> 0.93486682 | AZ20: =IF(BA20="Vendido",J20*1,IF(BA20="Disponible",J20*0,IF(BA20="Enganche Completado",J20*1,IF(BA20="Superávit de Enganche",J20*1,0)))) -> 99425.75 | BA20: =IF(F20=0,"Disponible",IF(F20>1,"Vendido",0)) -> Vendido | BB20: =IF(AND(BA20="Vendido",G20>=0,BJ20<=AT20,AT20<AZ20),"Cliente al día",IF(AND(BA20="Vendido",G20>=0,BJ20<=AT20,AT20=AZ20),"Enganche Completado",IF(AND(BA20="Vendido",G20>=0,BJ20<AT20,AT20>AZ20),"Superávit de Enganche",IF(AND(BA20="Disponible",G20=0,AV20=0),"Disponible","Cliente Atrasado")))) -> Cliente Atrasado | BC20: 35 | BD20: =IF(BC20>1,1,0) -> 1 | BE20: =+BC20+BD20 -> 36 | BF20: 6000 | BG20: 2669 | BH20: =COUNTIFS(K20:AS20,">0.01",K20:AS20,"<" & BF20) -> 21 | BI20: =IF($G20>0,DATEDIF($G20,$D$3,"M"),0) -> 33 | BJ20: =(BI20*BG20)+BF20 -> 94077 | BK20: =SUMIF(K20:AS20,"<=" & BG20,K20:AS20) -> 53380 | BL20: =SUMIF(K20:AS20,">" & BG20,K20:AS20) -> 11338 | BM20: =AT20-BK20-BL20 -> 0 | BN20: =IF(AT20>BJ20,AT20-BJ20,0) -> 0 | BO20: =IF(AT20<BJ20,BJ20-AT20,0) -> 29359 | BP20: =IFERROR(IF(AND(BQ20="F&F","CE"),"",ROUNDUP(IF(G20="",0,SUM(BO20/BG20)),0)),"") | BQ20: F&F | BT20: =+AT20-BJ20 -> -29359 | BU20: =+BN20-BO20 -> -29359 | BV20: =+BT20-BU20 -> 0 | BY20: =ROUND(I20/1.093*70%,3) -> 636356.84 | BZ20: =ROUND(I20/1.093*30%,3) -> 272724.36 | CA20: =ROUND(BY20*12%,2) -> 76362.82 | CB20: =ROUND(BZ20*3%,2) -> 8181.73 | CC20: =ROUND(BY20+CA20,2) -> 712719.66 | CD20: =ROUND(BZ20+CB20,2) -> 280906.09 | CE20: =ROUND(CC20+CD20,2) -> 993625.75 | CF20: =CE20-I20 -> 0.00332
B21: 201 | C21: B7 | H21: 1.Disponible | I21: 1295000 | J21: 90700 | K21: 0 | L21: 0 | M21: 0 | N21: 0 | O21: 0 | P21: 0 | Q21: 0 | R21: 0 | S21: 0 | T21: 0 | U21: 0 | V21: 0 | W21: 0 | X21: 0 | Y21: 0 | Z21: 0 | AA21: 0 | AB21: 0 | AC21: 0 | AD21: 0 | AE21: 0 | AF21: 0 | AG21: 0 | AH21: 0 | AI21: 0 | AJ21: 0 | AN21: 0 | AO21: 0 | AP21: 0 | AQ21: 0 | AT21: =SUM(K21:AS21) -> 0 | AU21: =IFERROR((+AT21/J21),0) -> 0 | AV21: =+AT21-AZ21 -> 0 | AW21: =+AV21/J21 -> 0 | AX21: =+I21-AT21 -> 1295000 | AY21: =+AX21/I21 -> 1 | AZ21: =IF(BA21="Vendido",J21*1,IF(BA21="Disponible",J21*0,IF(BA21="Enganche Completado",J21*1,IF(BA21="Superávit de Enganche",J21*1,0)))) -> 0 | BA21: =IF(F21=0,"Disponible",IF(F21>1,"Vendido",0)) -> Disponible | BB21: =IF(AND(BA21="Vendido",G21>=0,BJ21<=AT21,AT21<AZ21),"Cliente al día",IF(AND(BA21="Vendido",G21>=0,BJ21<=AT21,AT21=AZ21),"Enganche Completado",IF(AND(BA21="Vendido",G21>=0,BJ21<AT21,AT21>AZ21),"Superávit de Enganche",IF(AND(BA21="Disponible",G21=0,AV21=0),"Disponible","Cliente Atrasado")))) -> Disponible | BD21: =IF(BC21>1,1,0) -> 0 | BE21: =+BC21+BD21 -> 0 | BH21: =COUNTIFS(K21:AS21,">0.01",K21:AS21,"<" & BF21) -> 0 | BI21: =IF($G21>0,DATEDIF($G21,$D$3,"M"),0) -> 0 | BJ21: =(BI21*BG21)+BF21 -> 0 | BK21: =SUMIF(K21:AS21,"<=" & BG21,K21:AS21) -> 0 | BL21: =SUMIF(K21:AS21,">" & BG21,K21:AS21) -> 0 | BM21: =AT21-BK21-BL21 -> 0 | BN21: =IF(AT21>BJ21,AT21-BJ21,0) -> 0 | BO21: =IF(AT21<BJ21,BJ21-AT21,0) -> 0 | BP21: =IFERROR(IF(AND(BQ21="F&F","CE"),"",ROUNDUP(IF(G21="",0,SUM(BO21/BG21)),0)),"") -> 0 | BT21: =+AT21-BJ21 -> 0 | BU21: =+BN21-BO21 -> 0 | BV21: =+BT21-BU21 -> 0 | BY21: =ROUND(I21/1.093*70%,3) -> 829368.71 | BZ21: =ROUND(I21/1.093*30%,3) -> 355443.73 | CA21: =ROUND(BY21*12%,2) -> 99524.25 | CB21: =ROUND(BZ21*3%,2) -> 10663.31 | CC21: =ROUND(BY21+CA21,2) -> 928892.96 | CD21: =ROUND(BZ21+CB21,2) -> 366107.04 | CE21: =ROUND(CC21+CD21,2) -> 1295000 | CF21: =CE21-I21 -> 0
B22: 202 | C22: B2 | E22: Antonio Rada | F22: Bella Rosana Chaveque Gonzalez | G22: 45736 | H22: 4.Plan de pagos | I22: 1321630.2 | J22: 132230.19 | K22: 0 | L22: 0 | M22: 0 | N22: 0 | O22: 0 | P22: 0 | Q22: 0 | R22: 0 | S22: 0 | T22: 0 | U22: 0 | V22: 0 | W22: 0 | X22: 0 | Y22: 0 | Z22: 0 | AA22: 0 | AB22: 0 | AC22: 0 | AD22: 0 | AE22: 0 | AF22: 0 | AG22: 0 | AH22: 0 | AI22: 10000 | AJ22: 10000 | AK22: 10000 | AL22: 8500 | AM22: 10000 | AN22: 8000 | AO22: 8000 | AP22: 8000 | AQ22: 8500 | AR22: 10000 | AS22: 9000 | AT22: =SUM(K22:AS22) -> 100000 | AU22: =IFERROR((+AT22/J22),0) -> 0.75625695 | AV22: =+AT22-AZ22 -> -32230.19 | AW22: =+AV22/J22 -> -0.24374305 | AX22: =+I22-AT22 -> 1221630.2 | AY22: =+AX22/I22 -> 0.92433587 | AZ22: =IF(BA22="Vendido",J22*1,IF(BA22="Disponible",J22*0,IF(BA22="Enganche Completado",J22*1,IF(BA22="Superávit de Enganche",J22*1,0)))) -> 132230.19 | BA22: =IF(F22=0,"Disponible",IF(F22>1,"Vendido",0)) -> Vendido | BB22: =IF(AND(BA22="Vendido",G22>=0,BJ22<=AT22,AT22<AZ22),"Cliente al día",IF(AND(BA22="Vendido",G22>=0,BJ22<=AT22,AT22=AZ22),"Enganche Completado",IF(AND(BA22="Vendido",G22>=0,BJ22<AT22,AT22>AZ22),"Superávit de Enganche",IF(AND(BA22="Disponible",G22=0,AV22=0),"Disponible","Cliente Atrasado")))) -> Cliente al día | BC22: 14 | BD22: =IF(BC22>1,1,0) -> 1 | BE22: =+BC22+BD22 -> 15 | BF22: 10000 | BG22: 8731 | BH22: =COUNTIFS(K22:AS22,">0.01",K22:AS22,"<" & BF22) -> 6 | BI22: =IF($G22>0,DATEDIF($G22,$D$3,"M"),0) -> 10 | BJ22: =(BI22*BG22)+BF22 -> 97310 | BK22: =SUMIF(K22:AS22,"<=" & BG22,K22:AS22) -> 41000 | BL22: =SUMIF(K22:AS22,">" & BG22,K22:AS22) -> 59000 | BM22: =AT22-BK22-BL22 -> 0 | BN22: =IF(AT22>BJ22,AT22-BJ22,0) -> 2690 | BO22: =IF(AT22<BJ22,BJ22-AT22,0) -> 0 | BP22: =IFERROR(IF(AND(BQ22="F&F","CE"),"",ROUNDUP(IF(G22="",0,SUM(BO22/BG22)),0)),"") -> 0 | BT22: =+AT22-BJ22 -> 2690 | BU22: =+BN22-BO22 -> 2690 | BV22: =+BT22-BU22 -> 0 | BY22: =ROUND(I22/1.093*70%,3) -> 846423.73 | BZ22: =ROUND(I22/1.093*30%,3) -> 362753.03 | CA22: =ROUND(BY22*12%,2) -> 101570.85 | CB22: =ROUND(BZ22*3%,2) -> 10882.59 | CC22: =ROUND(BY22+CA22,2) -> 947994.58 | CD22: =ROUND(BZ22+CB22,2) -> 373635.62 | CE22: =ROUND(CC22+CD22,2) -> 1321630.2 | CF22: =CE22-I22 -> 0.01124205
